Workbook
Name UPDATE: 'Data Sheet'!$E$1

Sheet Cover
E4: Equity Research Report
E9: ='Assumptions&Scenario'!K10
B10: https://sudhirkulaye.com | E10: ='Assumptions&Scenario'!U10
I15: Author:
I16: Sudhir Kulaye, CFA

Sheet Assumptions&Scenario
B3: =$K$10
B4: Standalone Assumptions
C6: Standalone Assumptions | Y6: Guidance
D10: Short Name | K10: ='Data Sheet'!B1 | P10: Last Update | U10: =TODAY() | Y10: Terminal EBIT Margin | AC10: =IFERROR(HistoricalData!AH333, HistoricalData!AH375)
D11: Ticker | K11: {=_xlfn.TEXTJOIN("", TRUE, LEFT(TRIM(MID(SUBSTITUTE(K10, " ", REPT(" ", 100)), (ROW(INDIRECT("1:" & LEN(K10) - LEN(SUBSTITUTE(K10, " ", ""))) )-1)*100+1, 100)), 1))} | P11: Is Financial | U11: No | Y11: Terminal After Tax Return on Capital | AC11: =IFERROR(HistoricalData!U562, U19)
D13: Terminal Growth | P13: Discount Rate | Y13: Industry Sales to Capital | AC13: =HistoricalData!U559
D14: Second Stage Period | K14: 10 | P14: Debt Portion | U14: =HistoricalData!U645 | Y14: Debt Portion | AC14: =HistoricalData!U645
D15: Second Stage Growth Rate | K15: 0.1 | P15: Equity Portion | U15: =1-U14 | Y15: Risk Free Rate | AC15: 0.065 | AD15: (10-Year G-Sec yield)
D16: Terminal Growth Beyond Second Stage | K16: 0.05 | P16: Cost of Debt | U16: =AC17 | Y16: Bond Ratings | AC16: AAA
D17: Adjusted Terminal Growth Rate | K17: =K16+(K15-K16)*(K14/40) | P17: Tax Rate | U17: 0.25 | Y17: Cost of Debt | AC17: =AC15 + CHOOSE(MATCH(AC16, {"AAA","AA","A","BBB","BB or Lower"}, 0), 2%, 3%, 4.5%, 6%, 8%) | AD17: (Inhouse Calculation)
D18: Terminal EBIT Margin | K18: =IFERROR(HistoricalData!AH333, HistoricalData!AH375) | P18: Cost of Equity | U18: =AC21 | Y18: NIFTY 10 Yr Return | AC18: 0.123
D19: Terminal After Tax Return on Capital | K19: =IFERROR(HistoricalData!U562, U19) | P19: WACC% | U19: =U14*U16*(1-U17)+U15*U18 | Y19: ERP | AC19: =AC18-AC15
D20: Terminal After Tax Return on Equity | K20: =IFERROR(HistoricalData!U564, U20) | P20: Fwd. Market Multiple (x) | U20: 19.5 | Y20: Beta | AC20: 1 | AD20: Update Beta
D21: Terminal Reinvestment Rate | K21: =K17/K19 | P21: Premium / Discount to Market Multiple | U21: =AC23 | Y21: Cost of Equity | AC21: =AC15+AC20*AC19
D22: Industry Sales to Capital | K22: =HistoricalData!U559 | P22: Other Adjustment for ESOP & Contingent Liability | U22: 0 | Y22: Stock Type | AC22: Quality compounder
Y23: Premium / Discount to Market Multiple | AC23: =CHOOSE(MATCH(AC22, {"High-growth","Quality compounder","Market average","Slow-growth","Troubled/distressed"}, 0), 50%, 30%, 0%, -25%, -50%)
D24: Variable Cost Per Unit | P24: Fixed Cost
K25: =L88 | L25: Inflation Y1 | M25: Inflation Y2 | S25: =L88 | T25: Inflation Y1 | U25: Inflation Y2
D26: Raw Material | I26: ( ₹ ) | K26: =HistoricalData!U199*(1+L26) | L26: =IFERROR(HistoricalData!Y199/HistoricalData!U199-1, 0) | M26: =IFERROR(HistoricalData!Z199/HistoricalData!Y199-1, 0) | P26: Employee Cost | R26: (₹ crore) | S26: =HistoricalData!U189*(1+T26) | T26: =IFERROR(HistoricalData!Y189/HistoricalData!U189-1, 0) | U26: =IFERROR(HistoricalData!Z189/HistoricalData!Y189-1, 0)
D27: Power and Fuel | I27: ( ₹ ) | K27: =HistoricalData!U200*(1+L27) | L27: =IFERROR(HistoricalData!Y200/HistoricalData!U200-1, 0) | M27: =IFERROR(HistoricalData!Z200/HistoricalData!Y200-1, 0) | P27: Fixed Cost Iteam 2 | R27: (₹ crore) | S27: =HistoricalData!U190*(1+T27) | T27: =IFERROR(HistoricalData!Y190/HistoricalData!U190-1, 0) | U27: =IFERROR(HistoricalData!Z190/HistoricalData!Y190-1, 0)
D28: Other Mfr. Exp | I28: ( ₹ ) | K28: =HistoricalData!U201*(1+L28) | L28: =IFERROR(HistoricalData!Y201/HistoricalData!U201-1, 0) | M28: =IFERROR(HistoricalData!Z201/HistoricalData!Y201-1, 0) | P28: Fixed Cost Iteam 3 | R28: (₹ crore) | S28: =HistoricalData!U191*(1+T28) | T28: =IFERROR(HistoricalData!Y191/HistoricalData!U191-1, 0) | U28: =IFERROR(HistoricalData!Z191/HistoricalData!Y191-1, 0)
D29: Variable Cost Iteam 4 | I29: ( ₹ ) | K29: =HistoricalData!U202*(1+L29) | L29: =IFERROR(HistoricalData!Y202/HistoricalData!U202-1, 0) | M29: =IFERROR(HistoricalData!Z202/HistoricalData!Y202-1, 0) | P29: Selling and Admin | R29: (₹ crore) | S29: =HistoricalData!U192*(1+T29) | T29: =IFERROR(HistoricalData!Y192/HistoricalData!U192-1, 0) | U29: =IFERROR(HistoricalData!Z192/HistoricalData!Y192-1, 0)
D30: Other Variable Cost | I30: ( ₹ ) | K30: =HistoricalData!U203*(1+L30) | L30: =IFERROR(HistoricalData!Y203/HistoricalData!U203-1, 0) | M30: =IFERROR(HistoricalData!Z203/HistoricalData!Y203-1, 0) | P30: Other Fixed Cost | R30: (₹ crore) | S30: =HistoricalData!U193*(1+T30) | T30: =IFERROR(HistoricalData!Y193/HistoricalData!U193-1, 0) | U30: =IFERROR(HistoricalData!Z193/HistoricalData!Y193-1, 0)
D31: Total Variable Cost | I31: ( ₹ ) | K31: =HistoricalData!U204*(1+L31) | L31: =IFERROR(HistoricalData!Y204/HistoricalData!U204-1, 0) | M31: =IFERROR(HistoricalData!Z204/HistoricalData!Y204-1, 0) | P31: Total Fixed Cost | R31: (₹ crore) | S31: =HistoricalData!U194*(1+T31) | T31: =IFERROR(HistoricalData!Y194/HistoricalData!U194-1, 0) | U31: =IFERROR(HistoricalData!Z194/HistoricalData!Y194-1, 0)
D34: Interest Rates | P34: Depreciation | Y34: Interest Rates Guidance
D35: Interest earned on Investments: | K35: =IFERROR(HistoricalData!U629, 7%) | P35: Depreciation Method | U35: Stright Line | Y35: Interest earned on Investments: | AC35: =IFERROR(HistoricalData!U629, 7%)
D36: Interest rate on Bank Revolver: | K36: =IFERROR(HistoricalData!$U$639, 9.5%) | P36: Years remaining for depreciation of existing assets: | U36: =HistoricalData!$U$560 | Y36: Interest rate on Bank Revolver: | AC36: =IFERROR(HistoricalData!$U$639, 9.5%)
D37: Interest rate on Senior Secured Term Debt: | K37: =IFERROR(HistoricalData!$U$639, 9.5%) | P37: Years used for depreciation of new assets: | U37: =HistoricalData!$U$560 | Y37: Interest rate on Senior Secured Term Debt: | AC37: =IFERROR(HistoricalData!$U$639, 9.5%)
D40: Capacity | K40: =L88 | P40: Equity
D41: Capacity | K41: =HistoricalData!AH37 | P41: Stock Price | U41: =HistoricalData!U394
D42: Unit of Capacity | K42: (Units) | P42: No. of outstanding shares in Crores | U42: =HistoricalData!U391
D43: Capacity Multiplier For Revenue in Cr. | K43: 1 | P43: Common Dividend Payout Rate | U43: =IFERROR(AVERAGE(HistoricalData!T653:U653), 0)
D44: Capacity Per Unit | K44: (₹/Unit) | P44: Materiality Threshold | U44: 0.05
P45: Requied CAR Ratio | U45: 0.12
B49: =$K$10
B50: Annual Inputs and Assumptions
L51: Projected
C52: FIN Years | K52: ="FY"&TEXT(DATE(YEAR('Data Sheet'!K16)+(MONTH('Data Sheet'!K16)>3),1,1),"YY") | L52: ="FY"&TEXT(RIGHT(K52,2)+COLUMN()-COLUMN(K52),"00") | M52: ="FY"&TEXT(RIGHT(L52,2)+COLUMN()-COLUMN(L52),"00") | N52: ="FY"&TEXT(RIGHT(M52,2)+COLUMN()-COLUMN(M52),"00") | O52: ="FY"&TEXT(RIGHT(N52,2)+COLUMN()-COLUMN(N52),"00") | P52: ="FY"&TEXT(RIGHT(O52,2)+COLUMN()-COLUMN(O52),"00") | Q52: ="FY"&TEXT(RIGHT(P52,2)+COLUMN()-COLUMN(P52),"00") | R52: ="FY"&TEXT(RIGHT(Q52,2)+COLUMN()-COLUMN(Q52),"00") | S52: ="FY"&TEXT(RIGHT(R52,2)+COLUMN()-COLUMN(R52),"00") | ... U52: ="FY"&TEXT(RIGHT(T52,2)+COLUMN()-COLUMN(T52),"00")
C56: Income Statement
D57: Exceptional item | H57: (₹ crore) | L57: 0 | M57: 0 | N57: 0 | O57: 0 | P57: 0 | Q57: 0 | R57: 0 | S57: 0 | T57: 0 | U57: 0
C59: Cash Flow Statement
D60: Other Investing Activities | H60: (₹ crore) | L60: 0 | M60: 0 | N60: 0 | O60: 0 | P60: 0 | Q60: 0 | R60: 0 | S60: 0 | T60: 0 | U60: 0
C62: Capital Expenditures | H62: (₹ crore) | L62: =-HistoricalData!Y421 | M62: =-HistoricalData!Z421 | N62: =-HistoricalData!AA421 | O62: =-HistoricalData!AB421 | P62: =-HistoricalData!AC421 | Q62: =-HistoricalData!AD421 | R62: =-HistoricalData!AE421 | S62: =-HistoricalData!AF421 | ... U62: =-HistoricalData!AH421
C64: Income Tax
D65: Reduction in EBT | H65: (₹ crore) | L65: =IFERROR(IF(HistoricalData!Y571>0, HistoricalData!Y568/HistoricalData!Y570, (HistoricalData!Y336*10%)), 0) | M65: =IFERROR(IF(HistoricalData!Z571>0, HistoricalData!Z568/HistoricalData!Z570, (HistoricalData!Z336*10%)), 0) | N65: =IFERROR(IF(HistoricalData!AA571>0, HistoricalData!AA568/HistoricalData!AA570, (HistoricalData!AA336*10%)), 0) | O65: =IFERROR(IF(HistoricalData!AB571>0, HistoricalData!AB568/HistoricalData!AB570, (HistoricalData!AB336*10%)), 0) | P65: =IFERROR(IF(HistoricalData!AC571>0, HistoricalData!AC568/HistoricalData!AC570, (HistoricalData!AC336*10%)), 0) | Q65: =IFERROR(IF(HistoricalData!AD571>0, HistoricalData!AD568/HistoricalData!AD570, (HistoricalData!AD336*10%)), 0) | R65: =IFERROR(IF(HistoricalData!AE571>0, HistoricalData!AE568/HistoricalData!AE570, (HistoricalData!AE336*10%)), 0) | S65: =IFERROR(IF(HistoricalData!AF571>0, HistoricalData!AF568/HistoricalData!AF570, (HistoricalData!AF336*10%)), 0) | ... U65: =IFERROR(IF(HistoricalData!AH571>0, HistoricalData!AH568/HistoricalData!AH570, (HistoricalData!AH336*10%)), 0)
D66: (for timing differences)
C68: Working Capital Days
D69: Accounts Receivable | H69: days | L69: =HistoricalData!Y599 | M69: =HistoricalData!Z599 | N69: =M69 | O69: =N69 | P69: =O69 | Q69: =P69 | R69: =Q69 | S69: =R69 | T69: =S69 | U69: =T69
D70: Inventories | H70: days | L70: =HistoricalData!Y600 | M70: =HistoricalData!Z600 | N70: =M70 | O70: =N70 | P70: =O70 | Q70: =P70 | R70: =Q70 | S70: =R70 | T70: =S70 | U70: =T70
D71: Prepaid Expenses | H71: days | L71: =HistoricalData!Y601 | M71: =HistoricalData!Z601 | N71: =M71 | O71: =N71 | P71: =O71 | Q71: =P71 | R71: =Q71 | S71: =R71 | T71: =S71 | U71: =T71
D72: Other Assets | H72: days | L72: =HistoricalData!Y602 | M72: =HistoricalData!Z602 | N72: =M72 | O72: =N72 | P72: =O72 | Q72: =P72 | R72: =Q72 | S72: =R72 | T72: =S72 | U72: =T72
D73: Accounts Payable | H73: days | L73: =HistoricalData!Y603 | M73: =HistoricalData!Z603 | N73: =M73 | O73: =N73 | P73: =O73 | Q73: =P73 | R73: =Q73 | S73: =R73 | T73: =S73 | U73: =T73
D74: Other Liabilities | H74: days | L74: =HistoricalData!Y604 | M74: =HistoricalData!Z604 | N74: =M74 | O74: =N74 | P74: =O74 | Q74: =P74 | R74: =Q74 | S74: =R74 | T74: =S74 | U74: =T74
C76: Change in Debt & Equity
D77: Senior Debt Issuance | H77: (₹ crore)
D78: / (Repayment)
D79: Common Stock Issuance | H79: (₹ crore) | L79: 0 | M79: 0 | N79: 0 | O79: 0 | P79: 0 | Q79: 0 | R79: 0 | S79: 0 | T79: 0 | U79: 0
D80: / (Buy-back)
D81: Face Value | H81: ( ₹ ) | L81: 1 | M81: 1 | N81: 1 | O81: 1 | P81: 1 | Q81: 1 | R81: 1 | S81: 1 | T81: 1 | U81: 1
B85: =$K$10
B86: Annaul Economic and Sales Scenarios
L87: Projected
C88: SCENARIO SWITCH: | H88: 1 | K88: ="FY"&TEXT(DATE(YEAR('Data Sheet'!K16)+(MONTH('Data Sheet'!K16)>3),1,1),"YY") | L88: ="FY"&TEXT(RIGHT(K88,2)+COLUMN()-COLUMN(K88),"00") | M88: ="FY"&TEXT(RIGHT(L88,2)+COLUMN()-COLUMN(L88),"00") | N88: ="FY"&TEXT(RIGHT(M88,2)+COLUMN()-COLUMN(M88),"00") | O88: ="FY"&TEXT(RIGHT(N88,2)+COLUMN()-COLUMN(N88),"00") | P88: ="FY"&TEXT(RIGHT(O88,2)+COLUMN()-COLUMN(O88),"00") | Q88: ="FY"&TEXT(RIGHT(P88,2)+COLUMN()-COLUMN(P88),"00") | R88: ="FY"&TEXT(RIGHT(Q88,2)+COLUMN()-COLUMN(Q88),"00") | S88: ="FY"&TEXT(RIGHT(R88,2)+COLUMN()-COLUMN(R88),"00") | ... U88: ="FY"&TEXT(RIGHT(T88,2)+COLUMN()-COLUMN(T88),"00")
C92: ECONOMIC SCENARIOS
C94: Variable Cost Inflation | H94: (Sensitive to Row Material) | L94: {=INDEX(L96:L98,$H$88)} | M94: {=INDEX(M96:M98,$H$88)} | N94: {=INDEX(N96:N98,$H$88)} | O94: {=INDEX(O96:O98,$H$88)} | P94: {=INDEX(P96:P98,$H$88)} | Q94: {=INDEX(Q96:Q98,$H$88)} | R94: {=INDEX(R96:R98,$H$88)} | S94: {=INDEX(S96:S98,$H$88)} | ... U94: {=INDEX(U96:U98,$H$88)}
D96: Base Case | L96: =L31 | M96: =M31 | N96: =HistoricalData!AA288 | O96: =HistoricalData!AB288 | P96: =HistoricalData!AC288 | Q96: =HistoricalData!AD288 | R96: =HistoricalData!AE288 | S96: =HistoricalData!AF288 | T96: =HistoricalData!AG288 | U96: =HistoricalData!AH288
A97: -0.005 | D97: ="Best Case ("&TEXT(A97*100,"0.00")&"%)" | L97: =L$96+$A97 | M97: =M$96+$A97 | N97: =N$96+$A97 | O97: =O$96+$A97 | P97: =P$96+$A97 | Q97: =Q$96+$A97 | R97: =R$96+$A97 | S97: =S$96+$A97 | ... U97: =U$96+$A97
A98: 0.005 | D98: ="Worst Case ("&TEXT(A98*100,"0.00")&"%)" | L98: =L$96+$A98 | M98: =M$96+$A98 | N98: =N$96+$A98 | O98: =O$96+$A98 | P98: =P$96+$A98 | Q98: =Q$96+$A98 | R98: =R$96+$A98 | S98: =S$96+$A98 | ... U98: =U$96+$A98
C100: Fixed Cost Inflation | L100: {=INDEX(L102:L104,$H$88)} | M100: {=INDEX(M102:M104,$H$88)} | N100: {=INDEX(N102:N104,$H$88)} | O100: {=INDEX(O102:O104,$H$88)} | P100: {=INDEX(P102:P104,$H$88)} | Q100: {=INDEX(Q102:Q104,$H$88)} | R100: {=INDEX(R102:R104,$H$88)} | S100: {=INDEX(S102:S104,$H$88)} | ... U100: {=INDEX(U102:U104,$H$88)}
D102: Base Case | L102: =T31 | M102: =U31 | N102: =HistoricalData!AA293 | O102: =HistoricalData!AB293 | P102: =HistoricalData!AC293 | Q102: =HistoricalData!AD293 | R102: =HistoricalData!AE293 | S102: =HistoricalData!AF293 | T102: =HistoricalData!AG293 | U102: =HistoricalData!AH293
A103: -0.005 | D103: Best Case | L103: =L$102+$A103 | M103: =M$102+$A103 | N103: =N$102+$A103 | O103: =O$102+$A103 | P103: =P$102+$A103 | Q103: =Q$102+$A103 | R103: =R$102+$A103 | S103: =S$102+$A103 | ... U103: =U$102+$A103
A104: 0.005 | D104: Worst Case | L104: =L$102+$A104 | M104: =M$102+$A104 | N104: =N$102+$A104 | O104: =O$102+$A104 | P104: =P$102+$A104 | Q104: =Q$102+$A104 | R104: =R$102+$A104 | S104: =S$102+$A104 | ... U104: =U$102+$A104
C106: Capacity | H106: =K42 | L106: {=INDEX(L108:L110,$H$88)} | M106: {=INDEX(M108:M110,$H$88)} | N106: {=INDEX(N108:N110,$H$88)} | O106: {=INDEX(O108:O110,$H$88)} | P106: {=INDEX(P108:P110,$H$88)} | Q106: {=INDEX(Q108:Q110,$H$88)} | R106: {=INDEX(R108:R110,$H$88)} | S106: {=INDEX(S108:S110,$H$88)} | ... U106: {=INDEX(U108:U110,$H$88)}
D108: Base Case | L108: =K41 | M108: =L108 | N108: =M108 | O108: =N108 | P108: =O108 | Q108: =P108 | R108: =Q108 | S108: =R108 | T108: =S108 | U108: =T108
A109: 0.05 | D109: ="Best Case ("&TEXT(A109*100,"0.00")&"%)" | L109: =L$108*(1+$A109) | M109: =M$108*(1+$A109) | N109: =N$108*(1+$A109) | O109: =O$108*(1+$A109) | P109: =P$108*(1+$A109) | Q109: =Q$108*(1+$A109) | R109: =R$108*(1+$A109) | S109: =S$108*(1+$A109) | ... U109: =U$108*(1+$A109)
A110: -0.05 | D110: ="Worst Case ("&TEXT(A110*100,"0.00")&"%)" | L110: =L$108*(1+$A110) | M110: =M$108*(1+$A110) | N110: =N$108*(1+$A110) | O110: =O$108*(1+$A110) | P110: =P$108*(1+$A110) | Q110: =Q$108*(1+$A110) | R110: =R$108*(1+$A110) | S110: =S$108*(1+$A110) | ... U110: =U$108*(1+$A110)
C112: Price Inflation | H112: (Sensitive to Row Material) | L112: {=INDEX(L114:L116,$H$88)} | M112: {=INDEX(M114:M116,$H$88)} | N112: {=INDEX(N114:N116,$H$88)} | O112: {=INDEX(O114:O116,$H$88)} | P112: {=INDEX(P114:P116,$H$88)} | Q112: {=INDEX(Q114:Q116,$H$88)} | R112: {=INDEX(R114:R116,$H$88)} | S112: {=INDEX(S114:S116,$H$88)} | ... U112: {=INDEX(U114:U116,$H$88)}
D114: Base Case | L114: =HistoricalData!Y41 | M114: =HistoricalData!Z41 | N114: =HistoricalData!AA41 | O114: =HistoricalData!AB41 | P114: =HistoricalData!AC41 | Q114: =HistoricalData!AD41 | R114: =HistoricalData!AE41 | S114: =HistoricalData!AF41 | ... U114: =HistoricalData!AH41
A115: 0.005 | D115: ="Best Case ("&TEXT(A115*100,"0.00")&"%)" | L115: =L$114+$A115 | M115: =M$114+$A115 | N115: =N$114+$A115 | O115: =O$114+$A115 | P115: =P$114+$A115 | Q115: =Q$114+$A115 | R115: =R$114+$A115 | S115: =S$114+$A115 | ... U115: =U$114+$A115
A116: -0.005 | D116: ="Worst Case ("&TEXT(A116*100,"0.00")&"%)" | L116: =L$114+$A116 | M116: =M$114+$A116 | N116: =N$114+$A116 | O116: =O$114+$A116 | P116: =P$114+$A116 | Q116: =Q$114+$A116 | R116: =R$114+$A116 | S116: =S$114+$A116 | ... U116: =U$114+$A116
C118: Volume Growth | H118: (New Service/Product) | L118: {=INDEX(L120:L122,$H$88)} | M118: {=INDEX(M120:M122,$H$88)} | N118: {=INDEX(N120:N122,$H$88)} | O118: {=INDEX(O120:O122,$H$88)} | P118: {=INDEX(P120:P122,$H$88)} | Q118: {=INDEX(Q120:Q122,$H$88)} | R118: {=INDEX(R120:R122,$H$88)} | S118: {=INDEX(S120:S122,$H$88)} | ... U118: {=INDEX(U120:U122,$H$88)}
D120: Base Case | L120: =HistoricalData!Y38 | M120: =HistoricalData!Z38 | N120: =HistoricalData!AA38 | O120: =HistoricalData!AB38 | P120: =HistoricalData!AC38 | Q120: =HistoricalData!AD38 | R120: =HistoricalData!AE38 | S120: =HistoricalData!AF38 | ... U120: =HistoricalData!AH38
A121: 0.02 | D121: ="Best Case ("&TEXT(A121*100,"0.00")&"%)" | L121: =L$120+$A121 | M121: =M$120+$A121 | N121: =N$120+$A121 | O121: =O$120+$A121 | P121: =P$120+$A121 | Q121: =Q$120+$A121 | R121: =R$120+$A121 | S121: =S$120+$A121 | ... U121: =U$120+$A121
A122: -0.02 | D122: ="Worst Case ("&TEXT(A122*100,"0.00")&"%)" | L122: =L$120+$A122 | M122: =M$120+$A122 | N122: =N$120+$A122 | O122: =O$120+$A122 | P122: =P$120+$A122 | Q122: =Q$120+$A122 | R122: =R$120+$A122 | S122: =S$120+$A122 | ... U122: =U$120+$A122
C124: Spread on Interest Rate | L124: {=INDEX(L126:L128,$H$88)} | M124: {=INDEX(M126:M128,$H$88)} | N124: {=INDEX(N126:N128,$H$88)} | O124: {=INDEX(O126:O128,$H$88)} | P124: {=INDEX(P126:P128,$H$88)} | Q124: {=INDEX(Q126:Q128,$H$88)} | R124: {=INDEX(R126:R128,$H$88)} | S124: {=INDEX(S126:S128,$H$88)} | ... U124: {=INDEX(U126:U128,$H$88)}
D126: Base Case | L126: 0 | M126: 0 | N126: 0 | O126: -0.0005 | P126: 0.0007 | Q126: 0.0007 | R126: 0.001 | S126: 0.0012 | T126: -0.0015 | U126: -0.0017
A127: -0.0025 | D127: ="Best Case ("&TEXT(A127*100,"0.00")&"%)" | L127: =L$126+$A127 | M127: =M$126+$A127 | N127: =N$126+$A127 | O127: =O$126+$A127 | P127: =P$126+$A127 | Q127: =Q$126+$A127 | R127: =R$126+$A127 | S127: =S$126+$A127 | ... U127: =U$126+$A127
A128: 0.0025 | D128: ="Worst Case ("&TEXT(A128*100,"0.00")&"%)" | L128: =L$126+$A128 | M128: =M$126+$A128 | N128: =N$126+$A128 | O128: =O$126+$A128 | P128: =P$126+$A128 | Q128: =Q$126+$A128 | R128: =R$126+$A128 | S128: =S$126+$A128 | ... U128: =U$126+$A128
C130: Exchange Rate | H130: (INR/INR) | L130: {=INDEX(L132:L134,$H$88)} | M130: {=INDEX(M132:M134,$H$88)} | N130: {=INDEX(N132:N134,$H$88)} | O130: {=INDEX(O132:O134,$H$88)} | P130: {=INDEX(P132:P134,$H$88)} | Q130: {=INDEX(Q132:Q134,$H$88)} | R130: {=INDEX(R132:R134,$H$88)} | S130: {=INDEX(S132:S134,$H$88)} | ... U130: {=INDEX(U132:U134,$H$88)}
D132: Base Case | L132: =1 | M132: =L132 | N132: =M132 | O132: =N132 | P132: =O132 | Q132: =P132 | R132: =Q132 | S132: =R132 | T132: =S132 | U132: =T132
A133: 0 | D133: ="Best Case ("&TEXT(A133*100,"0.00")&"%)" | L133: =L$132*(1+$A133) | M133: =M$132*(1+$A133) | N133: =N$132*(1+$A133) | O133: =O$132*(1+$A133) | P133: =P$132*(1+$A133) | Q133: =Q$132*(1+$A133) | R133: =R$132*(1+$A133) | S133: =S$132*(1+$A133) | ... U133: =U$132*(1+$A133)
A134: 0 | D134: ="Worst Case ("&TEXT(A134*100,"0.00")&"%)" | L134: =L$132*(1+$A134) | M134: =M$132*(1+$A134) | N134: =N$132*(1+$A134) | O134: =O$132*(1+$A134) | P134: =P$132*(1+$A134) | Q134: =Q$132*(1+$A134) | R134: =R$132*(1+$A134) | S134: =S$132*(1+$A134) | ... U134: =U$132*(1+$A134)
B138: ='Assumptions&Scenario'!$K$10
B139: Quarterly Economic and Sales Scenarios
L140: Projected
C141: Quarters | M141: ="FY"&TEXT(YEAR('Data Sheet'!$K$41)+(MONTH('Data Sheet'!$K$41)>3)-2000,"00")&"Q"&INT((MOD(MONTH('Data Sheet'!$K$41)-4,12))/3)+1 | N141: ="FY"&TEXT(MID(M141,3,2)+IF(RIGHT(M141,1)="4",1,0),"00")&"Q"&MOD(RIGHT(M141,1),4)+1 | O141: ="FY"&TEXT(MID(N141,3,2)+IF(RIGHT(N141,1)="4",1,0),"00")&"Q"&MOD(RIGHT(N141,1),4)+1 | P141: ="FY"&TEXT(MID(O141,3,2)+IF(RIGHT(O141,1)="4",1,0),"00")&"Q"&MOD(RIGHT(O141,1),4)+1 | Q141: ="FY"&TEXT(MID(P141,3,2)+IF(RIGHT(P141,1)="4",1,0),"00")&"Q"&MOD(RIGHT(P141,1),4)+1 | R141: ="FY"&TEXT(MID(Q141,3,2)+IF(RIGHT(Q141,1)="4",1,0),"00")&"Q"&MOD(RIGHT(Q141,1),4)+1 | S141: ="FY"&TEXT(MID(R141,3,2)+IF(RIGHT(R141,1)="4",1,0),"00")&"Q"&MOD(RIGHT(R141,1),4)+1 | T141: ="FY"&TEXT(MID(S141,3,2)+IF(RIGHT(S141,1)="4",1,0),"00")&"Q"&MOD(RIGHT(S141,1),4)+1 | U141: ="FY"&TEXT(MID(T141,3,2)+IF(RIGHT(T141,1)="4",1,0),"00")&"Q"&MOD(RIGHT(T141,1),4)+1
C145: ECONOMIC SCENARIOS
C147: Variable Cost Inflation | H147: (Sensitive to Row Material) | N147: {=INDEX(N149:N151,$H$88)} | O147: {=INDEX(O149:O151,$H$88)} | P147: {=INDEX(P149:P151,$H$88)} | Q147: {=INDEX(Q149:Q151,$H$88)} | R147: {=INDEX(R149:R151,$H$88)} | S147: {=INDEX(S149:S151,$H$88)} | T147: {=INDEX(T149:T151,$H$88)} | U147: {=INDEX(U149:U151,$H$88)}
D149: Base Case | N149: =HistoricalData!Y243 | O149: =HistoricalData!Z243 | P149: =HistoricalData!AA243 | Q149: =HistoricalData!AB243 | R149: =HistoricalData!AC243 | S149: =HistoricalData!AD243 | T149: =HistoricalData!AE243 | U149: =HistoricalData!AF243
A150: -0.005 | D150: ="Best Case ("&TEXT(A150*100,"0.00")&"%)" | N150: =N$149+$A150 | O150: =O$149+$A150 | P150: =P$149+$A150 | Q150: =Q$149+$A150 | R150: =R$149+$A150 | S150: =S$149+$A150 | T150: =T$149+$A150 | U150: =U$149+$A150
...

Sheet HistoricalData
B3: ='Assumptions&Scenario'!$K$10
B4: Annual Revenue History | Y4: Annual Revenue Forecast
C6: FIN Years | J6: ="FY"&TEXT(RIGHT(K6,2)-(COLUMN(K6)-COLUMN()),"00") | K6: ="FY"&TEXT(RIGHT(L6,2)-(COLUMN(L6)-COLUMN()),"00") | L6: ="FY"&TEXT(RIGHT(M6,2)-(COLUMN(M6)-COLUMN()),"00") | M6: ="FY"&TEXT(RIGHT(N6,2)-(COLUMN(N6)-COLUMN()),"00") | N6: ="FY"&TEXT(RIGHT(O6,2)-(COLUMN(O6)-COLUMN()),"00") | O6: ="FY"&TEXT(RIGHT(P6,2)-(COLUMN(P6)-COLUMN()),"00") | P6: ="FY"&TEXT(RIGHT(Q6,2)-(COLUMN(Q6)-COLUMN()),"00") | Q6: ="FY"&TEXT(RIGHT(R6,2)-(COLUMN(R6)-COLUMN()),"00") | ... T6: ="FY"&TEXT(RIGHT(U6,2)-(COLUMN(U6)-COLUMN()),"00") | U6: ="FY"&TEXT(DATE(YEAR('Data Sheet'!$K$16)+(MONTH('Data Sheet'!$K$16)>3),1,1),"YY") | Y6: =Model!$L$6 | Z6: ="FY"&TEXT(RIGHT(Y6,2)+COLUMN()-COLUMN(Y6),"00") | AA6: ="FY"&TEXT(RIGHT(Z6,2)+COLUMN()-COLUMN(Z6),"00") | AB6: ="FY"&TEXT(RIGHT(AA6,2)+COLUMN()-COLUMN(AA6),"00") | AC6: ="FY"&TEXT(RIGHT(AB6,2)+COLUMN()-COLUMN(AB6),"00") | AD6: ="FY"&TEXT(RIGHT(AC6,2)+COLUMN()-COLUMN(AC6),"00") | AE6: ="FY"&TEXT(RIGHT(AD6,2)+COLUMN()-COLUMN(AD6),"00") | AF6: ="FY"&TEXT(RIGHT(AE6,2)+COLUMN()-COLUMN(AE6),"00") | AG6: ="FY"&TEXT(RIGHT(AF6,2)+COLUMN()-COLUMN(AF6),"00") | AH6: ="FY"&TEXT(RIGHT(AG6,2)+COLUMN()-COLUMN(AG6),"00")
C10: Revenue | H10: (₹ crore) | L10: =IFERROR('Data Sheet'!B17, 0) | M10: =IFERROR('Data Sheet'!C17, 0) | N10: =IFERROR('Data Sheet'!D17, 0) | O10: =IFERROR('Data Sheet'!E17, 0) | P10: =IFERROR('Data Sheet'!F17, 0) | Q10: =IFERROR('Data Sheet'!G17, 0) | R10: =IFERROR('Data Sheet'!H17, 0) | S10: =IFERROR('Data Sheet'!I17, 0) | ... U10: =IFERROR('Data Sheet'!K17, 0) | Y10: {=IFERROR(_xlfn.FORECAST.LINEAR(RIGHT(Y$6,2), $J10:$U10, VALUE(RIGHT($J$6:$U$6,2))), 0)} | Z10: {=IFERROR(_xlfn.FORECAST.LINEAR(RIGHT(Z$6,2), $J10:$U10, VALUE(RIGHT($J$6:$U$6,2))), 0)} | AA10: {=IFERROR(_xlfn.FORECAST.LINEAR(RIGHT(AA$6,2), $J10:$U10, VALUE(RIGHT($J$6:$U$6,2))), 0)} | AB10: {=IFERROR(_xlfn.FORECAST.LINEAR(RIGHT(AB$6,2), $J10:$U10, VALUE(RIGHT($J$6:$U$6,2))), 0)} | AC10: {=IFERROR(_xlfn.FORECAST.LINEAR(RIGHT(AC$6,2), $J10:$U10, VALUE(RIGHT($J$6:$U$6,2))), 0)} | AD10: {=IFERROR(_xlfn.FORECAST.LINEAR(RIGHT(AD$6,2), $J10:$U10, VALUE(RIGHT($J$6:$U$6,2))), 0)} | AE10: {=IFERROR(_xlfn.FORECAST.LINEAR(RIGHT(AE$6,2), $J10:$U10, VALUE(RIGHT($J$6:$U$6,2))), 0)} | AF10: {=IFERROR(_xlfn.FORECAST.LINEAR(RIGHT(AF$6,2), $J10:$U10, VALUE(RIGHT($J$6:$U$6,2))), 0)} | ... AH10: {=IFERROR(_xlfn.FORECAST.LINEAR(RIGHT(AH$6,2), $J10:$U10, VALUE(RIGHT($J$6:$U$6,2))), 0)}
D11: Revenue Growth | K11: =IFERROR(K10/J10-1, 0) | L11: =IFERROR(L10/K10-1, 0) | M11: =IFERROR(M10/L10-1, 0) | N11: =IFERROR(N10/M10-1, 0) | O11: =IFERROR(O10/N10-1, 0) | P11: =IFERROR(P10/O10-1, 0) | Q11: =IFERROR(Q10/P10-1, 0) | R11: =IFERROR(R10/Q10-1, 0) | ... U11: =IFERROR(U10/T10-1, 0) | Y11: =IFERROR(Y10/U10-1, 0) | Z11: =IFERROR(Z10/Y10-1, 0) | AA11: =IFERROR(AA10/Z10-1, 0) | AB11: =IFERROR(AB10/AA10-1, 0) | AC11: =IFERROR(AC10/AB10-1, 0) | AD11: =IFERROR(AD10/AC10-1, 0) | AE11: =IFERROR(AE10/AD10-1, 0) | AF11: =IFERROR(AF10/AE10-1, 0) | AG11: =IFERROR(AG10/AF10-1, 0) | AH11: =IFERROR(AH10/AG10-1, 0)
C13: Segmental Revenue | H13: (₹ crore)
D14: Segment1 | Y14: {=IFERROR(_xlfn.FORECAST.LINEAR(RIGHT(Y$6,2), $J14:$U14, VALUE(RIGHT($J$6:$U$6,2))), 0)} | Z14: {=IFERROR(_xlfn.FORECAST.LINEAR(RIGHT(Z$6,2), $J14:$U14, VALUE(RIGHT($J$6:$U$6,2))), 0)} | AA14: {=IFERROR(_xlfn.FORECAST.LINEAR(RIGHT(AA$6,2), $J14:$U14, VALUE(RIGHT($J$6:$U$6,2))), 0)} | AB14: {=IFERROR(_xlfn.FORECAST.LINEAR(RIGHT(AB$6,2), $J14:$U14, VALUE(RIGHT($J$6:$U$6,2))), 0)} | AC14: {=IFERROR(_xlfn.FORECAST.LINEAR(RIGHT(AC$6,2), $J14:$U14, VALUE(RIGHT($J$6:$U$6,2))), 0)} | AD14: {=IFERROR(_xlfn.FORECAST.LINEAR(RIGHT(AD$6,2), $J14:$U14, VALUE(RIGHT($J$6:$U$6,2))), 0)} | AE14: {=IFERROR(_xlfn.FORECAST.LINEAR(RIGHT(AE$6,2), $J14:$U14, VALUE(RIGHT($J$6:$U$6,2))), 0)} | AF14: {=IFERROR(_xlfn.FORECAST.LINEAR(RIGHT(AF$6,2), $J14:$U14, VALUE(RIGHT($J$6:$U$6,2))), 0)} | ... AH14: {=IFERROR(_xlfn.FORECAST.LINEAR(RIGHT(AH$6,2), $J14:$U14, VALUE(RIGHT($J$6:$U$6,2))), 0)}
D15: Segment2 | Y15: {=IFERROR(_xlfn.FORECAST.LINEAR(RIGHT(Y$6,2), $J15:$U15, VALUE(RIGHT($J$6:$U$6,2))), 0)} | Z15: {=IFERROR(_xlfn.FORECAST.LINEAR(RIGHT(Z$6,2), $J15:$U15, VALUE(RIGHT($J$6:$U$6,2))), 0)} | AA15: {=IFERROR(_xlfn.FORECAST.LINEAR(RIGHT(AA$6,2), $J15:$U15, VALUE(RIGHT($J$6:$U$6,2))), 0)} | AB15: {=IFERROR(_xlfn.FORECAST.LINEAR(RIGHT(AB$6,2), $J15:$U15, VALUE(RIGHT($J$6:$U$6,2))), 0)} | AC15: {=IFERROR(_xlfn.FORECAST.LINEAR(RIGHT(AC$6,2), $J15:$U15, VALUE(RIGHT($J$6:$U$6,2))), 0)} | AD15: {=IFERROR(_xlfn.FORECAST.LINEAR(RIGHT(AD$6,2), $J15:$U15, VALUE(RIGHT($J$6:$U$6,2))), 0)} | AE15: {=IFERROR(_xlfn.FORECAST.LINEAR(RIGHT(AE$6,2), $J15:$U15, VALUE(RIGHT($J$6:$U$6,2))), 0)} | AF15: {=IFERROR(_xlfn.FORECAST.LINEAR(RIGHT(AF$6,2), $J15:$U15, VALUE(RIGHT($J$6:$U$6,2))), 0)} | ... AH15: {=IFERROR(_xlfn.FORECAST.LINEAR(RIGHT(AH$6,2), $J15:$U15, VALUE(RIGHT($J$6:$U$6,2))), 0)}
D16: Segment3 | Y16: {=IFERROR(_xlfn.FORECAST.LINEAR(RIGHT(Y$6,2), $J16:$U16, VALUE(RIGHT($J$6:$U$6,2))), 0)} | Z16: {=IFERROR(_xlfn.FORECAST.LINEAR(RIGHT(Z$6,2), $J16:$U16, VALUE(RIGHT($J$6:$U$6,2))), 0)} | AA16: {=IFERROR(_xlfn.FORECAST.LINEAR(RIGHT(AA$6,2), $J16:$U16, VALUE(RIGHT($J$6:$U$6,2))), 0)} | AB16: {=IFERROR(_xlfn.FORECAST.LINEAR(RIGHT(AB$6,2), $J16:$U16, VALUE(RIGHT($J$6:$U$6,2))), 0)} | AC16: {=IFERROR(_xlfn.FORECAST.LINEAR(RIGHT(AC$6,2), $J16:$U16, VALUE(RIGHT($J$6:$U$6,2))), 0)} | AD16: {=IFERROR(_xlfn.FORECAST.LINEAR(RIGHT(AD$6,2), $J16:$U16, VALUE(RIGHT($J$6:$U$6,2))), 0)} | AE16: {=IFERROR(_xlfn.FORECAST.LINEAR(RIGHT(AE$6,2), $J16:$U16, VALUE(RIGHT($J$6:$U$6,2))), 0)} | AF16: {=IFERROR(_xlfn.FORECAST.LINEAR(RIGHT(AF$6,2), $J16:$U16, VALUE(RIGHT($J$6:$U$6,2))), 0)} | ... AH16: {=IFERROR(_xlfn.FORECAST.LINEAR(RIGHT(AH$6,2), $J16:$U16, VALUE(RIGHT($J$6:$U$6,2))), 0)}
D17: Segment4 | Y17: {=IFERROR(_xlfn.FORECAST.LINEAR(RIGHT(Y$6,2), $J17:$U17, VALUE(RIGHT($J$6:$U$6,2))), 0)} | Z17: {=IFERROR(_xlfn.FORECAST.LINEAR(RIGHT(Z$6,2), $J17:$U17, VALUE(RIGHT($J$6:$U$6,2))), 0)} | AA17: {=IFERROR(_xlfn.FORECAST.LINEAR(RIGHT(AA$6,2), $J17:$U17, VALUE(RIGHT($J$6:$U$6,2))), 0)} | AB17: {=IFERROR(_xlfn.FORECAST.LINEAR(RIGHT(AB$6,2), $J17:$U17, VALUE(RIGHT($J$6:$U$6,2))), 0)} | AC17: {=IFERROR(_xlfn.FORECAST.LINEAR(RIGHT(AC$6,2), $J17:$U17, VALUE(RIGHT($J$6:$U$6,2))), 0)} | AD17: {=IFERROR(_xlfn.FORECAST.LINEAR(RIGHT(AD$6,2), $J17:$U17, VALUE(RIGHT($J$6:$U$6,2))), 0)} | AE17: {=IFERROR(_xlfn.FORECAST.LINEAR(RIGHT(AE$6,2), $J17:$U17, VALUE(RIGHT($J$6:$U$6,2))), 0)} | AF17: {=IFERROR(_xlfn.FORECAST.LINEAR(RIGHT(AF$6,2), $J17:$U17, VALUE(RIGHT($J$6:$U$6,2))), 0)} | ... AH17: {=IFERROR(_xlfn.FORECAST.LINEAR(RIGHT(AH$6,2), $J17:$U17, VALUE(RIGHT($J$6:$U$6,2))), 0)}
D18: Segment5 | Y18: {=IFERROR(_xlfn.FORECAST.LINEAR(RIGHT(Y$6,2), $J18:$U18, VALUE(RIGHT($J$6:$U$6,2))), 0)} | Z18: {=IFERROR(_xlfn.FORECAST.LINEAR(RIGHT(Z$6,2), $J18:$U18, VALUE(RIGHT($J$6:$U$6,2))), 0)} | AA18: {=IFERROR(_xlfn.FORECAST.LINEAR(RIGHT(AA$6,2), $J18:$U18, VALUE(RIGHT($J$6:$U$6,2))), 0)} | AB18: {=IFERROR(_xlfn.FORECAST.LINEAR(RIGHT(AB$6,2), $J18:$U18, VALUE(RIGHT($J$6:$U$6,2))), 0)} | AC18: {=IFERROR(_xlfn.FORECAST.LINEAR(RIGHT(AC$6,2), $J18:$U18, VALUE(RIGHT($J$6:$U$6,2))), 0)} | AD18: {=IFERROR(_xlfn.FORECAST.LINEAR(RIGHT(AD$6,2), $J18:$U18, VALUE(RIGHT($J$6:$U$6,2))), 0)} | AE18: {=IFERROR(_xlfn.FORECAST.LINEAR(RIGHT(AE$6,2), $J18:$U18, VALUE(RIGHT($J$6:$U$6,2))), 0)} | AF18: {=IFERROR(_xlfn.FORECAST.LINEAR(RIGHT(AF$6,2), $J18:$U18, VALUE(RIGHT($J$6:$U$6,2))), 0)} | ... AH18: {=IFERROR(_xlfn.FORECAST.LINEAR(RIGHT(AH$6,2), $J18:$U18, VALUE(RIGHT($J$6:$U$6,2))), 0)}
D19: Segment6 | Y19: {=IFERROR(_xlfn.FORECAST.LINEAR(RIGHT(Y$6,2), $J19:$U19, VALUE(RIGHT($J$6:$U$6,2))), 0)} | Z19: {=IFERROR(_xlfn.FORECAST.LINEAR(RIGHT(Z$6,2), $J19:$U19, VALUE(RIGHT($J$6:$U$6,2))), 0)} | AA19: {=IFERROR(_xlfn.FORECAST.LINEAR(RIGHT(AA$6,2), $J19:$U19, VALUE(RIGHT($J$6:$U$6,2))), 0)} | AB19: {=IFERROR(_xlfn.FORECAST.LINEAR(RIGHT(AB$6,2), $J19:$U19, VALUE(RIGHT($J$6:$U$6,2))), 0)} | AC19: {=IFERROR(_xlfn.FORECAST.LINEAR(RIGHT(AC$6,2), $J19:$U19, VALUE(RIGHT($J$6:$U$6,2))), 0)} | AD19: {=IFERROR(_xlfn.FORECAST.LINEAR(RIGHT(AD$6,2), $J19:$U19, VALUE(RIGHT($J$6:$U$6,2))), 0)} | AE19: {=IFERROR(_xlfn.FORECAST.LINEAR(RIGHT(AE$6,2), $J19:$U19, VALUE(RIGHT($J$6:$U$6,2))), 0)} | AF19: {=IFERROR(_xlfn.FORECAST.LINEAR(RIGHT(AF$6,2), $J19:$U19, VALUE(RIGHT($J$6:$U$6,2))), 0)} | ... AH19: {=IFERROR(_xlfn.FORECAST.LINEAR(RIGHT(AH$6,2), $J19:$U19, VALUE(RIGHT($J$6:$U$6,2))), 0)}
D20: Segment7 | Y20: {=IFERROR(_xlfn.FORECAST.LINEAR(RIGHT(Y$6,2), $J20:$U20, VALUE(RIGHT($J$6:$U$6,2))), 0)} | Z20: {=IFERROR(_xlfn.FORECAST.LINEAR(RIGHT(Z$6,2), $J20:$U20, VALUE(RIGHT($J$6:$U$6,2))), 0)} | AA20: {=IFERROR(_xlfn.FORECAST.LINEAR(RIGHT(AA$6,2), $J20:$U20, VALUE(RIGHT($J$6:$U$6,2))), 0)} | AB20: {=IFERROR(_xlfn.FORECAST.LINEAR(RIGHT(AB$6,2), $J20:$U20, VALUE(RIGHT($J$6:$U$6,2))), 0)} | AC20: {=IFERROR(_xlfn.FORECAST.LINEAR(RIGHT(AC$6,2), $J20:$U20, VALUE(RIGHT($J$6:$U$6,2))), 0)} | AD20: {=IFERROR(_xlfn.FORECAST.LINEAR(RIGHT(AD$6,2), $J20:$U20, VALUE(RIGHT($J$6:$U$6,2))), 0)} | AE20: {=IFERROR(_xlfn.FORECAST.LINEAR(RIGHT(AE$6,2), $J20:$U20, VALUE(RIGHT($J$6:$U$6,2))), 0)} | AF20: {=IFERROR(_xlfn.FORECAST.LINEAR(RIGHT(AF$6,2), $J20:$U20, VALUE(RIGHT($J$6:$U$6,2))), 0)} | ... AH20: {=IFERROR(_xlfn.FORECAST.LINEAR(RIGHT(AH$6,2), $J20:$U20, VALUE(RIGHT($J$6:$U$6,2))), 0)}
D21: Segment8 | Y21: {=IFERROR(_xlfn.FORECAST.LINEAR(RIGHT(Y$6,2), $J21:$U21, VALUE(RIGHT($J$6:$U$6,2))), 0)} | Z21: {=IFERROR(_xlfn.FORECAST.LINEAR(RIGHT(Z$6,2), $J21:$U21, VALUE(RIGHT($J$6:$U$6,2))), 0)} | AA21: {=IFERROR(_xlfn.FORECAST.LINEAR(RIGHT(AA$6,2), $J21:$U21, VALUE(RIGHT($J$6:$U$6,2))), 0)} | AB21: {=IFERROR(_xlfn.FORECAST.LINEAR(RIGHT(AB$6,2), $J21:$U21, VALUE(RIGHT($J$6:$U$6,2))), 0)} | AC21: {=IFERROR(_xlfn.FORECAST.LINEAR(RIGHT(AC$6,2), $J21:$U21, VALUE(RIGHT($J$6:$U$6,2))), 0)} | AD21: {=IFERROR(_xlfn.FORECAST.LINEAR(RIGHT(AD$6,2), $J21:$U21, VALUE(RIGHT($J$6:$U$6,2))), 0)} | AE21: {=IFERROR(_xlfn.FORECAST.LINEAR(RIGHT(AE$6,2), $J21:$U21, VALUE(RIGHT($J$6:$U$6,2))), 0)} | AF21: {=IFERROR(_xlfn.FORECAST.LINEAR(RIGHT(AF$6,2), $J21:$U21, VALUE(RIGHT($J$6:$U$6,2))), 0)} | ... AH21: {=IFERROR(_xlfn.FORECAST.LINEAR(RIGHT(AH$6,2), $J21:$U21, VALUE(RIGHT($J$6:$U$6,2))), 0)}
D22: Segment9 | Y22: {=IFERROR(_xlfn.FORECAST.LINEAR(RIGHT(Y$6,2), $J22:$U22, VALUE(RIGHT($J$6:$U$6,2))), 0)} | Z22: {=IFERROR(_xlfn.FORECAST.LINEAR(RIGHT(Z$6,2), $J22:$U22, VALUE(RIGHT($J$6:$U$6,2))), 0)} | AA22: {=IFERROR(_xlfn.FORECAST.LINEAR(RIGHT(AA$6,2), $J22:$U22, VALUE(RIGHT($J$6:$U$6,2))), 0)} | AB22: {=IFERROR(_xlfn.FORECAST.LINEAR(RIGHT(AB$6,2), $J22:$U22, VALUE(RIGHT($J$6:$U$6,2))), 0)} | AC22: {=IFERROR(_xlfn.FORECAST.LINEAR(RIGHT(AC$6,2), $J22:$U22, VALUE(RIGHT($J$6:$U$6,2))), 0)} | AD22: {=IFERROR(_xlfn.FORECAST.LINEAR(RIGHT(AD$6,2), $J22:$U22, VALUE(RIGHT($J$6:$U$6,2))), 0)} | AE22: {=IFERROR(_xlfn.FORECAST.LINEAR(RIGHT(AE$6,2), $J22:$U22, VALUE(RIGHT($J$6:$U$6,2))), 0)} | AF22: {=IFERROR(_xlfn.FORECAST.LINEAR(RIGHT(AF$6,2), $J22:$U22, VALUE(RIGHT($J$6:$U$6,2))), 0)} | ... AH22: {=IFERROR(_xlfn.FORECAST.LINEAR(RIGHT(AH$6,2), $J22:$U22, VALUE(RIGHT($J$6:$U$6,2))), 0)}
D23: Segment10 | Y23: {=IFERROR(_xlfn.FORECAST.LINEAR(RIGHT(Y$6,2), $J23:$U23, VALUE(RIGHT($J$6:$U$6,2))), 0)} | Z23: {=IFERROR(_xlfn.FORECAST.LINEAR(RIGHT(Z$6,2), $J23:$U23, VALUE(RIGHT($J$6:$U$6,2))), 0)} | AA23: {=IFERROR(_xlfn.FORECAST.LINEAR(RIGHT(AA$6,2), $J23:$U23, VALUE(RIGHT($J$6:$U$6,2))), 0)} | AB23: {=IFERROR(_xlfn.FORECAST.LINEAR(RIGHT(AB$6,2), $J23:$U23, VALUE(RIGHT($J$6:$U$6,2))), 0)} | AC23: {=IFERROR(_xlfn.FORECAST.LINEAR(RIGHT(AC$6,2), $J23:$U23, VALUE(RIGHT($J$6:$U$6,2))), 0)} | AD23: {=IFERROR(_xlfn.FORECAST.LINEAR(RIGHT(AD$6,2), $J23:$U23, VALUE(RIGHT($J$6:$U$6,2))), 0)} | AE23: {=IFERROR(_xlfn.FORECAST.LINEAR(RIGHT(AE$6,2), $J23:$U23, VALUE(RIGHT($J$6:$U$6,2))), 0)} | AF23: {=IFERROR(_xlfn.FORECAST.LINEAR(RIGHT(AF$6,2), $J23:$U23, VALUE(RIGHT($J$6:$U$6,2))), 0)} | ... AH23: {=IFERROR(_xlfn.FORECAST.LINEAR(RIGHT(AH$6,2), $J23:$U23, VALUE(RIGHT($J$6:$U$6,2))), 0)}
D24: Segmental Revenue | J24: =SUM(J14:J23) | K24: =SUM(K14:K23) | L24: =SUM(L14:L23) | M24: =SUM(M14:M23) | N24: =SUM(N14:N23) | O24: =SUM(O14:O23) | P24: =SUM(P14:P23) | Q24: =SUM(Q14:Q23) | ... U24: =SUM(U14:U23) | Y24: =SUM(Y14:Y23) | Z24: =SUM(Z14:Z23) | AA24: =SUM(AA14:AA23) | AB24: =SUM(AB14:AB23) | AC24: =SUM(AC14:AC23) | AD24: =SUM(AD14:AD23) | AE24: =SUM(AE14:AE23) | AF24: =SUM(AF14:AF23) | ... AH24: =SUM(AH14:AH23)
C26: Geography Revenue | H26: (₹ crore)
D27: Geography1 | Y27: {=IFERROR(_xlfn.FORECAST.LINEAR(RIGHT(Y$6,2), $J27:$U27, VALUE(RIGHT($J$6:$U$6,2))), 0)} | Z27: {=IFERROR(_xlfn.FORECAST.LINEAR(RIGHT(Z$6,2), $J27:$U27, VALUE(RIGHT($J$6:$U$6,2))), 0)} | AA27: {=IFERROR(_xlfn.FORECAST.LINEAR(RIGHT(AA$6,2), $J27:$U27, VALUE(RIGHT($J$6:$U$6,2))), 0)} | AB27: {=IFERROR(_xlfn.FORECAST.LINEAR(RIGHT(AB$6,2), $J27:$U27, VALUE(RIGHT($J$6:$U$6,2))), 0)} | AC27: {=IFERROR(_xlfn.FORECAST.LINEAR(RIGHT(AC$6,2), $J27:$U27, VALUE(RIGHT($J$6:$U$6,2))), 0)} | AD27: {=IFERROR(_xlfn.FORECAST.LINEAR(RIGHT(AD$6,2), $J27:$U27, VALUE(RIGHT($J$6:$U$6,2))), 0)} | AE27: {=IFERROR(_xlfn.FORECAST.LINEAR(RIGHT(AE$6,2), $J27:$U27, VALUE(RIGHT($J$6:$U$6,2))), 0)} | AF27: {=IFERROR(_xlfn.FORECAST.LINEAR(RIGHT(AF$6,2), $J27:$U27, VALUE(RIGHT($J$6:$U$6,2))), 0)} | ... AH27: {=IFERROR(_xlfn.FORECAST.LINEAR(RIGHT(AH$6,2), $J27:$U27, VALUE(RIGHT($J$6:$U$6,2))), 0)}
D28: Geography2 | Y28: {=IFERROR(_xlfn.FORECAST.LINEAR(RIGHT(Y$6,2), $J28:$U28, VALUE(RIGHT($J$6:$U$6,2))), 0)} | Z28: {=IFERROR(_xlfn.FORECAST.LINEAR(RIGHT(Z$6,2), $J28:$U28, VALUE(RIGHT($J$6:$U$6,2))), 0)} | AA28: {=IFERROR(_xlfn.FORECAST.LINEAR(RIGHT(AA$6,2), $J28:$U28, VALUE(RIGHT($J$6:$U$6,2))), 0)} | AB28: {=IFERROR(_xlfn.FORECAST.LINEAR(RIGHT(AB$6,2), $J28:$U28, VALUE(RIGHT($J$6:$U$6,2))), 0)} | AC28: {=IFERROR(_xlfn.FORECAST.LINEAR(RIGHT(AC$6,2), $J28:$U28, VALUE(RIGHT($J$6:$U$6,2))), 0)} | AD28: {=IFERROR(_xlfn.FORECAST.LINEAR(RIGHT(AD$6,2), $J28:$U28, VALUE(RIGHT($J$6:$U$6,2))), 0)} | AE28: {=IFERROR(_xlfn.FORECAST.LINEAR(RIGHT(AE$6,2), $J28:$U28, VALUE(RIGHT($J$6:$U$6,2))), 0)} | AF28: {=IFERROR(_xlfn.FORECAST.LINEAR(RIGHT(AF$6,2), $J28:$U28, VALUE(RIGHT($J$6:$U$6,2))), 0)} | ... AH28: {=IFERROR(_xlfn.FORECAST.LINEAR(RIGHT(AH$6,2), $J28:$U28, VALUE(RIGHT($J$6:$U$6,2))), 0)}
D29: Geography3 | Y29: {=IFERROR(_xlfn.FORECAST.LINEAR(RIGHT(Y$6,2), $J29:$U29, VALUE(RIGHT($J$6:$U$6,2))), 0)} | Z29: {=IFERROR(_xlfn.FORECAST.LINEAR(RIGHT(Z$6,2), $J29:$U29, VALUE(RIGHT($J$6:$U$6,2))), 0)} | AA29: {=IFERROR(_xlfn.FORECAST.LINEAR(RIGHT(AA$6,2), $J29:$U29, VALUE(RIGHT($J$6:$U$6,2))), 0)} | AB29: {=IFERROR(_xlfn.FORECAST.LINEAR(RIGHT(AB$6,2), $J29:$U29, VALUE(RIGHT($J$6:$U$6,2))), 0)} | AC29: {=IFERROR(_xlfn.FORECAST.LINEAR(RIGHT(AC$6,2), $J29:$U29, VALUE(RIGHT($J$6:$U$6,2))), 0)} | AD29: {=IFERROR(_xlfn.FORECAST.LINEAR(RIGHT(AD$6,2), $J29:$U29, VALUE(RIGHT($J$6:$U$6,2))), 0)} | AE29: {=IFERROR(_xlfn.FORECAST.LINEAR(RIGHT(AE$6,2), $J29:$U29, VALUE(RIGHT($J$6:$U$6,2))), 0)} | AF29: {=IFERROR(_xlfn.FORECAST.LINEAR(RIGHT(AF$6,2), $J29:$U29, VALUE(RIGHT($J$6:$U$6,2))), 0)} | ... AH29: {=IFERROR(_xlfn.FORECAST.LINEAR(RIGHT(AH$6,2), $J29:$U29, VALUE(RIGHT($J$6:$U$6,2))), 0)}
D30: Geography4 | Y30: {=IFERROR(_xlfn.FORECAST.LINEAR(RIGHT(Y$6,2), $J30:$U30, VALUE(RIGHT($J$6:$U$6,2))), 0)} | Z30: {=IFERROR(_xlfn.FORECAST.LINEAR(RIGHT(Z$6,2), $J30:$U30, VALUE(RIGHT($J$6:$U$6,2))), 0)} | AA30: {=IFERROR(_xlfn.FORECAST.LINEAR(RIGHT(AA$6,2), $J30:$U30, VALUE(RIGHT($J$6:$U$6,2))), 0)} | AB30: {=IFERROR(_xlfn.FORECAST.LINEAR(RIGHT(AB$6,2), $J30:$U30, VALUE(RIGHT($J$6:$U$6,2))), 0)} | AC30: {=IFERROR(_xlfn.FORECAST.LINEAR(RIGHT(AC$6,2), $J30:$U30, VALUE(RIGHT($J$6:$U$6,2))), 0)} | AD30: {=IFERROR(_xlfn.FORECAST.LINEAR(RIGHT(AD$6,2), $J30:$U30, VALUE(RIGHT($J$6:$U$6,2))), 0)} | AE30: {=IFERROR(_xlfn.FORECAST.LINEAR(RIGHT(AE$6,2), $J30:$U30, VALUE(RIGHT($J$6:$U$6,2))), 0)} | AF30: {=IFERROR(_xlfn.FORECAST.LINEAR(RIGHT(AF$6,2), $J30:$U30, VALUE(RIGHT($J$6:$U$6,2))), 0)} | ... AH30: {=IFERROR(_xlfn.FORECAST.LINEAR(RIGHT(AH$6,2), $J30:$U30, VALUE(RIGHT($J$6:$U$6,2))), 0)}
D31: Geography5 | Y31: {=IFERROR(_xlfn.FORECAST.LINEAR(RIGHT(Y$6,2), $J31:$U31, VALUE(RIGHT($J$6:$U$6,2))), 0)} | Z31: {=IFERROR(_xlfn.FORECAST.LINEAR(RIGHT(Z$6,2), $J31:$U31, VALUE(RIGHT($J$6:$U$6,2))), 0)} | AA31: {=IFERROR(_xlfn.FORECAST.LINEAR(RIGHT(AA$6,2), $J31:$U31, VALUE(RIGHT($J$6:$U$6,2))), 0)} | AB31: {=IFERROR(_xlfn.FORECAST.LINEAR(RIGHT(AB$6,2), $J31:$U31, VALUE(RIGHT($J$6:$U$6,2))), 0)} | AC31: {=IFERROR(_xlfn.FORECAST.LINEAR(RIGHT(AC$6,2), $J31:$U31, VALUE(RIGHT($J$6:$U$6,2))), 0)} | AD31: {=IFERROR(_xlfn.FORECAST.LINEAR(RIGHT(AD$6,2), $J31:$U31, VALUE(RIGHT($J$6:$U$6,2))), 0)} | AE31: {=IFERROR(_xlfn.FORECAST.LINEAR(RIGHT(AE$6,2), $J31:$U31, VALUE(RIGHT($J$6:$U$6,2))), 0)} | AF31: {=IFERROR(_xlfn.FORECAST.LINEAR(RIGHT(AF$6,2), $J31:$U31, VALUE(RIGHT($J$6:$U$6,2))), 0)} | ... AH31: {=IFERROR(_xlfn.FORECAST.LINEAR(RIGHT(AH$6,2), $J31:$U31, VALUE(RIGHT($J$6:$U$6,2))), 0)}
D32: Geography6 | Y32: {=IFERROR(_xlfn.FORECAST.LINEAR(RIGHT(Y$6,2), $J32:$U32, VALUE(RIGHT($J$6:$U$6,2))), 0)} | Z32: {=IFERROR(_xlfn.FORECAST.LINEAR(RIGHT(Z$6,2), $J32:$U32, VALUE(RIGHT($J$6:$U$6,2))), 0)} | AA32: {=IFERROR(_xlfn.FORECAST.LINEAR(RIGHT(AA$6,2), $J32:$U32, VALUE(RIGHT($J$6:$U$6,2))), 0)} | AB32: {=IFERROR(_xlfn.FORECAST.LINEAR(RIGHT(AB$6,2), $J32:$U32, VALUE(RIGHT($J$6:$U$6,2))), 0)} | AC32: {=IFERROR(_xlfn.FORECAST.LINEAR(RIGHT(AC$6,2), $J32:$U32, VALUE(RIGHT($J$6:$U$6,2))), 0)} | AD32: {=IFERROR(_xlfn.FORECAST.LINEAR(RIGHT(AD$6,2), $J32:$U32, VALUE(RIGHT($J$6:$U$6,2))), 0)} | AE32: {=IFERROR(_xlfn.FORECAST.LINEAR(RIGHT(AE$6,2), $J32:$U32, VALUE(RIGHT($J$6:$U$6,2))), 0)} | AF32: {=IFERROR(_xlfn.FORECAST.LINEAR(RIGHT(AF$6,2), $J32:$U32, VALUE(RIGHT($J$6:$U$6,2))), 0)} | ... AH32: {=IFERROR(_xlfn.FORECAST.LINEAR(RIGHT(AH$6,2), $J32:$U32, VALUE(RIGHT($J$6:$U$6,2))), 0)}
D33: Geography7 | Y33: {=IFERROR(_xlfn.FORECAST.LINEAR(RIGHT(Y$6,2), $J33:$U33, VALUE(RIGHT($J$6:$U$6,2))), 0)} | Z33: {=IFERROR(_xlfn.FORECAST.LINEAR(RIGHT(Z$6,2), $J33:$U33, VALUE(RIGHT($J$6:$U$6,2))), 0)} | AA33: {=IFERROR(_xlfn.FORECAST.LINEAR(RIGHT(AA$6,2), $J33:$U33, VALUE(RIGHT($J$6:$U$6,2))), 0)} | AB33: {=IFERROR(_xlfn.FORECAST.LINEAR(RIGHT(AB$6,2), $J33:$U33, VALUE(RIGHT($J$6:$U$6,2))), 0)} | AC33: {=IFERROR(_xlfn.FORECAST.LINEAR(RIGHT(AC$6,2), $J33:$U33, VALUE(RIGHT($J$6:$U$6,2))), 0)} | AD33: {=IFERROR(_xlfn.FORECAST.LINEAR(RIGHT(AD$6,2), $J33:$U33, VALUE(RIGHT($J$6:$U$6,2))), 0)} | AE33: {=IFERROR(_xlfn.FORECAST.LINEAR(RIGHT(AE$6,2), $J33:$U33, VALUE(RIGHT($J$6:$U$6,2))), 0)} | AF33: {=IFERROR(_xlfn.FORECAST.LINEAR(RIGHT(AF$6,2), $J33:$U33, VALUE(RIGHT($J$6:$U$6,2))), 0)} | ... AH33: {=IFERROR(_xlfn.FORECAST.LINEAR(RIGHT(AH$6,2), $J33:$U33, VALUE(RIGHT($J$6:$U$6,2))), 0)}
D34: Geography8 | Y34: {=IFERROR(_xlfn.FORECAST.LINEAR(RIGHT(Y$6,2), $J34:$U34, VALUE(RIGHT($J$6:$U$6,2))), 0)} | Z34: {=IFERROR(_xlfn.FORECAST.LINEAR(RIGHT(Z$6,2), $J34:$U34, VALUE(RIGHT($J$6:$U$6,2))), 0)} | AA34: {=IFERROR(_xlfn.FORECAST.LINEAR(RIGHT(AA$6,2), $J34:$U34, VALUE(RIGHT($J$6:$U$6,2))), 0)} | AB34: {=IFERROR(_xlfn.FORECAST.LINEAR(RIGHT(AB$6,2), $J34:$U34, VALUE(RIGHT($J$6:$U$6,2))), 0)} | AC34: {=IFERROR(_xlfn.FORECAST.LINEAR(RIGHT(AC$6,2), $J34:$U34, VALUE(RIGHT($J$6:$U$6,2))), 0)} | AD34: {=IFERROR(_xlfn.FORECAST.LINEAR(RIGHT(AD$6,2), $J34:$U34, VALUE(RIGHT($J$6:$U$6,2))), 0)} | AE34: {=IFERROR(_xlfn.FORECAST.LINEAR(RIGHT(AE$6,2), $J34:$U34, VALUE(RIGHT($J$6:$U$6,2))), 0)} | AF34: {=IFERROR(_xlfn.FORECAST.LINEAR(RIGHT(AF$6,2), $J34:$U34, VALUE(RIGHT($J$6:$U$6,2))), 0)} | ... AH34: {=IFERROR(_xlfn.FORECAST.LINEAR(RIGHT(AH$6,2), $J34:$U34, VALUE(RIGHT($J$6:$U$6,2))), 0)}
D35: Geography Revenue | J35: =SUM(J27:J34) | K35: =SUM(K27:K34) | L35: =SUM(L27:L34) | M35: =SUM(M27:M34) | N35: =SUM(N27:N34) | O35: =SUM(O27:O34) | P35: =SUM(P27:P34) | Q35: =SUM(Q27:Q34) | ... U35: =SUM(U27:U34) | Y35: =SUM(Y27:Y34) | Z35: =SUM(Z27:Z34) | AA35: =SUM(AA27:AA34) | AB35: =SUM(AB27:AB34) | AC35: =SUM(AC27:AC34) | AD35: =SUM(AD27:AD34) | AE35: =SUM(AE27:AE34) | AF35: =SUM(AF27:AF34) | ... AH35: =SUM(AH27:AH34)
C37: ="Total Volume "& 'Assumptions&Scenario'!K42 | H37: ='Assumptions&Scenario'!K43 | L37: =L10 | M37: =M10 | N37: =N10 | O37: =O10 | P37: =P10 | Q37: =Q10 | R37: =R10 | S37: =S10 | ... U37: =U10 | Y37: {=IFERROR(_xlfn.FORECAST.LINEAR(RIGHT(Y$6,2), $J37:$U37, VALUE(RIGHT($J$6:$U$6,2))), 0)} | Z37: {=IFERROR(_xlfn.FORECAST.LINEAR(RIGHT(Z$6,2), $J37:$U37, VALUE(RIGHT($J$6:$U$6,2))), 0)} | AA37: {=IFERROR(_xlfn.FORECAST.LINEAR(RIGHT(AA$6,2), $J37:$U37, VALUE(RIGHT($J$6:$U$6,2))), 0)} | AB37: {=IFERROR(_xlfn.FORECAST.LINEAR(RIGHT(AB$6,2), $J37:$U37, VALUE(RIGHT($J$6:$U$6,2))), 0)} | AC37: {=IFERROR(_xlfn.FORECAST.LINEAR(RIGHT(AC$6,2), $J37:$U37, VALUE(RIGHT($J$6:$U$6,2))), 0)} | AD37: {=IFERROR(_xlfn.FORECAST.LINEAR(RIGHT(AD$6,2), $J37:$U37, VALUE(RIGHT($J$6:$U$6,2))), 0)} | AE37: {=IFERROR(_xlfn.FORECAST.LINEAR(RIGHT(AE$6,2), $J37:$U37, VALUE(RIGHT($J$6:$U$6,2))), 0)} | AF37: {=IFERROR(_xlfn.FORECAST.LINEAR(RIGHT(AF$6,2), $J37:$U37, VALUE(RIGHT($J$6:$U$6,2))), 0)} | ... AH37: {=IFERROR(_xlfn.FORECAST.LINEAR(RIGHT(AH$6,2), $J37:$U37, VALUE(RIGHT($J$6:$U$6,2))), 0)}
D38: Volume Growth | K38: =IFERROR(K37/J37-1, 0) | L38: =IFERROR(L37/K37-1, 0) | M38: =IFERROR(M37/L37-1, 0) | N38: =IFERROR(N37/M37-1, 0) | O38: =IFERROR(O37/N37-1, 0) | P38: =IFERROR(P37/O37-1, 0) | Q38: =IFERROR(Q37/P37-1, 0) | R38: =IFERROR(R37/Q37-1, 0) | ... U38: =IFERROR(U37/T37-1, 0) | Y38: =IFERROR(Y37/U37-1, 0) | Z38: =IFERROR(Z37/Y37-1, 0) | AA38: =IFERROR(AA37/Z37-1, 0) | AB38: =IFERROR(AB37/AA37-1, 0) | AC38: =IFERROR(AC37/AB37-1, 0) | AD38: =IFERROR(AD37/AC37-1, 0) | AE38: =IFERROR(AE37/AD37-1, 0) | AF38: =IFERROR(AF37/AE37-1, 0) | AG38: =IFERROR(AG37/AF37-1, 0) | AH38: =IFERROR(AH37/AG37-1, 0)
C40: Revenue / Unit | H40: ='Assumptions&Scenario'!$K$44 | J40: =IFERROR(J10*$H$37/J37, 0) | K40: =IFERROR(K10*$H$37/K37, 0) | L40: =IFERROR(L10*$H$37/L37, 0) | M40: =IFERROR(M10*$H$37/M37, 0) | N40: =IFERROR(N10*$H$37/N37, 0) | O40: =IFERROR(O10*$H$37/O37, 0) | P40: =IFERROR(P10*$H$37/P37, 0) | Q40: =IFERROR(Q10*$H$37/Q37, 0) | ... U40: =IFERROR(U10*$H$37/U37, 0) | Y40: =IFERROR(Y10*$H$37/Y37, 0) | Z40: =IFERROR(Z10*$H$37/Z37, 0) | AA40: =IFERROR(AA10*$H$37/AA37, 0) | AB40: =IFERROR(AB10*$H$37/AB37, 0) | AC40: =IFERROR(AC10*$H$37/AC37, 0) | AD40: =IFERROR(AD10*$H$37/AD37, 0) | AE40: =IFERROR(AE10*$H$37/AE37, 0) | AF40: =IFERROR(AF10*$H$37/AF37, 0) | ... AH40: =IFERROR(AH10*$H$37/AH37, 0)
D41: Price Growth | K41: =IFERROR(K40/J40-1, 0) | L41: =IFERROR(L40/K40-1, 0) | M41: =IFERROR(M40/L40-1, 0) | N41: =IFERROR(N40/M40-1, 0) | O41: =IFERROR(O40/N40-1, 0) | P41: =IFERROR(P40/O40-1, 0) | Q41: =IFERROR(Q40/P40-1, 0) | R41: =IFERROR(R40/Q40-1, 0) | ... U41: =IFERROR(U40/T40-1, 0) | Y41: =IFERROR(Y40/U40-1, 0) | Z41: =IFERROR(Z40/Y40-1, 0) | AA41: =IFERROR(AA40/Z40-1, 0) | AB41: =IFERROR(AB40/AA40-1, 0) | AC41: =IFERROR(AC40/AB40-1, 0) | AD41: =IFERROR(AD40/AC40-1, 0) | AE41: =IFERROR(AE40/AD40-1, 0) | AF41: =IFERROR(AF40/AE40-1, 0) | AG41: =IFERROR(AG40/AF40-1, 0) | AH41: =IFERROR(AH40/AG40-1, 0)
B45: ='Assumptions&Scenario'!$K$10
B46: Annual Other Information History | Y46: Annual Other Information Forecast
C48: FIN Years | J48: ="FY"&TEXT(RIGHT(K48,2)-(COLUMN(K48)-COLUMN()),"00") | K48: ="FY"&TEXT(RIGHT(L48,2)-(COLUMN(L48)-COLUMN()),"00") | L48: ="FY"&TEXT(RIGHT(M48,2)-(COLUMN(M48)-COLUMN()),"00") | M48: ="FY"&TEXT(RIGHT(N48,2)-(COLUMN(N48)-COLUMN()),"00") | N48: ="FY"&TEXT(RIGHT(O48,2)-(COLUMN(O48)-COLUMN()),"00") | O48: ="FY"&TEXT(RIGHT(P48,2)-(COLUMN(P48)-COLUMN()),"00") | P48: ="FY"&TEXT(RIGHT(Q48,2)-(COLUMN(Q48)-COLUMN()),"00") | Q48: ="FY"&TEXT(RIGHT(R48,2)-(COLUMN(R48)-COLUMN()),"00") | ... T48: ="FY"&TEXT(RIGHT(U48,2)-(COLUMN(U48)-COLUMN()),"00") | U48: ="FY"&TEXT(DATE(YEAR('Data Sheet'!$K$16)+(MONTH('Data Sheet'!$K$16)>3),1,1),"YY") | Y48: =Model!$L$6 | Z48: ="FY"&TEXT(RIGHT(Y48,2)+COLUMN()-COLUMN(Y48),"00") | AA48: ="FY"&TEXT(RIGHT(Z48,2)+COLUMN()-COLUMN(Z48),"00") | AB48: ="FY"&TEXT(RIGHT(AA48,2)+COLUMN()-COLUMN(AA48),"00") | AC48: ="FY"&TEXT(RIGHT(AB48,2)+COLUMN()-COLUMN(AB48),"00") | AD48: ="FY"&TEXT(RIGHT(AC48,2)+COLUMN()-COLUMN(AC48),"00") | AE48: ="FY"&TEXT(RIGHT(AD48,2)+COLUMN()-COLUMN(AD48),"00") | AF48: ="FY"&TEXT(RIGHT(AE48,2)+COLUMN()-COLUMN(AE48),"00") | AG48: ="FY"&TEXT(RIGHT(AF48,2)+COLUMN()-COLUMN(AF48),"00") | AH48: ="FY"&TEXT(RIGHT(AG48,2)+COLUMN()-COLUMN(AG48),"00")
B87: ='Assumptions&Scenario'!$K$10
B88: Quarterly Revenue Hisotry | Y88: Quarterly Revenue Forecast
J89: 1 | K89: 2 | L89: 2 | M89: 4 | N89: 5 | O89: 6 | P89: 7 | Q89: 8 | R89: 9 | S89: 10 | T89: 11 | U89: 12 | Y89: 13 | Z89: 14 | AA89: 15 | AB89: 16 | AC89: 17 | AD89: 18 | AE89: 19 | AF89: 20 | AG89: 21 | AH89: 22
C90: Quarters | J90: ="FY"&TEXT(MID(K90,3,2)-IF(RIGHT(K90,1)="1",1,0),"00")&"Q"&CHOOSE(RIGHT(K90,1)+0,4,1,2,3) | K90: ="FY"&TEXT(MID(L90,3,2)-IF(RIGHT(L90,1)="1",1,0),"00")&"Q"&CHOOSE(RIGHT(L90,1)+0,4,1,2,3) | L90: ="FY"&TEXT(MID(M90,3,2)-IF(RIGHT(M90,1)="1",1,0),"00")&"Q"&CHOOSE(RIGHT(M90,1)+0,4,1,2,3) | M90: ="FY"&TEXT(MID(N90,3,2)-IF(RIGHT(N90,1)="1",1,0),"00")&"Q"&CHOOSE(RIGHT(N90,1)+0,4,1,2,3) | N90: ="FY"&TEXT(MID(O90,3,2)-IF(RIGHT(O90,1)="1",1,0),"00")&"Q"&CHOOSE(RIGHT(O90,1)+0,4,1,2,3) | O90: ="FY"&TEXT(MID(P90,3,2)-IF(RIGHT(P90,1)="1",1,0),"00")&"Q"&CHOOSE(RIGHT(P90,1)+0,4,1,2,3) | P90: ="FY"&TEXT(MID(Q90,3,2)-IF(RIGHT(Q90,1)="1",1,0),"00")&"Q"&CHOOSE(RIGHT(Q90,1)+0,4,1,2,3) | Q90: ="FY"&TEXT(MID(R90,3,2)-IF(RIGHT(R90,1)="1",1,0),"00")&"Q"&CHOOSE(RIGHT(R90,1)+0,4,1,2,3) | ... T90: ="FY"&TEXT(MID(U90,3,2)-IF(RIGHT(U90,1)="1",1,0),"00")&"Q"&CHOOSE(RIGHT(U90,1)+0,4,1,2,3) | U90: ="FY"&TEXT(YEAR('Data Sheet'!$K$41)+(MONTH('Data Sheet'!$K$41)>3)-2000,"00")&"Q"&INT((MOD(MONTH('Data Sheet'!$K$41)-4,12))/3)+1 | Y90: =Model!$N$31 | Z90: ="FY"&TEXT(MID(Y90,3,2)+IF(RIGHT(Y90,1)="4",1,0),"00")&"Q"&MOD(RIGHT(Y90,1),4)+1 | AA90: ="FY"&TEXT(MID(Z90,3,2)+IF(RIGHT(Z90,1)="4",1,0),"00")&"Q"&MOD(RIGHT(Z90,1),4)+1 | AB90: ="FY"&TEXT(MID(AA90,3,2)+IF(RIGHT(AA90,1)="4",1,0),"00")&"Q"&MOD(RIGHT(AA90,1),4)+1 | AC90: ="FY"&TEXT(MID(AB90,3,2)+IF(RIGHT(AB90,1)="4",1,0),"00")&"Q"&MOD(RIGHT(AB90,1),4)+1 | AD90: ="FY"&TEXT(MID(AC90,3,2)+IF(RIGHT(AC90,1)="4",1,0),"00")&"Q"&MOD(RIGHT(AC90,1),4)+1 | AE90: ="FY"&TEXT(MID(AD90,3,2)+IF(RIGHT(AD90,1)="4",1,0),"00")&"Q"&MOD(RIGHT(AD90,1),4)+1 | AF90: ="FY"&TEXT(MID(AE90,3,2)+IF(RIGHT(AE90,1)="4",1,0),"00")&"Q"&MOD(RIGHT(AE90,1),4)+1 | AG90: ="FY"&TEXT(MID(AF90,3,2)+IF(RIGHT(AF90,1)="4",1,0),"00")&"Q"&MOD(RIGHT(AF90,1),4)+1 | AH90: ="FY"&TEXT(MID(AG90,3,2)+IF(RIGHT(AG90,1)="4",1,0),"00")&"Q"&MOD(RIGHT(AG90,1),4)+1
C94: Revenue | H94: =$H$10 | L94: =IFERROR('Data Sheet'!B42, 0) | M94: =IFERROR('Data Sheet'!C42, 0) | N94: =IFERROR('Data Sheet'!D42, 0) | O94: =IFERROR('Data Sheet'!E42, 0) | P94: =IFERROR('Data Sheet'!F42, 0) | Q94: =IFERROR('Data Sheet'!G42, 0) | R94: =IFERROR('Data Sheet'!H42, 0) | S94: =IFERROR('Data Sheet'!I42, 0) | ... U94: =IFERROR('Data Sheet'!K42, 0) | Y94: =IFERROR(_xlfn.FORECAST.LINEAR(Y$89, $J94:$U94, $J$89:$U$89), 0) | Z94: =IFERROR(_xlfn.FORECAST.LINEAR(Z$89, $J94:$U94, $J$89:$U$89), 0) | AA94: =IFERROR(_xlfn.FORECAST.LINEAR(AA$89, $J94:$U94, $J$89:$U$89), 0) | AB94: =IFERROR(_xlfn.FORECAST.LINEAR(AB$89, $J94:$U94, $J$89:$U$89), 0) | AC94: =IFERROR(_xlfn.FORECAST.LINEAR(AC$89, $J94:$U94, $J$89:$U$89), 0) | AD94: =IFERROR(_xlfn.FORECAST.LINEAR(AD$89, $J94:$U94, $J$89:$U$89), 0) | AE94: =IFERROR(_xlfn.FORECAST.LINEAR(AE$89, $J94:$U94, $J$89:$U$89), 0) | AF94: =IFERROR(_xlfn.FORECAST.LINEAR(AF$89, $J94:$U94, $J$89:$U$89), 0) | ... AH94: =IFERROR(_xlfn.FORECAST.LINEAR(AH$89, $J94:$U94, $J$89:$U$89), 0)
D95: Revenue Growth | N95: =IFERROR(N94/J94-1, 0) | O95: =IFERROR(O94/K94-1, 0) | P95: =IFERROR(P94/L94-1, 0) | Q95: =IFERROR(Q94/M94-1, 0) | R95: =IFERROR(R94/N94-1, 0) | S95: =IFERROR(S94/O94-1, 0) | T95: =IFERROR(T94/P94-1, 0) | U95: =IFERROR(U94/Q94-1, 0) | Y95: =IFERROR(Y94/R94-1, 0) | Z95: =IFERROR(Z94/S94-1, 0) | AA95: =IFERROR(AA94/T94-1, 0) | AB95: =IFERROR(AB94/U94-1, 0) | AC95: =IFERROR(AC94/Y94-1, 0) | AD95: =IFERROR(AD94/Z94-1, 0) | AE95: =IFERROR(AE94/AA94-1, 0) | AF95: =IFERROR(AF94/AB94-1, 0) | AG95: =IFERROR(AG94/AC94-1, 0) | AH95: =IFERROR(AH94/AD94-1, 0)
C97: Segmental Revenue | H97: =$H$13
D98: =D14 | Y98: =IFERROR(_xlfn.FORECAST.LINEAR(Y$89, $J98:$U98, $J$89:$U$89), 0) | Z98: =IFERROR(_xlfn.FORECAST.LINEAR(Z$89, $J98:$U98, $J$89:$U$89), 0) | AA98: =IFERROR(_xlfn.FORECAST.LINEAR(AA$89, $J98:$U98, $J$89:$U$89), 0) | AB98: =IFERROR(_xlfn.FORECAST.LINEAR(AB$89, $J98:$U98, $J$89:$U$89), 0) | AC98: =IFERROR(_xlfn.FORECAST.LINEAR(AC$89, $J98:$U98, $J$89:$U$89), 0) | AD98: =IFERROR(_xlfn.FORECAST.LINEAR(AD$89, $J98:$U98, $J$89:$U$89), 0) | AE98: =IFERROR(_xlfn.FORECAST.LINEAR(AE$89, $J98:$U98, $J$89:$U$89), 0) | AF98: =IFERROR(_xlfn.FORECAST.LINEAR(AF$89, $J98:$U98, $J$89:$U$89), 0) | ... AH98: =IFERROR(_xlfn.FORECAST.LINEAR(AH$89, $J98:$U98, $J$89:$U$89), 0)
D99: =D15 | Y99: =IFERROR(_xlfn.FORECAST.LINEAR(Y$89, $J99:$U99, $J$89:$U$89), 0) | Z99: =IFERROR(_xlfn.FORECAST.LINEAR(Z$89, $J99:$U99, $J$89:$U$89), 0) | AA99: =IFERROR(_xlfn.FORECAST.LINEAR(AA$89, $J99:$U99, $J$89:$U$89), 0) | AB99: =IFERROR(_xlfn.FORECAST.LINEAR(AB$89, $J99:$U99, $J$89:$U$89), 0) | AC99: =IFERROR(_xlfn.FORECAST.LINEAR(AC$89, $J99:$U99, $J$89:$U$89), 0) | AD99: =IFERROR(_xlfn.FORECAST.LINEAR(AD$89, $J99:$U99, $J$89:$U$89), 0) | AE99: =IFERROR(_xlfn.FORECAST.LINEAR(AE$89, $J99:$U99, $J$89:$U$89), 0) | AF99: =IFERROR(_xlfn.FORECAST.LINEAR(AF$89, $J99:$U99, $J$89:$U$89), 0) | ... AH99: =IFERROR(_xlfn.FORECAST.LINEAR(AH$89, $J99:$U99, $J$89:$U$89), 0)
D100: =D16 | Y100: =IFERROR(_xlfn.FORECAST.LINEAR(Y$89, $J100:$U100, $J$89:$U$89), 0) | Z100: =IFERROR(_xlfn.FORECAST.LINEAR(Z$89, $J100:$U100, $J$89:$U$89), 0) | AA100: =IFERROR(_xlfn.FORECAST.LINEAR(AA$89, $J100:$U100, $J$89:$U$89), 0) | AB100: =IFERROR(_xlfn.FORECAST.LINEAR(AB$89, $J100:$U100, $J$89:$U$89), 0) | AC100: =IFERROR(_xlfn.FORECAST.LINEAR(AC$89, $J100:$U100, $J$89:$U$89), 0) | AD100: =IFERROR(_xlfn.FORECAST.LINEAR(AD$89, $J100:$U100, $J$89:$U$89), 0) | AE100: =IFERROR(_xlfn.FORECAST.LINEAR(AE$89, $J100:$U100, $J$89:$U$89), 0) | AF100: =IFERROR(_xlfn.FORECAST.LINEAR(AF$89, $J100:$U100, $J$89:$U$89), 0) | ... AH100: =IFERROR(_xlfn.FORECAST.LINEAR(AH$89, $J100:$U100, $J$89:$U$89), 0)
D101: =D17 | Y101: =IFERROR(_xlfn.FORECAST.LINEAR(Y$89, $J101:$U101, $J$89:$U$89), 0) | Z101: =IFERROR(_xlfn.FORECAST.LINEAR(Z$89, $J101:$U101, $J$89:$U$89), 0) | AA101: =IFERROR(_xlfn.FORECAST.LINEAR(AA$89, $J101:$U101, $J$89:$U$89), 0) | AB101: =IFERROR(_xlfn.FORECAST.LINEAR(AB$89, $J101:$U101, $J$89:$U$89), 0) | AC101: =IFERROR(_xlfn.FORECAST.LINEAR(AC$89, $J101:$U101, $J$89:$U$89), 0) | AD101: =IFERROR(_xlfn.FORECAST.LINEAR(AD$89, $J101:$U101, $J$89:$U$89), 0) | AE101: =IFERROR(_xlfn.FORECAST.LINEAR(AE$89, $J101:$U101, $J$89:$U$89), 0) | AF101: =IFERROR(_xlfn.FORECAST.LINEAR(AF$89, $J101:$U101, $J$89:$U$89), 0) | ... AH101: =IFERROR(_xlfn.FORECAST.LINEAR(AH$89, $J101:$U101, $J$89:$U$89), 0)
D102: =D18 | Y102: =IFERROR(_xlfn.FORECAST.LINEAR(Y$89, $J102:$U102, $J$89:$U$89), 0) | Z102: =IFERROR(_xlfn.FORECAST.LINEAR(Z$89, $J102:$U102, $J$89:$U$89), 0) | AA102: =IFERROR(_xlfn.FORECAST.LINEAR(AA$89, $J102:$U102, $J$89:$U$89), 0) | AB102: =IFERROR(_xlfn.FORECAST.LINEAR(AB$89, $J102:$U102, $J$89:$U$89), 0) | AC102: =IFERROR(_xlfn.FORECAST.LINEAR(AC$89, $J102:$U102, $J$89:$U$89), 0) | AD102: =IFERROR(_xlfn.FORECAST.LINEAR(AD$89, $J102:$U102, $J$89:$U$89), 0) | AE102: =IFERROR(_xlfn.FORECAST.LINEAR(AE$89, $J102:$U102, $J$89:$U$89), 0) | AF102: =IFERROR(_xlfn.FORECAST.LINEAR(AF$89, $J102:$U102, $J$89:$U$89), 0) | ... AH102: =IFERROR(_xlfn.FORECAST.LINEAR(AH$89, $J102:$U102, $J$89:$U$89), 0)
D103: =D19 | Y103: =IFERROR(_xlfn.FORECAST.LINEAR(Y$89, $J103:$U103, $J$89:$U$89), 0) | Z103: =IFERROR(_xlfn.FORECAST.LINEAR(Z$89, $J103:$U103, $J$89:$U$89), 0) | AA103: =IFERROR(_xlfn.FORECAST.LINEAR(AA$89, $J103:$U103, $J$89:$U$89), 0) | AB103: =IFERROR(_xlfn.FORECAST.LINEAR(AB$89, $J103:$U103, $J$89:$U$89), 0) | AC103: =IFERROR(_xlfn.FORECAST.LINEAR(AC$89, $J103:$U103, $J$89:$U$89), 0) | AD103: =IFERROR(_xlfn.FORECAST.LINEAR(AD$89, $J103:$U103, $J$89:$U$89), 0) | AE103: =IFERROR(_xlfn.FORECAST.LINEAR(AE$89, $J103:$U103, $J$89:$U$89), 0) | AF103: =IFERROR(_xlfn.FORECAST.LINEAR(AF$89, $J103:$U103, $J$89:$U$89), 0) | ... AH103: =IFERROR(_xlfn.FORECAST.LINEAR(AH$89, $J103:$U103, $J$89:$U$89), 0)
D104: =D20 | Y104: =IFERROR(_xlfn.FORECAST.LINEAR(Y$89, $J104:$U104, $J$89:$U$89), 0) | Z104: =IFERROR(_xlfn.FORECAST.LINEAR(Z$89, $J104:$U104, $J$89:$U$89), 0) | AA104: =IFERROR(_xlfn.FORECAST.LINEAR(AA$89, $J104:$U104, $J$89:$U$89), 0) | AB104: =IFERROR(_xlfn.FORECAST.LINEAR(AB$89, $J104:$U104, $J$89:$U$89), 0) | AC104: =IFERROR(_xlfn.FORECAST.LINEAR(AC$89, $J104:$U104, $J$89:$U$89), 0) | AD104: =IFERROR(_xlfn.FORECAST.LINEAR(AD$89, $J104:$U104, $J$89:$U$89), 0) | AE104: =IFERROR(_xlfn.FORECAST.LINEAR(AE$89, $J104:$U104, $J$89:$U$89), 0) | AF104: =IFERROR(_xlfn.FORECAST.LINEAR(AF$89, $J104:$U104, $J$89:$U$89), 0) | ... AH104: =IFERROR(_xlfn.FORECAST.LINEAR(AH$89, $J104:$U104, $J$89:$U$89), 0)
D105: =D21 | Y105: =IFERROR(_xlfn.FORECAST.LINEAR(Y$89, $J105:$U105, $J$89:$U$89), 0) | Z105: =IFERROR(_xlfn.FORECAST.LINEAR(Z$89, $J105:$U105, $J$89:$U$89), 0) | AA105: =IFERROR(_xlfn.FORECAST.LINEAR(AA$89, $J105:$U105, $J$89:$U$89), 0) | AB105: =IFERROR(_xlfn.FORECAST.LINEAR(AB$89, $J105:$U105, $J$89:$U$89), 0) | AC105: =IFERROR(_xlfn.FORECAST.LINEAR(AC$89, $J105:$U105, $J$89:$U$89), 0) | AD105: =IFERROR(_xlfn.FORECAST.LINEAR(AD$89, $J105:$U105, $J$89:$U$89), 0) | AE105: =IFERROR(_xlfn.FORECAST.LINEAR(AE$89, $J105:$U105, $J$89:$U$89), 0) | AF105: =IFERROR(_xlfn.FORECAST.LINEAR(AF$89, $J105:$U105, $J$89:$U$89), 0) | ... AH105: =IFERROR(_xlfn.FORECAST.LINEAR(AH$89, $J105:$U105, $J$89:$U$89), 0)
D106: =D22 | Y106: =IFERROR(_xlfn.FORECAST.LINEAR(Y$89, $J106:$U106, $J$89:$U$89), 0) | Z106: =IFERROR(_xlfn.FORECAST.LINEAR(Z$89, $J106:$U106, $J$89:$U$89), 0) | AA106: =IFERROR(_xlfn.FORECAST.LINEAR(AA$89, $J106:$U106, $J$89:$U$89), 0) | AB106: =IFERROR(_xlfn.FORECAST.LINEAR(AB$89, $J106:$U106, $J$89:$U$89), 0) | AC106: =IFERROR(_xlfn.FORECAST.LINEAR(AC$89, $J106:$U106, $J$89:$U$89), 0) | AD106: =IFERROR(_xlfn.FORECAST.LINEAR(AD$89, $J106:$U106, $J$89:$U$89), 0) | AE106: =IFERROR(_xlfn.FORECAST.LINEAR(AE$89, $J106:$U106, $J$89:$U$89), 0) | AF106: =IFERROR(_xlfn.FORECAST.LINEAR(AF$89, $J106:$U106, $J$89:$U$89), 0) | ... AH106: =IFERROR(_xlfn.FORECAST.LINEAR(AH$89, $J106:$U106, $J$89:$U$89), 0)
D107: =D23 | Y107: =IFERROR(_xlfn.FORECAST.LINEAR(Y$89, $J107:$U107, $J$89:$U$89), 0) | Z107: =IFERROR(_xlfn.FORECAST.LINEAR(Z$89, $J107:$U107, $J$89:$U$89), 0) | AA107: =IFERROR(_xlfn.FORECAST.LINEAR(AA$89, $J107:$U107, $J$89:$U$89), 0) | AB107: =IFERROR(_xlfn.FORECAST.LINEAR(AB$89, $J107:$U107, $J$89:$U$89), 0) | AC107: =IFERROR(_xlfn.FORECAST.LINEAR(AC$89, $J107:$U107, $J$89:$U$89), 0) | AD107: =IFERROR(_xlfn.FORECAST.LINEAR(AD$89, $J107:$U107, $J$89:$U$89), 0) | AE107: =IFERROR(_xlfn.FORECAST.LINEAR(AE$89, $J107:$U107, $J$89:$U$89), 0) | AF107: =IFERROR(_xlfn.FORECAST.LINEAR(AF$89, $J107:$U107, $J$89:$U$89), 0) | ... AH107: =IFERROR(_xlfn.FORECAST.LINEAR(AH$89, $J107:$U107, $J$89:$U$89), 0)
D108: Segmental Revenue | J108: =SUM(J98:J107) | K108: =SUM(K98:K107) | L108: =SUM(L98:L107) | M108: =SUM(M98:M107) | N108: =SUM(N98:N107) | O108: =SUM(O98:O107) | P108: =SUM(P98:P107) | Q108: =SUM(Q98:Q107) | ... U108: =SUM(U98:U107) | Y108: =SUM(Y98:Y107) | Z108: =SUM(Z98:Z107) | AA108: =SUM(AA98:AA107) | AB108: =SUM(AB98:AB107) | AC108: =SUM(AC98:AC107) | AD108: =SUM(AD98:AD107) | AE108: =SUM(AE98:AE107) | AF108: =SUM(AF98:AF107) | ... AH108: =SUM(AH98:AH107)
C110: Geography Revenue | H110: =$H$26
D111: =D27 | Y111: =IFERROR(_xlfn.FORECAST.LINEAR(Y$89, $J111:$U111, $J$89:$U$89), 0) | Z111: =IFERROR(_xlfn.FORECAST.LINEAR(Z$89, $J111:$U111, $J$89:$U$89), 0) | AA111: =IFERROR(_xlfn.FORECAST.LINEAR(AA$89, $J111:$U111, $J$89:$U$89), 0) | AB111: =IFERROR(_xlfn.FORECAST.LINEAR(AB$89, $J111:$U111, $J$89:$U$89), 0) | AC111: =IFERROR(_xlfn.FORECAST.LINEAR(AC$89, $J111:$U111, $J$89:$U$89), 0) | AD111: =IFERROR(_xlfn.FORECAST.LINEAR(AD$89, $J111:$U111, $J$89:$U$89), 0) | AE111: =IFERROR(_xlfn.FORECAST.LINEAR(AE$89, $J111:$U111, $J$89:$U$89), 0) | AF111: =IFERROR(_xlfn.FORECAST.LINEAR(AF$89, $J111:$U111, $J$89:$U$89), 0) | ... AH111: =IFERROR(_xlfn.FORECAST.LINEAR(AH$89, $J111:$U111, $J$89:$U$89), 0)
D112: =D28 | Y112: =IFERROR(_xlfn.FORECAST.LINEAR(Y$89, $J112:$U112, $J$89:$U$89), 0) | Z112: =IFERROR(_xlfn.FORECAST.LINEAR(Z$89, $J112:$U112, $J$89:$U$89), 0) | AA112: =IFERROR(_xlfn.FORECAST.LINEAR(AA$89, $J112:$U112, $J$89:$U$89), 0) | AB112: =IFERROR(_xlfn.FORECAST.LINEAR(AB$89, $J112:$U112, $J$89:$U$89), 0) | AC112: =IFERROR(_xlfn.FORECAST.LINEAR(AC$89, $J112:$U112, $J$89:$U$89), 0) | AD112: =IFERROR(_xlfn.FORECAST.LINEAR(AD$89, $J112:$U112, $J$89:$U$89), 0) | AE112: =IFERROR(_xlfn.FORECAST.LINEAR(AE$89, $J112:$U112, $J$89:$U$89), 0) | AF112: =IFERROR(_xlfn.FORECAST.LINEAR(AF$89, $J112:$U112, $J$89:$U$89), 0) | ... AH112: =IFERROR(_xlfn.FORECAST.LINEAR(AH$89, $J112:$U112, $J$89:$U$89), 0)
D113: =D29 | Y113: =IFERROR(_xlfn.FORECAST.LINEAR(Y$89, $J113:$U113, $J$89:$U$89), 0) | Z113: =IFERROR(_xlfn.FORECAST.LINEAR(Z$89, $J113:$U113, $J$89:$U$89), 0) | AA113: =IFERROR(_xlfn.FORECAST.LINEAR(AA$89, $J113:$U113, $J$89:$U$89), 0) | AB113: =IFERROR(_xlfn.FORECAST.LINEAR(AB$89, $J113:$U113, $J$89:$U$89), 0) | AC113: =IFERROR(_xlfn.FORECAST.LINEAR(AC$89, $J113:$U113, $J$89:$U$89), 0) | AD113: =IFERROR(_xlfn.FORECAST.LINEAR(AD$89, $J113:$U113, $J$89:$U$89), 0) | AE113: =IFERROR(_xlfn.FORECAST.LINEAR(AE$89, $J113:$U113, $J$89:$U$89), 0) | AF113: =IFERROR(_xlfn.FORECAST.LINEAR(AF$89, $J113:$U113, $J$89:$U$89), 0) | ... AH113: =IFERROR(_xlfn.FORECAST.LINEAR(AH$89, $J113:$U113, $J$89:$U$89), 0)
D114: =D30 | Y114: =IFERROR(_xlfn.FORECAST.LINEAR(Y$89, $J114:$U114, $J$89:$U$89), 0) | Z114: =IFERROR(_xlfn.FORECAST.LINEAR(Z$89, $J114:$U114, $J$89:$U$89), 0) | AA114: =IFERROR(_xlfn.FORECAST.LINEAR(AA$89, $J114:$U114, $J$89:$U$89), 0) | AB114: =IFERROR(_xlfn.FORECAST.LINEAR(AB$89, $J114:$U114, $J$89:$U$89), 0) | AC114: =IFERROR(_xlfn.FORECAST.LINEAR(AC$89, $J114:$U114, $J$89:$U$89), 0) | AD114: =IFERROR(_xlfn.FORECAST.LINEAR(AD$89, $J114:$U114, $J$89:$U$89), 0) | AE114: =IFERROR(_xlfn.FORECAST.LINEAR(AE$89, $J114:$U114, $J$89:$U$89), 0) | AF114: =IFERROR(_xlfn.FORECAST.LINEAR(AF$89, $J114:$U114, $J$89:$U$89), 0) | ... AH114: =IFERROR(_xlfn.FORECAST.LINEAR(AH$89, $J114:$U114, $J$89:$U$89), 0)
D115: =D31 | Y115: =IFERROR(_xlfn.FORECAST.LINEAR(Y$89, $J115:$U115, $J$89:$U$89), 0) | Z115: =IFERROR(_xlfn.FORECAST.LINEAR(Z$89, $J115:$U115, $J$89:$U$89), 0) | AA115: =IFERROR(_xlfn.FORECAST.LINEAR(AA$89, $J115:$U115, $J$89:$U$89), 0) | AB115: =IFERROR(_xlfn.FORECAST.LINEAR(AB$89, $J115:$U115, $J$89:$U$89), 0) | AC115: =IFERROR(_xlfn.FORECAST.LINEAR(AC$89, $J115:$U115, $J$89:$U$89), 0) | AD115: =IFERROR(_xlfn.FORECAST.LINEAR(AD$89, $J115:$U115, $J$89:$U$89), 0) | AE115: =IFERROR(_xlfn.FORECAST.LINEAR(AE$89, $J115:$U115, $J$89:$U$89), 0) | AF115: =IFERROR(_xlfn.FORECAST.LINEAR(AF$89, $J115:$U115, $J$89:$U$89), 0) | ... AH115: =IFERROR(_xlfn.FORECAST.LINEAR(AH$89, $J115:$U115, $J$89:$U$89), 0)
D116: =D32 | Y116: =IFERROR(_xlfn.FORECAST.LINEAR(Y$89, $J116:$U116, $J$89:$U$89), 0) | Z116: =IFERROR(_xlfn.FORECAST.LINEAR(Z$89, $J116:$U116, $J$89:$U$89), 0) | AA116: =IFERROR(_xlfn.FORECAST.LINEAR(AA$89, $J116:$U116, $J$89:$U$89), 0) | AB116: =IFERROR(_xlfn.FORECAST.LINEAR(AB$89, $J116:$U116, $J$89:$U$89), 0) | AC116: =IFERROR(_xlfn.FORECAST.LINEAR(AC$89, $J116:$U116, $J$89:$U$89), 0) | AD116: =IFERROR(_xlfn.FORECAST.LINEAR(AD$89, $J116:$U116, $J$89:$U$89), 0) | AE116: =IFERROR(_xlfn.FORECAST.LINEAR(AE$89, $J116:$U116, $J$89:$U$89), 0) | AF116: =IFERROR(_xlfn.FORECAST.LINEAR(AF$89, $J116:$U116, $J$89:$U$89), 0) | ... AH116: =IFERROR(_xlfn.FORECAST.LINEAR(AH$89, $J116:$U116, $J$89:$U$89), 0)
D117: =D33 | Y117: =IFERROR(_xlfn.FORECAST.LINEAR(Y$89, $J117:$U117, $J$89:$U$89), 0) | Z117: =IFERROR(_xlfn.FORECAST.LINEAR(Z$89, $J117:$U117, $J$89:$U$89), 0) | AA117: =IFERROR(_xlfn.FORECAST.LINEAR(AA$89, $J117:$U117, $J$89:$U$89), 0) | AB117: =IFERROR(_xlfn.FORECAST.LINEAR(AB$89, $J117:$U117, $J$89:$U$89), 0) | AC117: =IFERROR(_xlfn.FORECAST.LINEAR(AC$89, $J117:$U117, $J$89:$U$89), 0) | AD117: =IFERROR(_xlfn.FORECAST.LINEAR(AD$89, $J117:$U117, $J$89:$U$89), 0) | AE117: =IFERROR(_xlfn.FORECAST.LINEAR(AE$89, $J117:$U117, $J$89:$U$89), 0) | AF117: =IFERROR(_xlfn.FORECAST.LINEAR(AF$89, $J117:$U117, $J$89:$U$89), 0) | ... AH117: =IFERROR(_xlfn.FORECAST.LINEAR(AH$89, $J117:$U117, $J$89:$U$89), 0)
D118: =D34 | Y118: =IFERROR(_xlfn.FORECAST.LINEAR(Y$89, $J118:$U118, $J$89:$U$89), 0) | Z118: =IFERROR(_xlfn.FORECAST.LINEAR(Z$89, $J118:$U118, $J$89:$U$89), 0) | AA118: =IFERROR(_xlfn.FORECAST.LINEAR(AA$89, $J118:$U118, $J$89:$U$89), 0) | AB118: =IFERROR(_xlfn.FORECAST.LINEAR(AB$89, $J118:$U118, $J$89:$U$89), 0) | AC118: =IFERROR(_xlfn.FORECAST.LINEAR(AC$89, $J118:$U118, $J$89:$U$89), 0) | AD118: =IFERROR(_xlfn.FORECAST.LINEAR(AD$89, $J118:$U118, $J$89:$U$89), 0) | AE118: =IFERROR(_xlfn.FORECAST.LINEAR(AE$89, $J118:$U118, $J$89:$U$89), 0) | AF118: =IFERROR(_xlfn.FORECAST.LINEAR(AF$89, $J118:$U118, $J$89:$U$89), 0) | ... AH118: =IFERROR(_xlfn.FORECAST.LINEAR(AH$89, $J118:$U118, $J$89:$U$89), 0)
D119: Geography Revenue | J119: =SUM(J111:J118) | K119: =SUM(K111:K118) | L119: =SUM(L111:L118) | M119: =SUM(M111:M118) | N119: =SUM(N111:N118) | O119: =SUM(O111:O118) | P119: =SUM(P111:P118) | Q119: =SUM(Q111:Q118) | ... U119: =SUM(U111:U118) | Y119: =SUM(Y111:Y118) | Z119: =SUM(Z111:Z118) | AA119: =SUM(AA111:AA118) | AB119: =SUM(AB111:AB118) | AC119: =SUM(AC111:AC118) | AD119: =SUM(AD111:AD118) | AE119: =SUM(AE111:AE118) | AF119: =SUM(AF111:AF118) | ... AH119: =SUM(AH111:AH118)
C121: =$C$37 | H121: =H37 | L121: =L94 | M121: =M94 | N121: =N94 | O121: =O94 | P121: =P94 | Q121: =Q94 | R121: =R94 | S121: =S94 | ... U121: =U94 | Y121: =IFERROR(_xlfn.FORECAST.LINEAR(Y$89, $J121:$U121, $J$89:$U$89), 0) | Z121: =IFERROR(_xlfn.FORECAST.LINEAR(Z$89, $J121:$U121, $J$89:$U$89), 0) | AA121: =IFERROR(_xlfn.FORECAST.LINEAR(AA$89, $J121:$U121, $J$89:$U$89), 0) | AB121: =IFERROR(_xlfn.FORECAST.LINEAR(AB$89, $J121:$U121, $J$89:$U$89), 0) | AC121: =IFERROR(_xlfn.FORECAST.LINEAR(AC$89, $J121:$U121, $J$89:$U$89), 0) | AD121: =IFERROR(_xlfn.FORECAST.LINEAR(AD$89, $J121:$U121, $J$89:$U$89), 0) | AE121: =IFERROR(_xlfn.FORECAST.LINEAR(AE$89, $J121:$U121, $J$89:$U$89), 0) | AF121: =IFERROR(_xlfn.FORECAST.LINEAR(AF$89, $J121:$U121, $J$89:$U$89), 0) | ... AH121: =IFERROR(_xlfn.FORECAST.LINEAR(AH$89, $J121:$U121, $J$89:$U$89), 0)
D122: Volume Growth | N122: =IFERROR(N121/J121-1, 0) | O122: =IFERROR(O121/K121-1, 0) | P122: =IFERROR(P121/L121-1, 0) | Q122: =IFERROR(Q121/M121-1, 0) | R122: =IFERROR(R121/N121-1, 0) | S122: =IFERROR(S121/O121-1, 0) | T122: =IFERROR(T121/P121-1, 0) | U122: =IFERROR(U121/Q121-1, 0) | Y122: =IFERROR(Y121/R121-1, 0) | Z122: =IFERROR(Z121/S121-1, 0) | AA122: =IFERROR(AA121/T121-1, 0) | AB122: =IFERROR(AB121/U121-1, 0) | AC122: =IFERROR(AC121/Y121-1, 0) | AD122: =IFERROR(AD121/Z121-1, 0) | AE122: =IFERROR(AE121/AA121-1, 0) | AF122: =IFERROR(AF121/AB121-1, 0) | AG122: =IFERROR(AG121/AC121-1, 0) | AH122: =IFERROR(AH121/AD121-1, 0)
C124: Revenue / Unit | H124: ='Assumptions&Scenario'!K44 | J124: =IFERROR(J94*$H$37/J121, 0) | K124: =IFERROR(K94*$H$37/K121, 0) | L124: =IFERROR(L94*$H$37/L121, 0) | M124: =IFERROR(M94*$H$37/M121, 0) | N124: =IFERROR(N94*$H$37/N121, 0) | O124: =IFERROR(O94*$H$37/O121, 0) | P124: =IFERROR(P94*$H$37/P121, 0) | Q124: =IFERROR(Q94*$H$37/Q121, 0) | ... U124: =IFERROR(U94*$H$37/U121, 0) | Y124: =IFERROR(Y94*$H$37/Y121, 0) | Z124: =IFERROR(Z94*$H$37/Z121, 0) | AA124: =IFERROR(AA94*$H$37/AA121, 0) | AB124: =IFERROR(AB94*$H$37/AB121, 0) | AC124: =IFERROR(AC94*$H$37/AC121, 0) | AD124: =IFERROR(AD94*$H$37/AD121, 0) | AE124: =IFERROR(AE94*$H$37/AE121, 0) | AF124: =IFERROR(AF94*$H$37/AF121, 0) | ... AH124: =IFERROR(AH94*$H$37/AH121, 0)
D125: Price Growth | N125: =IFERROR(N124/J124-1, 0) | O125: =IFERROR(O124/K124-1, 0) | P125: =IFERROR(P124/L124-1, 0) | Q125: =IFERROR(Q124/M124-1, 0) | R125: =IFERROR(R124/N124-1, 0) | S125: =IFERROR(S124/O124-1, 0) | T125: =IFERROR(T124/P124-1, 0) | U125: =IFERROR(U124/Q124-1, 0) | Y125: =IFERROR(Y124/R124-1, 0) | Z125: =IFERROR(Z124/S124-1, 0) | AA125: =IFERROR(AA124/T124-1, 0) | AB125: =IFERROR(AB124/U124-1, 0) | AC125: =IFERROR(AC124/Y124-1, 0) | AD125: =IFERROR(AD124/Z124-1, 0) | AE125: =IFERROR(AE124/AA124-1, 0) | AF125: =IFERROR(AF124/AB124-1, 0) | AG125: =IFERROR(AG124/AC124-1, 0) | AH125: =IFERROR(AH124/AD124-1, 0)
B129: ='Assumptions&Scenario'!$K$10
B130: Quarterly Other Information History | Y130: Quarterly Other Information Forecast
J131: 1 | K131: 2 | L131: 2 | M131: 4 | N131: 5 | O131: 6 | P131: 7 | Q131: 8 | R131: 9 | S131: 10 | T131: 11 | U131: 12 | Y131: 13 | Z131: 14 | AA131: 15 | AB131: 16 | AC131: 17 | AD131: 18 | AE131: 19 | AF131: 20 | AG131: 21 | AH131: 22
C132: Quarters | J132: ="FY"&TEXT(MID(K132,3,2)-IF(RIGHT(K132,1)="1",1,0),"00")&"Q"&CHOOSE(RIGHT(K132,1)+0,4,1,2,3) | K132: ="FY"&TEXT(MID(L132,3,2)-IF(RIGHT(L132,1)="1",1,0),"00")&"Q"&CHOOSE(RIGHT(L132,1)+0,4,1,2,3) | L132: ="FY"&TEXT(MID(M132,3,2)-IF(RIGHT(M132,1)="1",1,0),"00")&"Q"&CHOOSE(RIGHT(M132,1)+0,4,1,2,3) | M132: ="FY"&TEXT(MID(N132,3,2)-IF(RIGHT(N132,1)="1",1,0),"00")&"Q"&CHOOSE(RIGHT(N132,1)+0,4,1,2,3) | N132: ="FY"&TEXT(MID(O132,3,2)-IF(RIGHT(O132,1)="1",1,0),"00")&"Q"&CHOOSE(RIGHT(O132,1)+0,4,1,2,3) | O132: ="FY"&TEXT(MID(P132,3,2)-IF(RIGHT(P132,1)="1",1,0),"00")&"Q"&CHOOSE(RIGHT(P132,1)+0,4,1,2,3) | P132: ="FY"&TEXT(MID(Q132,3,2)-IF(RIGHT(Q132,1)="1",1,0),"00")&"Q"&CHOOSE(RIGHT(Q132,1)+0,4,1,2,3) | Q132: ="FY"&TEXT(MID(R132,3,2)-IF(RIGHT(R132,1)="1",1,0),"00")&"Q"&CHOOSE(RIGHT(R132,1)+0,4,1,2,3) | ... T132: ="FY"&TEXT(MID(U132,3,2)-IF(RIGHT(U132,1)="1",1,0),"00")&"Q"&CHOOSE(RIGHT(U132,1)+0,4,1,2,3) | U132: ="FY"&TEXT(YEAR('Data Sheet'!$K$41)+(MONTH('Data Sheet'!$K$41)>3)-2000,"00")&"Q"&INT((MOD(MONTH('Data Sheet'!$K$41)-4,12))/3)+1 | Y132: =Model!$N$31 | Z132: ="FY"&TEXT(MID(Y132,3,2)+IF(RIGHT(Y132,1)="4",1,0),"00")&"Q"&MOD(RIGHT(Y132,1),4)+1 | AA132: ="FY"&TEXT(MID(Z132,3,2)+IF(RIGHT(Z132,1)="4",1,0),"00")&"Q"&MOD(RIGHT(Z132,1),4)+1 | AB132: ="FY"&TEXT(MID(AA132,3,2)+IF(RIGHT(AA132,1)="4",1,0),"00")&"Q"&MOD(RIGHT(AA132,1),4)+1 | AC132: ="FY"&TEXT(MID(AB132,3,2)+IF(RIGHT(AB132,1)="4",1,0),"00")&"Q"&MOD(RIGHT(AB132,1),4)+1 | AD132: ="FY"&TEXT(MID(AC132,3,2)+IF(RIGHT(AC132,1)="4",1,0),"00")&"Q"&MOD(RIGHT(AC132,1),4)+1 | AE132: ="FY"&TEXT(MID(AD132,3,2)+IF(RIGHT(AD132,1)="4",1,0),"00")&"Q"&MOD(RIGHT(AD132,1),4)+1 | AF132: ="FY"&TEXT(MID(AE132,3,2)+IF(RIGHT(AE132,1)="4",1,0),"00")&"Q"&MOD(RIGHT(AE132,1),4)+1 | AG132: ="FY"&TEXT(MID(AF132,3,2)+IF(RIGHT(AF132,1)="4",1,0),"00")&"Q"&MOD(RIGHT(AF132,1),4)+1 | AH132: ="FY"&TEXT(MID(AG132,3,2)+IF(RIGHT(AG132,1)="4",1,0),"00")&"Q"&MOD(RIGHT(AG132,1),4)+1
B171: ='Assumptions&Scenario'!$K$10
B172: Annual Cost History | Y172: Annual Cost Forecast
C174: FIN Years | J174: ="FY"&TEXT(RIGHT(K174,2)-(COLUMN(K174)-COLUMN()),"00") | K174: ="FY"&TEXT(RIGHT(L174,2)-(COLUMN(L174)-COLUMN()),"00") | L174: ="FY"&TEXT(RIGHT(M174,2)-(COLUMN(M174)-COLUMN()),"00") | M174: ="FY"&TEXT(RIGHT(N174,2)-(COLUMN(N174)-COLUMN()),"00") | N174: ="FY"&TEXT(RIGHT(O174,2)-(COLUMN(O174)-COLUMN()),"00") | O174: ="FY"&TEXT(RIGHT(P174,2)-(COLUMN(P174)-COLUMN()),"00") | P174: ="FY"&TEXT(RIGHT(Q174,2)-(COLUMN(Q174)-COLUMN()),"00") | Q174: ="FY"&TEXT(RIGHT(R174,2)-(COLUMN(R174)-COLUMN()),"00") | ... T174: ="FY"&TEXT(RIGHT(U174,2)-(COLUMN(U174)-COLUMN()),"00") | U174: ="FY"&TEXT(DATE(YEAR('Data Sheet'!$K$16)+(MONTH('Data Sheet'!$K$16)>3),1,1),"YY") | Y174: =Model!$L$6 | Z174: ="FY"&TEXT(RIGHT(Y174,2)+COLUMN()-COLUMN(Y174),"00") | AA174: ="FY"&TEXT(RIGHT(Z174,2)+COLUMN()-COLUMN(Z174),"00") | AB174: ="FY"&TEXT(RIGHT(AA174,2)+COLUMN()-COLUMN(AA174),"00") | AC174: ="FY"&TEXT(RIGHT(AB174,2)+COLUMN()-COLUMN(AB174),"00") | AD174: ="FY"&TEXT(RIGHT(AC174,2)+COLUMN()-COLUMN(AC174),"00") | AE174: ="FY"&TEXT(RIGHT(AD174,2)+COLUMN()-COLUMN(AD174),"00") | AF174: ="FY"&TEXT(RIGHT(AE174,2)+COLUMN()-COLUMN(AE174),"00") | AG174: ="FY"&TEXT(RIGHT(AF174,2)+COLUMN()-COLUMN(AF174),"00") | AH174: ="FY"&TEXT(RIGHT(AG174,2)+COLUMN()-COLUMN(AG174),"00")
C178: =$C$37 | H178: =H121 | J178: =J37 | K178: =K37 | L178: =L37 | M178: =M37 | N178: =N37 | O178: =O37 | P178: =P37 | Q178: =Q37 | ... U178: =U37 | Y178: =Y37 | Z178: =Z37 | AA178: =AA37 | AB178: =AB37 | AC178: =AC37 | AD178: =AD37 | AE178: =AE37 | AF178: =AF37 | ... AH178: =AH37
C180: Variable Cost | H180: =$H$10
D181: ='Assumptions&Scenario'!D26 | L181: =IFERROR('Data Sheet'!B18+'Data Sheet'!B19, 0) | M181: =IFERROR('Data Sheet'!C18+'Data Sheet'!C19, 0) | N181: =IFERROR('Data Sheet'!D18+'Data Sheet'!D19, 0) | O181: =IFERROR('Data Sheet'!E18+'Data Sheet'!E19, 0) | P181: =IFERROR('Data Sheet'!F18+'Data Sheet'!F19, 0) | Q181: =IFERROR('Data Sheet'!G18+'Data Sheet'!G19, 0) | R181: =IFERROR('Data Sheet'!H18+'Data Sheet'!H19, 0) | S181: =IFERROR('Data Sheet'!I18+'Data Sheet'!I19, 0) | ... U181: =IFERROR('Data Sheet'!K18+'Data Sheet'!K19, 0) | Y181: {=IFERROR(_xlfn.FORECAST.LINEAR(RIGHT(Y$6,2), $J181:$U181, VALUE(RIGHT($J$6:$U$6,2))), 0)} | Z181: {=IFERROR(_xlfn.FORECAST.LINEAR(RIGHT(Z$6,2), $J181:$U181, VALUE(RIGHT($J$6:$U$6,2))), 0)} | AA181: {=IFERROR(_xlfn.FORECAST.LINEAR(RIGHT(AA$6,2), $J181:$U181, VALUE(RIGHT($J$6:$U$6,2))), 0)} | AB181: {=IFERROR(_xlfn.FORECAST.LINEAR(RIGHT(AB$6,2), $J181:$U181, VALUE(RIGHT($J$6:$U$6,2))), 0)} | AC181: {=IFERROR(_xlfn.FORECAST.LINEAR(RIGHT(AC$6,2), $J181:$U181, VALUE(RIGHT($J$6:$U$6,2))), 0)} | AD181: {=IFERROR(_xlfn.FORECAST.LINEAR(RIGHT(AD$6,2), $J181:$U181, VALUE(RIGHT($J$6:$U$6,2))), 0)} | AE181: {=IFERROR(_xlfn.FORECAST.LINEAR(RIGHT(AE$6,2), $J181:$U181, VALUE(RIGHT($J$6:$U$6,2))), 0)} | AF181: {=IFERROR(_xlfn.FORECAST.LINEAR(RIGHT(AF$6,2), $J181:$U181, VALUE(RIGHT($J$6:$U$6,2))), 0)} | ... AH181: {=IFERROR(_xlfn.FORECAST.LINEAR(RIGHT(AH$6,2), $J181:$U181, VALUE(RIGHT($J$6:$U$6,2))), 0)}
D182: ='Assumptions&Scenario'!D27 | L182: =IFERROR('Data Sheet'!B20, 0) | M182: =IFERROR('Data Sheet'!C20, 0) | N182: =IFERROR('Data Sheet'!D20, 0) | O182: =IFERROR('Data Sheet'!E20, 0) | P182: =IFERROR('Data Sheet'!F20, 0) | Q182: =IFERROR('Data Sheet'!G20, 0) | R182: =IFERROR('Data Sheet'!H20, 0) | S182: =IFERROR('Data Sheet'!I20, 0) | ... U182: =IFERROR('Data Sheet'!K20, 0) | Y182: {=IFERROR(_xlfn.FORECAST.LINEAR(RIGHT(Y$6,2), $J182:$U182, VALUE(RIGHT($J$6:$U$6,2))), 0)} | Z182: {=IFERROR(_xlfn.FORECAST.LINEAR(RIGHT(Z$6,2), $J182:$U182, VALUE(RIGHT($J$6:$U$6,2))), 0)} | AA182: {=IFERROR(_xlfn.FORECAST.LINEAR(RIGHT(AA$6,2), $J182:$U182, VALUE(RIGHT($J$6:$U$6,2))), 0)} | AB182: {=IFERROR(_xlfn.FORECAST.LINEAR(RIGHT(AB$6,2), $J182:$U182, VALUE(RIGHT($J$6:$U$6,2))), 0)} | AC182: {=IFERROR(_xlfn.FORECAST.LINEAR(RIGHT(AC$6,2), $J182:$U182, VALUE(RIGHT($J$6:$U$6,2))), 0)} | AD182: {=IFERROR(_xlfn.FORECAST.LINEAR(RIGHT(AD$6,2), $J182:$U182, VALUE(RIGHT($J$6:$U$6,2))), 0)} | AE182: {=IFERROR(_xlfn.FORECAST.LINEAR(RIGHT(AE$6,2), $J182:$U182, VALUE(RIGHT($J$6:$U$6,2))), 0)} | AF182: {=IFERROR(_xlfn.FORECAST.LINEAR(RIGHT(AF$6,2), $J182:$U182, VALUE(RIGHT($J$6:$U$6,2))), 0)} | ... AH182: {=IFERROR(_xlfn.FORECAST.LINEAR(RIGHT(AH$6,2), $J182:$U182, VALUE(RIGHT($J$6:$U$6,2))), 0)}
D183: ='Assumptions&Scenario'!D28 | L183: =IFERROR('Data Sheet'!B21, 0) | M183: =IFERROR('Data Sheet'!C21, 0) | N183: =IFERROR('Data Sheet'!D21, 0) | O183: =IFERROR('Data Sheet'!E21, 0) | P183: =IFERROR('Data Sheet'!F21, 0) | Q183: =IFERROR('Data Sheet'!G21, 0) | R183: =IFERROR('Data Sheet'!H21, 0) | S183: =IFERROR('Data Sheet'!I21, 0) | ... U183: =IFERROR('Data Sheet'!K21, 0) | Y183: {=IFERROR(_xlfn.FORECAST.LINEAR(RIGHT(Y$6,2), $J183:$U183, VALUE(RIGHT($J$6:$U$6,2))), 0)} | Z183: {=IFERROR(_xlfn.FORECAST.LINEAR(RIGHT(Z$6,2), $J183:$U183, VALUE(RIGHT($J$6:$U$6,2))), 0)} | AA183: {=IFERROR(_xlfn.FORECAST.LINEAR(RIGHT(AA$6,2), $J183:$U183, VALUE(RIGHT($J$6:$U$6,2))), 0)} | AB183: {=IFERROR(_xlfn.FORECAST.LINEAR(RIGHT(AB$6,2), $J183:$U183, VALUE(RIGHT($J$6:$U$6,2))), 0)} | AC183: {=IFERROR(_xlfn.FORECAST.LINEAR(RIGHT(AC$6,2), $J183:$U183, VALUE(RIGHT($J$6:$U$6,2))), 0)} | AD183: {=IFERROR(_xlfn.FORECAST.LINEAR(RIGHT(AD$6,2), $J183:$U183, VALUE(RIGHT($J$6:$U$6,2))), 0)} | AE183: {=IFERROR(_xlfn.FORECAST.LINEAR(RIGHT(AE$6,2), $J183:$U183, VALUE(RIGHT($J$6:$U$6,2))), 0)} | AF183: {=IFERROR(_xlfn.FORECAST.LINEAR(RIGHT(AF$6,2), $J183:$U183, VALUE(RIGHT($J$6:$U$6,2))), 0)} | ... AH183: {=IFERROR(_xlfn.FORECAST.LINEAR(RIGHT(AH$6,2), $J183:$U183, VALUE(RIGHT($J$6:$U$6,2))), 0)}
D184: ='Assumptions&Scenario'!D29 | Y184: {=IFERROR(_xlfn.FORECAST.LINEAR(RIGHT(Y$6,2), $J184:$U184, VALUE(RIGHT($J$6:$U$6,2))), 0)} | Z184: {=IFERROR(_xlfn.FORECAST.LINEAR(RIGHT(Z$6,2), $J184:$U184, VALUE(RIGHT($J$6:$U$6,2))), 0)} | AA184: {=IFERROR(_xlfn.FORECAST.LINEAR(RIGHT(AA$6,2), $J184:$U184, VALUE(RIGHT($J$6:$U$6,2))), 0)} | AB184: {=IFERROR(_xlfn.FORECAST.LINEAR(RIGHT(AB$6,2), $J184:$U184, VALUE(RIGHT($J$6:$U$6,2))), 0)} | AC184: {=IFERROR(_xlfn.FORECAST.LINEAR(RIGHT(AC$6,2), $J184:$U184, VALUE(RIGHT($J$6:$U$6,2))), 0)} | AD184: {=IFERROR(_xlfn.FORECAST.LINEAR(RIGHT(AD$6,2), $J184:$U184, VALUE(RIGHT($J$6:$U$6,2))), 0)} | AE184: {=IFERROR(_xlfn.FORECAST.LINEAR(RIGHT(AE$6,2), $J184:$U184, VALUE(RIGHT($J$6:$U$6,2))), 0)} | AF184: {=IFERROR(_xlfn.FORECAST.LINEAR(RIGHT(AF$6,2), $J184:$U184, VALUE(RIGHT($J$6:$U$6,2))), 0)} | ... AH184: {=IFERROR(_xlfn.FORECAST.LINEAR(RIGHT(AH$6,2), $J184:$U184, VALUE(RIGHT($J$6:$U$6,2))), 0)}
D185: ='Assumptions&Scenario'!D30 | Y185: {=IFERROR(_xlfn.FORECAST.LINEAR(RIGHT(Y$6,2), $J185:$U185, VALUE(RIGHT($J$6:$U$6,2))), 0)} | Z185: {=IFERROR(_xlfn.FORECAST.LINEAR(RIGHT(Z$6,2), $J185:$U185, VALUE(RIGHT($J$6:$U$6,2))), 0)} | AA185: {=IFERROR(_xlfn.FORECAST.LINEAR(RIGHT(AA$6,2), $J185:$U185, VALUE(RIGHT($J$6:$U$6,2))), 0)} | AB185: {=IFERROR(_xlfn.FORECAST.LINEAR(RIGHT(AB$6,2), $J185:$U185, VALUE(RIGHT($J$6:$U$6,2))), 0)} | AC185: {=IFERROR(_xlfn.FORECAST.LINEAR(RIGHT(AC$6,2), $J185:$U185, VALUE(RIGHT($J$6:$U$6,2))), 0)} | AD185: {=IFERROR(_xlfn.FORECAST.LINEAR(RIGHT(AD$6,2), $J185:$U185, VALUE(RIGHT($J$6:$U$6,2))), 0)} | AE185: {=IFERROR(_xlfn.FORECAST.LINEAR(RIGHT(AE$6,2), $J185:$U185, VALUE(RIGHT($J$6:$U$6,2))), 0)} | AF185: {=IFERROR(_xlfn.FORECAST.LINEAR(RIGHT(AF$6,2), $J185:$U185, VALUE(RIGHT($J$6:$U$6,2))), 0)} | ... AH185: {=IFERROR(_xlfn.FORECAST.LINEAR(RIGHT(AH$6,2), $J185:$U185, VALUE(RIGHT($J$6:$U$6,2))), 0)}
D186: Total Variable Cost | J186: =SUM(J181:J185) | K186: =SUM(K181:K185) | L186: =SUM(L181:L185) | M186: =SUM(M181:M185) | N186: =SUM(N181:N185) | O186: =SUM(O181:O185) | P186: =SUM(P181:P185) | Q186: =SUM(Q181:Q185) | ... U186: =SUM(U181:U185) | Y186: =SUM(Y181:Y185) | Z186: =SUM(Z181:Z185) | AA186: =SUM(AA181:AA185) | AB186: =SUM(AB181:AB185) | AC186: =SUM(AC181:AC185) | AD186: =SUM(AD181:AD185) | AE186: =SUM(AE181:AE185) | AF186: =SUM(AF181:AF185) | ... AH186: =SUM(AH181:AH185)
C188: Fixed Cost | H188: =$H$10
D189: ='Assumptions&Scenario'!P26 | L189: =IFERROR('Data Sheet'!B22, 0) | M189: =IFERROR('Data Sheet'!C22, 0) | N189: =IFERROR('Data Sheet'!D22, 0) | O189: =IFERROR('Data Sheet'!E22, 0) | P189: =IFERROR('Data Sheet'!F22, 0) | Q189: =IFERROR('Data Sheet'!G22, 0) | R189: =IFERROR('Data Sheet'!H22, 0) | S189: =IFERROR('Data Sheet'!I22, 0) | ... U189: =IFERROR('Data Sheet'!K22, 0) | Y189: {=IFERROR(_xlfn.FORECAST.LINEAR(RIGHT(Y$6,2), $J189:$U189, VALUE(RIGHT($J$6:$U$6,2))), 0)} | Z189: {=IFERROR(_xlfn.FORECAST.LINEAR(RIGHT(Z$6,2), $J189:$U189, VALUE(RIGHT($J$6:$U$6,2))), 0)} | AA189: {=IFERROR(_xlfn.FORECAST.LINEAR(RIGHT(AA$6,2), $J189:$U189, VALUE(RIGHT($J$6:$U$6,2))), 0)} | AB189: {=IFERROR(_xlfn.FORECAST.LINEAR(RIGHT(AB$6,2), $J189:$U189, VALUE(RIGHT($J$6:$U$6,2))), 0)} | AC189: {=IFERROR(_xlfn.FORECAST.LINEAR(RIGHT(AC$6,2), $J189:$U189, VALUE(RIGHT($J$6:$U$6,2))), 0)} | AD189: {=IFERROR(_xlfn.FORECAST.LINEAR(RIGHT(AD$6,2), $J189:$U189, VALUE(RIGHT($J$6:$U$6,2))), 0)} | AE189: {=IFERROR(_xlfn.FORECAST.LINEAR(RIGHT(AE$6,2), $J189:$U189, VALUE(RIGHT($J$6:$U$6,2))), 0)} | AF189: {=IFERROR(_xlfn.FORECAST.LINEAR(RIGHT(AF$6,2), $J189:$U189, VALUE(RIGHT($J$6:$U$6,2))), 0)} | ... AH189: {=IFERROR(_xlfn.FORECAST.LINEAR(RIGHT(AH$6,2), $J189:$U189, VALUE(RIGHT($J$6:$U$6,2))), 0)}
D190: ='Assumptions&Scenario'!P27 | Y190: {=IFERROR(_xlfn.FORECAST.LINEAR(RIGHT(Y$6,2), $J190:$U190, VALUE(RIGHT($J$6:$U$6,2))), 0)} | Z190: {=IFERROR(_xlfn.FORECAST.LINEAR(RIGHT(Z$6,2), $J190:$U190, VALUE(RIGHT($J$6:$U$6,2))), 0)} | AA190: {=IFERROR(_xlfn.FORECAST.LINEAR(RIGHT(AA$6,2), $J190:$U190, VALUE(RIGHT($J$6:$U$6,2))), 0)} | AB190: {=IFERROR(_xlfn.FORECAST.LINEAR(RIGHT(AB$6,2), $J190:$U190, VALUE(RIGHT($J$6:$U$6,2))), 0)} | AC190: {=IFERROR(_xlfn.FORECAST.LINEAR(RIGHT(AC$6,2), $J190:$U190, VALUE(RIGHT($J$6:$U$6,2))), 0)} | AD190: {=IFERROR(_xlfn.FORECAST.LINEAR(RIGHT(AD$6,2), $J190:$U190, VALUE(RIGHT($J$6:$U$6,2))), 0)} | AE190: {=IFERROR(_xlfn.FORECAST.LINEAR(RIGHT(AE$6,2), $J190:$U190, VALUE(RIGHT($J$6:$U$6,2))), 0)} | AF190: {=IFERROR(_xlfn.FORECAST.LINEAR(RIGHT(AF$6,2), $J190:$U190, VALUE(RIGHT($J$6:$U$6,2))), 0)} | ... AH190: {=IFERROR(_xlfn.FORECAST.LINEAR(RIGHT(AH$6,2), $J190:$U190, VALUE(RIGHT($J$6:$U$6,2))), 0)}
D191: ='Assumptions&Scenario'!P28 | Y191: {=IFERROR(_xlfn.FORECAST.LINEAR(RIGHT(Y$6,2), $J191:$U191, VALUE(RIGHT($J$6:$U$6,2))), 0)} | Z191: {=IFERROR(_xlfn.FORECAST.LINEAR(RIGHT(Z$6,2), $J191:$U191, VALUE(RIGHT($J$6:$U$6,2))), 0)} | AA191: {=IFERROR(_xlfn.FORECAST.LINEAR(RIGHT(AA$6,2), $J191:$U191, VALUE(RIGHT($J$6:$U$6,2))), 0)} | AB191: {=IFERROR(_xlfn.FORECAST.LINEAR(RIGHT(AB$6,2), $J191:$U191, VALUE(RIGHT($J$6:$U$6,2))), 0)} | AC191: {=IFERROR(_xlfn.FORECAST.LINEAR(RIGHT(AC$6,2), $J191:$U191, VALUE(RIGHT($J$6:$U$6,2))), 0)} | AD191: {=IFERROR(_xlfn.FORECAST.LINEAR(RIGHT(AD$6,2), $J191:$U191, VALUE(RIGHT($J$6:$U$6,2))), 0)} | AE191: {=IFERROR(_xlfn.FORECAST.LINEAR(RIGHT(AE$6,2), $J191:$U191, VALUE(RIGHT($J$6:$U$6,2))), 0)} | AF191: {=IFERROR(_xlfn.FORECAST.LINEAR(RIGHT(AF$6,2), $J191:$U191, VALUE(RIGHT($J$6:$U$6,2))), 0)} | ... AH191: {=IFERROR(_xlfn.FORECAST.LINEAR(RIGHT(AH$6,2), $J191:$U191, VALUE(RIGHT($J$6:$U$6,2))), 0)}
D192: ='Assumptions&Scenario'!P29 | L192: =IFERROR('Data Sheet'!B23, 0) | M192: =IFERROR('Data Sheet'!C23, 0) | N192: =IFERROR('Data Sheet'!D23, 0) | O192: =IFERROR('Data Sheet'!E23, 0) | P192: =IFERROR('Data Sheet'!F23, 0) | Q192: =IFERROR('Data Sheet'!G23, 0) | R192: =IFERROR('Data Sheet'!H23, 0) | S192: =IFERROR('Data Sheet'!I23, 0) | ... U192: =IFERROR('Data Sheet'!K23, 0) | Y192: {=IFERROR(_xlfn.FORECAST.LINEAR(RIGHT(Y$6,2), $J192:$U192, VALUE(RIGHT($J$6:$U$6,2))), 0)} | Z192: {=IFERROR(_xlfn.FORECAST.LINEAR(RIGHT(Z$6,2), $J192:$U192, VALUE(RIGHT($J$6:$U$6,2))), 0)} | AA192: {=IFERROR(_xlfn.FORECAST.LINEAR(RIGHT(AA$6,2), $J192:$U192, VALUE(RIGHT($J$6:$U$6,2))), 0)} | AB192: {=IFERROR(_xlfn.FORECAST.LINEAR(RIGHT(AB$6,2), $J192:$U192, VALUE(RIGHT($J$6:$U$6,2))), 0)} | AC192: {=IFERROR(_xlfn.FORECAST.LINEAR(RIGHT(AC$6,2), $J192:$U192, VALUE(RIGHT($J$6:$U$6,2))), 0)} | AD192: {=IFERROR(_xlfn.FORECAST.LINEAR(RIGHT(AD$6,2), $J192:$U192, VALUE(RIGHT($J$6:$U$6,2))), 0)} | AE192: {=IFERROR(_xlfn.FORECAST.LINEAR(RIGHT(AE$6,2), $J192:$U192, VALUE(RIGHT($J$6:$U$6,2))), 0)} | AF192: {=IFERROR(_xlfn.FORECAST.LINEAR(RIGHT(AF$6,2), $J192:$U192, VALUE(RIGHT($J$6:$U$6,2))), 0)} | ... AH192: {=IFERROR(_xlfn.FORECAST.LINEAR(RIGHT(AH$6,2), $J192:$U192, VALUE(RIGHT($J$6:$U$6,2))), 0)}
D193: ='Assumptions&Scenario'!P30 | L193: =IFERROR('Data Sheet'!B24, 0) | M193: =IFERROR('Data Sheet'!C24, 0) | N193: =IFERROR('Data Sheet'!D24, 0) | O193: =IFERROR('Data Sheet'!E24, 0) | P193: =IFERROR('Data Sheet'!F24, 0) | Q193: =IFERROR('Data Sheet'!G24, 0) | R193: =IFERROR('Data Sheet'!H24, 0) | S193: =IFERROR('Data Sheet'!I24, 0) | ... U193: =IFERROR('Data Sheet'!K24, 0) | Y193: {=IFERROR(_xlfn.FORECAST.LINEAR(RIGHT(Y$6,2), $J193:$U193, VALUE(RIGHT($J$6:$U$6,2))), 0)} | Z193: {=IFERROR(_xlfn.FORECAST.LINEAR(RIGHT(Z$6,2), $J193:$U193, VALUE(RIGHT($J$6:$U$6,2))), 0)} | AA193: {=IFERROR(_xlfn.FORECAST.LINEAR(RIGHT(AA$6,2), $J193:$U193, VALUE(RIGHT($J$6:$U$6,2))), 0)} | AB193: {=IFERROR(_xlfn.FORECAST.LINEAR(RIGHT(AB$6,2), $J193:$U193, VALUE(RIGHT($J$6:$U$6,2))), 0)} | AC193: {=IFERROR(_xlfn.FORECAST.LINEAR(RIGHT(AC$6,2), $J193:$U193, VALUE(RIGHT($J$6:$U$6,2))), 0)} | AD193: {=IFERROR(_xlfn.FORECAST.LINEAR(RIGHT(AD$6,2), $J193:$U193, VALUE(RIGHT($J$6:$U$6,2))), 0)} | AE193: {=IFERROR(_xlfn.FORECAST.LINEAR(RIGHT(AE$6,2), $J193:$U193, VALUE(RIGHT($J$6:$U$6,2))), 0)} | AF193: {=IFERROR(_xlfn.FORECAST.LINEAR(RIGHT(AF$6,2), $J193:$U193, VALUE(RIGHT($J$6:$U$6,2))), 0)} | ... AH193: {=IFERROR(_xlfn.FORECAST.LINEAR(RIGHT(AH$6,2), $J193:$U193, VALUE(RIGHT($J$6:$U$6,2))), 0)}
D194: Total Fixed Cost | J194: =SUM(J189:J193) | K194: =SUM(K189:K193) | L194: =SUM(L189:L193) | M194: =SUM(M189:M193) | N194: =SUM(N189:N193) | O194: =SUM(O189:O193) | P194: =SUM(P189:P193) | Q194: =SUM(Q189:Q193) | ... U194: =SUM(U189:U193) | Y194: =SUM(Y189:Y193) | Z194: =SUM(Z189:Z193) | AA194: =SUM(AA189:AA193) | AB194: =SUM(AB189:AB193) | AC194: =SUM(AC189:AC193) | AD194: =SUM(AD189:AD193) | AE194: =SUM(AE189:AE193) | AF194: =SUM(AF189:AF193) | ... AH194: =SUM(AH189:AH193)
C195: Total Cost | J195: =J194+J186 | K195: =K194+K186 | L195: =L194+L186 | M195: =M194+M186 | N195: =N194+N186 | O195: =O194+O186 | P195: =P194+P186 | Q195: =Q194+Q186 | ... U195: =U194+U186 | Y195: =Y194+Y186 | Z195: =Z194+Z186 | AA195: =AA194+AA186 | AB195: =AB194+AB186 | AC195: =AC194+AC186 | AD195: =AD194+AD186 | AE195: =AE194+AE186 | AF195: =AF194+AF186 | ... AH195: =AH194+AH186
D196: Cost Growth | K196: =IFERROR(K195/J195-1, 0) | L196: =IFERROR(L195/K195-1, 0) | M196: =IFERROR(M195/L195-1, 0) | N196: =IFERROR(N195/M195-1, 0) | O196: =IFERROR(O195/N195-1, 0) | P196: =IFERROR(P195/O195-1, 0) | Q196: =IFERROR(Q195/P195-1, 0) | R196: =IFERROR(R195/Q195-1, 0) | ... U196: =IFERROR(U195/T195-1, 0) | Y196: =IFERROR(Y195/U195-1, 0) | Z196: =IFERROR(Z195/Y195-1, 0) | AA196: =IFERROR(AA195/Z195-1, 0) | AB196: =IFERROR(AB195/AA195-1, 0) | AC196: =IFERROR(AC195/AB195-1, 0) | AD196: =IFERROR(AD195/AC195-1, 0) | AE196: =IFERROR(AE195/AD195-1, 0) | AF196: =IFERROR(AF195/AE195-1, 0) | AG196: =IFERROR(AG195/AF195-1, 0) | AH196: =IFERROR(AH195/AG195-1, 0)
C198: Variable Cost Per Unit | H198: ='Assumptions&Scenario'!$K$44
D199: =D181 | J199: =IFERROR(J181*$H$178/J$178, 0) | K199: =IFERROR(K181*$H$178/K$178, 0) | L199: =IFERROR(L181*$H$178/L$178, 0) | M199: =IFERROR(M181*$H$178/M$178, 0) | N199: =IFERROR(N181*$H$178/N$178, 0) | O199: =IFERROR(O181*$H$178/O$178, 0) | P199: =IFERROR(P181*$H$178/P$178, 0) | Q199: =IFERROR(Q181*$H$178/Q$178, 0) | ... U199: =IFERROR(U181*$H$178/U$178, 0) | Y199: =IFERROR(Y181*$H$178/Y$178, 0) | Z199: =IFERROR(Z181*$H$178/Z$178, 0) | AA199: =IFERROR(AA181*$H$178/AA$178, 0) | AB199: =IFERROR(AB181*$H$178/AB$178, 0) | AC199: =IFERROR(AC181*$H$178/AC$178, 0) | AD199: =IFERROR(AD181*$H$178/AD$178, 0) | AE199: =IFERROR(AE181*$H$178/AE$178, 0) | AF199: =IFERROR(AF181*$H$178/AF$178, 0) | ... AH199: =IFERROR(AH181*$H$178/AH$178, 0)
D200: =D182 | J200: =IFERROR(J182*$H$178/J$178, 0) | K200: =IFERROR(K182*$H$178/K$178, 0) | L200: =IFERROR(L182*$H$178/L$178, 0) | M200: =IFERROR(M182*$H$178/M$178, 0) | N200: =IFERROR(N182*$H$178/N$178, 0) | O200: =IFERROR(O182*$H$178/O$178, 0) | P200: =IFERROR(P182*$H$178/P$178, 0) | Q200: =IFERROR(Q182*$H$178/Q$178, 0) | ... U200: =IFERROR(U182*$H$178/U$178, 0) | Y200: =IFERROR(Y182*$H$178/Y$178, 0) | Z200: =IFERROR(Z182*$H$178/Z$178, 0) | AA200: =IFERROR(AA182*$H$178/AA$178, 0) | AB200: =IFERROR(AB182*$H$178/AB$178, 0) | AC200: =IFERROR(AC182*$H$178/AC$178, 0) | AD200: =IFERROR(AD182*$H$178/AD$178, 0) | AE200: =IFERROR(AE182*$H$178/AE$178, 0) | AF200: =IFERROR(AF182*$H$178/AF$178, 0) | ... AH200: =IFERROR(AH182*$H$178/AH$178, 0)
D201: =D183 | J201: =IFERROR(J183*$H$178/J$178, 0) | K201: =IFERROR(K183*$H$178/K$178, 0) | L201: =IFERROR(L183*$H$178/L$178, 0) | M201: =IFERROR(M183*$H$178/M$178, 0) | N201: =IFERROR(N183*$H$178/N$178, 0) | O201: =IFERROR(O183*$H$178/O$178, 0) | P201: =IFERROR(P183*$H$178/P$178, 0) | Q201: =IFERROR(Q183*$H$178/Q$178, 0) | ... U201: =IFERROR(U183*$H$178/U$178, 0) | Y201: =IFERROR(Y183*$H$178/Y$178, 0) | Z201: =IFERROR(Z183*$H$178/Z$178, 0) | AA201: =IFERROR(AA183*$H$178/AA$178, 0) | AB201: =IFERROR(AB183*$H$178/AB$178, 0) | AC201: =IFERROR(AC183*$H$178/AC$178, 0) | AD201: =IFERROR(AD183*$H$178/AD$178, 0) | AE201: =IFERROR(AE183*$H$178/AE$178, 0) | AF201: =IFERROR(AF183*$H$178/AF$178, 0) | ... AH201: =IFERROR(AH183*$H$178/AH$178, 0)
D202: =D184 | J202: =IFERROR(J184*$H$178/J$178, 0) | K202: =IFERROR(K184*$H$178/K$178, 0) | L202: =IFERROR(L184*$H$178/L$178, 0) | M202: =IFERROR(M184*$H$178/M$178, 0) | N202: =IFERROR(N184*$H$178/N$178, 0) | O202: =IFERROR(O184*$H$178/O$178, 0) | P202: =IFERROR(P184*$H$178/P$178, 0) | Q202: =IFERROR(Q184*$H$178/Q$178, 0) | ... U202: =IFERROR(U184*$H$178/U$178, 0) | Y202: =IFERROR(Y184*$H$178/Y$178, 0) | Z202: =IFERROR(Z184*$H$178/Z$178, 0) | AA202: =IFERROR(AA184*$H$178/AA$178, 0) | AB202: =IFERROR(AB184*$H$178/AB$178, 0) | AC202: =IFERROR(AC184*$H$178/AC$178, 0) | AD202: =IFERROR(AD184*$H$178/AD$178, 0) | AE202: =IFERROR(AE184*$H$178/AE$178, 0) | AF202: =IFERROR(AF184*$H$178/AF$178, 0) | ... AH202: =IFERROR(AH184*$H$178/AH$178, 0)
D203: =D185 | J203: =IFERROR(J185*$H$178/J$178, 0) | K203: =IFERROR(K185*$H$178/K$178, 0) | L203: =IFERROR(L185*$H$178/L$178, 0) | M203: =IFERROR(M185*$H$178/M$178, 0) | N203: =IFERROR(N185*$H$178/N$178, 0) | O203: =IFERROR(O185*$H$178/O$178, 0) | P203: =IFERROR(P185*$H$178/P$178, 0) | Q203: =IFERROR(Q185*$H$178/Q$178, 0) | ... U203: =IFERROR(U185*$H$178/U$178, 0) | Y203: =IFERROR(Y185*$H$178/Y$178, 0) | Z203: =IFERROR(Z185*$H$178/Z$178, 0) | AA203: =IFERROR(AA185*$H$178/AA$178, 0) | AB203: =IFERROR(AB185*$H$178/AB$178, 0) | AC203: =IFERROR(AC185*$H$178/AC$178, 0) | AD203: =IFERROR(AD185*$H$178/AD$178, 0) | AE203: =IFERROR(AE185*$H$178/AE$178, 0) | AF203: =IFERROR(AF185*$H$178/AF$178, 0) | ... AH203: =IFERROR(AH185*$H$178/AH$178, 0)
D204: Total Variable Cost Per Unit | J204: =SUM(J199:J203) | K204: =SUM(K199:K203) | L204: =SUM(L199:L203) | M204: =SUM(M199:M203) | N204: =SUM(N199:N203) | O204: =SUM(O199:O203) | P204: =SUM(P199:P203) | Q204: =SUM(Q199:Q203) | ... U204: =SUM(U199:U203) | Y204: =SUM(Y199:Y203) | Z204: =SUM(Z199:Z203) | AA204: =SUM(AA199:AA203) | AB204: =SUM(AB199:AB203) | AC204: =SUM(AC199:AC203) | AD204: =SUM(AD199:AD203) | AE204: =SUM(AE199:AE203) | AF204: =SUM(AF199:AF203) | ... AH204: =SUM(AH199:AH203)
C206: Fixed Cost Per Unit | H206: ='Assumptions&Scenario'!$K$44
D207: =D189 | J207: =IFERROR(J189*$H$178/J$178, 0) | K207: =IFERROR(K189*$H$178/K$178, 0) | L207: =IFERROR(L189*$H$178/L$178, 0) | M207: =IFERROR(M189*$H$178/M$178, 0) | N207: =IFERROR(N189*$H$178/N$178, 0) | O207: =IFERROR(O189*$H$178/O$178, 0) | P207: =IFERROR(P189*$H$178/P$178, 0) | Q207: =IFERROR(Q189*$H$178/Q$178, 0) | ... U207: =IFERROR(U189*$H$178/U$178, 0) | Y207: =IFERROR(Y189*$H$178/Y$178, 0) | Z207: =IFERROR(Z189*$H$178/Z$178, 0) | AA207: =IFERROR(AA189*$H$178/AA$178, 0) | AB207: =IFERROR(AB189*$H$178/AB$178, 0) | AC207: =IFERROR(AC189*$H$178/AC$178, 0) | AD207: =IFERROR(AD189*$H$178/AD$178, 0) | AE207: =IFERROR(AE189*$H$178/AE$178, 0) | AF207: =IFERROR(AF189*$H$178/AF$178, 0) | ... AH207: =IFERROR(AH189*$H$178/AH$178, 0)
D208: =D190 | J208: =IFERROR(J190*$H$178/J$178, 0) | K208: =IFERROR(K190*$H$178/K$178, 0) | L208: =IFERROR(L190*$H$178/L$178, 0) | M208: =IFERROR(M190*$H$178/M$178, 0) | N208: =IFERROR(N190*$H$178/N$178, 0) | O208: =IFERROR(O190*$H$178/O$178, 0) | P208: =IFERROR(P190*$H$178/P$178, 0) | Q208: =IFERROR(Q190*$H$178/Q$178, 0) | ... U208: =IFERROR(U190*$H$178/U$178, 0) | Y208: =IFERROR(Y190*$H$178/Y$178, 0) | Z208: =IFERROR(Z190*$H$178/Z$178, 0) | AA208: =IFERROR(AA190*$H$178/AA$178, 0) | AB208: =IFERROR(AB190*$H$178/AB$178, 0) | AC208: =IFERROR(AC190*$H$178/AC$178, 0) | AD208: =IFERROR(AD190*$H$178/AD$178, 0) | AE208: =IFERROR(AE190*$H$178/AE$178, 0) | AF208: =IFERROR(AF190*$H$178/AF$178, 0) | ... AH208: =IFERROR(AH190*$H$178/AH$178, 0)
...

Sheet Model
U2: =UPPER("Currently Running " & CHOOSE('Assumptions&Scenario'!H88, 'Assumptions&Scenario'!D102,'Assumptions&Scenario'!D103,'Assumptions&Scenario'!D104) & " Scenario")
B3: ='Assumptions&Scenario'!$K$10
B4: Annual Revenue Schedule
L5: Projected
C6: FIN Years | J6: ="FY"&TEXT(RIGHT(K6,2)-(COLUMN(K6)-COLUMN()),"00") | K6: ="FY"&TEXT(DATE(YEAR('Data Sheet'!$K$16)+(MONTH('Data Sheet'!$K$16)>3),1,1),"YY") | L6: ="FY"&TEXT(RIGHT(K6,2)+COLUMN()-COLUMN(K6),"00") | M6: ="FY"&TEXT(RIGHT(L6,2)+COLUMN()-COLUMN(L6),"00") | N6: ="FY"&TEXT(RIGHT(M6,2)+COLUMN()-COLUMN(M6),"00") | O6: ="FY"&TEXT(RIGHT(N6,2)+COLUMN()-COLUMN(N6),"00") | P6: ="FY"&TEXT(RIGHT(O6,2)+COLUMN()-COLUMN(O6),"00") | Q6: ="FY"&TEXT(RIGHT(P6,2)+COLUMN()-COLUMN(P6),"00") | R6: ="FY"&TEXT(RIGHT(Q6,2)+COLUMN()-COLUMN(Q6),"00") | S6: ="FY"&TEXT(RIGHT(R6,2)+COLUMN()-COLUMN(R6),"00") | ... U6: ="FY"&TEXT(RIGHT(T6,2)+COLUMN()-COLUMN(T6),"00")
C10: Multiplier | H10: ='Assumptions&Scenario'!K43
C11: Pricing
D12: Price Inflation | L12: ='Assumptions&Scenario'!L112 | M12: ='Assumptions&Scenario'!M112 | N12: ='Assumptions&Scenario'!N112 | O12: ='Assumptions&Scenario'!O112 | P12: ='Assumptions&Scenario'!P112 | Q12: ='Assumptions&Scenario'!Q112 | R12: ='Assumptions&Scenario'!R112 | S12: ='Assumptions&Scenario'!S112 | ... U12: ='Assumptions&Scenario'!U112
D13: Price | H13: ='Assumptions&Scenario'!K44 | J13: =HistoricalData!T40 | K13: =HistoricalData!U40 | L13: =K13*(1+L12) | M13: =L13*(1+M12) | N13: =M13*(1+N12) | O13: =N13*(1+O12) | P13: =O13*(1+P12) | Q13: =P13*(1+Q12) | R13: =Q13*(1+R12) | S13: =R13*(1+S12) | ... U13: =T13*(1+U12)
C14: Volume
D15: Capacity | L15: ='Assumptions&Scenario'!L106 | M15: ='Assumptions&Scenario'!M106 | N15: ='Assumptions&Scenario'!N106 | O15: ='Assumptions&Scenario'!O106 | P15: ='Assumptions&Scenario'!P106 | Q15: ='Assumptions&Scenario'!Q106 | R15: ='Assumptions&Scenario'!R106 | S15: ='Assumptions&Scenario'!S106 | ... U15: ='Assumptions&Scenario'!U106
D16: Volume Growth | L16: ='Assumptions&Scenario'!L118 | M16: ='Assumptions&Scenario'!M118 | N16: ='Assumptions&Scenario'!N118 | O16: ='Assumptions&Scenario'!O118 | P16: ='Assumptions&Scenario'!P118 | Q16: ='Assumptions&Scenario'!Q118 | R16: ='Assumptions&Scenario'!R118 | S16: ='Assumptions&Scenario'!S118 | ... U16: ='Assumptions&Scenario'!U118
D17: Volume | H17: ='Assumptions&Scenario'!K42 | J17: =HistoricalData!T37 | K17: =HistoricalData!U37 | L17: =K17*(1+L16) | M17: =L17*(1+M16) | N17: =M17*(1+N16) | O17: =N17*(1+O16) | P17: =O17*(1+P16) | Q17: =P17*(1+Q16) | R17: =Q17*(1+R16) | S17: =R17*(1+S16) | ... U17: =T17*(1+U16)
D18: Utilization | L18: =IFERROR(L17/L15, 0) | M18: =IFERROR(M17/M15, 0) | N18: =IFERROR(N17/N15, 0) | O18: =IFERROR(O17/O15, 0) | P18: =IFERROR(P17/P15, 0) | Q18: =IFERROR(Q17/Q15, 0) | R18: =IFERROR(R17/R15, 0) | S18: =IFERROR(S17/S15, 0) | ... U18: =IFERROR(U17/U15, 0)
C20: Revenue
D21: Revenue | H21: (₹ crore) | L21: =L13*L17/$H$10 | M21: =M13*M17/$H$10 | N21: =N13*N17/$H$10 | O21: =O13*O17/$H$10 | P21: =P13*P17/$H$10 | Q21: =Q13*Q17/$H$10 | R21: =R13*R17/$H$10 | S21: =S13*S17/$H$10 | ... U21: =U13*U17/$H$10
D22: Exchange Rate (To Cr) | H22: 1 | L22: ='Assumptions&Scenario'!L130 | M22: ='Assumptions&Scenario'!M130 | N22: ='Assumptions&Scenario'!N130 | O22: ='Assumptions&Scenario'!O130 | P22: ='Assumptions&Scenario'!P130 | Q22: ='Assumptions&Scenario'!Q130 | R22: ='Assumptions&Scenario'!R130 | S22: ='Assumptions&Scenario'!S130 | ... U22: ='Assumptions&Scenario'!U130
D23: Revenue | H23: =HistoricalData!H10 | J23: =HistoricalData!T10 | K23: =HistoricalData!U10 | L23: =L21*L22/$H22 | M23: =M21*M22/$H22 | N23: =N21*N22/$H22 | O23: =O21*O22/$H22 | P23: =P21*P22/$H22 | Q23: =Q21*Q22/$H22 | R23: =R21*R22/$H22 | S23: =S21*S22/$H22 | ... U23: =U21*U22/$H22
D24: Revenue g% | K24: =IFERROR(K23/J23-1, 0) | L24: =IFERROR(L23/K23-1, 0) | M24: =IFERROR(M23/L23-1, 0) | N24: =IFERROR(N23/M23-1, 0) | O24: =IFERROR(O23/N23-1, 0) | P24: =IFERROR(P23/O23-1, 0) | Q24: =IFERROR(Q23/P23-1, 0) | R24: =IFERROR(R23/Q23-1, 0) | ... U24: =IFERROR(U23/T23-1, 0)
U27: =$U$2
B28: ='Assumptions&Scenario'!$K$10
B29: Quarterly Revenue Schedule
L30: Projected
C31: Quarters | J31: ="FY"&TEXT(MID(K31,3,2)-IF(RIGHT(K31,1)="1",1,0),"00")&"Q"&CHOOSE(RIGHT(K31,1)+0,4,1,2,3) | K31: ="FY"&TEXT(MID(L31,3,2)-IF(RIGHT(L31,1)="1",1,0),"00")&"Q"&CHOOSE(RIGHT(L31,1)+0,4,1,2,3) | L31: ="FY"&TEXT(MID(M31,3,2)-IF(RIGHT(M31,1)="1",1,0),"00")&"Q"&CHOOSE(RIGHT(M31,1)+0,4,1,2,3) | M31: ="FY"&TEXT(YEAR('Data Sheet'!$K$41)+(MONTH('Data Sheet'!$K$41)>3)-2000,"00")&"Q"&INT((MOD(MONTH('Data Sheet'!$K$41)-4,12))/3)+1 | N31: ="FY"&TEXT(MID(M31,3,2)+IF(RIGHT(M31,1)="4",1,0),"00")&"Q"&MOD(RIGHT(M31,1),4)+1 | O31: ="FY"&TEXT(MID(N31,3,2)+IF(RIGHT(N31,1)="4",1,0),"00")&"Q"&MOD(RIGHT(N31,1),4)+1 | P31: ="FY"&TEXT(MID(O31,3,2)+IF(RIGHT(O31,1)="4",1,0),"00")&"Q"&MOD(RIGHT(O31,1),4)+1 | Q31: ="FY"&TEXT(MID(P31,3,2)+IF(RIGHT(P31,1)="4",1,0),"00")&"Q"&MOD(RIGHT(P31,1),4)+1 | R31: ="FY"&TEXT(MID(Q31,3,2)+IF(RIGHT(Q31,1)="4",1,0),"00")&"Q"&MOD(RIGHT(Q31,1),4)+1 | S31: ="FY"&TEXT(MID(R31,3,2)+IF(RIGHT(R31,1)="4",1,0),"00")&"Q"&MOD(RIGHT(R31,1),4)+1 | T31: ="FY"&TEXT(MID(S31,3,2)+IF(RIGHT(S31,1)="4",1,0),"00")&"Q"&MOD(RIGHT(S31,1),4)+1 | U31: ="FY"&TEXT(MID(T31,3,2)+IF(RIGHT(T31,1)="4",1,0),"00")&"Q"&MOD(RIGHT(T31,1),4)+1
C35: Multiplier | H35: =$H$10
C36: Pricing
D37: Price Inflation | N37: ='Assumptions&Scenario'!N159 | O37: ='Assumptions&Scenario'!O159 | P37: ='Assumptions&Scenario'!P159 | Q37: ='Assumptions&Scenario'!Q159 | R37: ='Assumptions&Scenario'!R159 | S37: ='Assumptions&Scenario'!S159 | T37: ='Assumptions&Scenario'!T159 | U37: ='Assumptions&Scenario'!U159
D38: Price | H38: =$H$13 | J38: =HistoricalData!R124 | K38: =HistoricalData!S124 | L38: =HistoricalData!T124 | M38: =HistoricalData!U124 | N38: =J38*(1+N37) | O38: =K38*(1+O37) | P38: =L38*(1+P37) | Q38: =M38*(1+Q37) | R38: =N38*(1+R37) | S38: =O38*(1+S37) | T38: =P38*(1+T37) | U38: =Q38*(1+U37)
C39: Volume
D40: Capacity | N40: ='Assumptions&Scenario'!K41 | O40: =N40 | P40: =O40 | Q40: =P40 | R40: =Q40 | S40: =R40 | T40: =S40 | U40: =T40
D41: Volume Growth | N41: ='Assumptions&Scenario'!N165 | O41: ='Assumptions&Scenario'!O165 | P41: ='Assumptions&Scenario'!P165 | Q41: ='Assumptions&Scenario'!Q165 | R41: ='Assumptions&Scenario'!R165 | S41: ='Assumptions&Scenario'!S165 | T41: ='Assumptions&Scenario'!T165 | U41: ='Assumptions&Scenario'!U165
D42: Volume | H42: =$H$17 | J42: =HistoricalData!R121 | K42: =HistoricalData!S121 | L42: =HistoricalData!T121 | M42: =HistoricalData!U121 | N42: =J42*(1+N41) | O42: =K42*(1+O41) | P42: =L42*(1+P41) | Q42: =M42*(1+Q41) | R42: =N42*(1+R41) | S42: =O42*(1+S41) | T42: =P42*(1+T41) | U42: =Q42*(1+U41)
D43: Utilization | N43: =IFERROR(SUM(K42:N42)/N40, 0) | O43: =IFERROR(SUM(L42:O42)/O40, 0) | P43: =IFERROR(SUM(M42:P42)/P40, 0) | Q43: =IFERROR(SUM(N42:Q42)/Q40, 0) | R43: =IFERROR(SUM(O42:R42)/R40, 0) | S43: =IFERROR(SUM(P42:S42)/S40, 0) | T43: =IFERROR(SUM(Q42:T42)/T40, 0) | U43: =IFERROR(SUM(R42:U42)/U40, 0)
C45: Revenue
D46: Revenue | H46: =$H$21 | N46: =N38*N42/$H$35 | O46: =O38*O42/$H$35 | P46: =P38*P42/$H$35 | Q46: =Q38*Q42/$H$35 | R46: =R38*R42/$H$35 | S46: =S38*S42/$H$35 | T46: =T38*T42/$H$35 | U46: =U38*U42/$H$35
D47: Exchange Rate | H47: =$H$22 | N47: ='Assumptions&Scenario'!N171 | O47: ='Assumptions&Scenario'!O171 | P47: ='Assumptions&Scenario'!P171 | Q47: ='Assumptions&Scenario'!Q171 | R47: ='Assumptions&Scenario'!R171 | S47: ='Assumptions&Scenario'!S171 | T47: ='Assumptions&Scenario'!T171 | U47: ='Assumptions&Scenario'!U171
D48: Revenue | H48: =H23 | J48: =HistoricalData!R94 | K48: =HistoricalData!S94 | L48: =HistoricalData!T94 | M48: =HistoricalData!U94 | N48: =N46*N47/$H47 | O48: =O46*O47/$H47 | P48: =P46*P47/$H47 | Q48: =Q46*Q47/$H47 | R48: =R46*R47/$H47 | S48: =S46*S47/$H47 | T48: =T46*T47/$H47 | U48: =U46*U47/$H47
D49: Revenue g% | N49: =IFERROR(N48/J48-1, 0) | O49: =IFERROR(O48/K48-1, 0) | P49: =IFERROR(P48/L48-1, 0) | Q49: =IFERROR(Q48/M48-1, 0) | R49: =IFERROR(R48/N48-1, 0) | S49: =IFERROR(S48/O48-1, 0) | T49: =IFERROR(T48/P48-1, 0) | U49: =IFERROR(U48/Q48-1, 0)
U52: =$U$2
B53: ='Assumptions&Scenario'!$K$10
B54: Annual Cost Inflation
L55: Projected
C56: FIN Years | J56: ="FY"&TEXT(RIGHT(K56,2)-(COLUMN(K56)-COLUMN()),"00") | K56: ="FY"&TEXT(DATE(YEAR('Data Sheet'!$K$16)+(MONTH('Data Sheet'!$K$16)>3),1,1),"YY") | L56: ="FY"&TEXT(RIGHT(K56,2)+COLUMN()-COLUMN(K56),"00") | M56: ="FY"&TEXT(RIGHT(L56,2)+COLUMN()-COLUMN(L56),"00") | N56: ="FY"&TEXT(RIGHT(M56,2)+COLUMN()-COLUMN(M56),"00") | O56: ="FY"&TEXT(RIGHT(N56,2)+COLUMN()-COLUMN(N56),"00") | P56: ="FY"&TEXT(RIGHT(O56,2)+COLUMN()-COLUMN(O56),"00") | Q56: ="FY"&TEXT(RIGHT(P56,2)+COLUMN()-COLUMN(P56),"00") | R56: ="FY"&TEXT(RIGHT(Q56,2)+COLUMN()-COLUMN(Q56),"00") | S56: ="FY"&TEXT(RIGHT(R56,2)+COLUMN()-COLUMN(R56),"00") | ... U56: ="FY"&TEXT(RIGHT(T56,2)+COLUMN()-COLUMN(T56),"00")
C60: Inflation
C61: Variable Cost
D62: ='Assumptions&Scenario'!D26 | L62: ='Assumptions&Scenario'!L26 | M62: ='Assumptions&Scenario'!M26
D63: ='Assumptions&Scenario'!D27 | L63: ='Assumptions&Scenario'!L27 | M63: ='Assumptions&Scenario'!M27
D64: ='Assumptions&Scenario'!D28 | L64: ='Assumptions&Scenario'!L28 | M64: ='Assumptions&Scenario'!M28
D65: ='Assumptions&Scenario'!D29 | L65: ='Assumptions&Scenario'!L29 | M65: ='Assumptions&Scenario'!M29
D66: ='Assumptions&Scenario'!D30 | L66: ='Assumptions&Scenario'!L30 | M66: ='Assumptions&Scenario'!M30
D67: Total Variable Cost | L67: ='Assumptions&Scenario'!L94 | M67: ='Assumptions&Scenario'!M94 | N67: ='Assumptions&Scenario'!N94 | O67: ='Assumptions&Scenario'!O94 | P67: ='Assumptions&Scenario'!P94 | Q67: ='Assumptions&Scenario'!Q94 | R67: ='Assumptions&Scenario'!R94 | S67: ='Assumptions&Scenario'!S94 | ... U67: ='Assumptions&Scenario'!U94
C69: Fixed Cost
D70: ='Assumptions&Scenario'!P26 | L70: ='Assumptions&Scenario'!T26 | M70: ='Assumptions&Scenario'!U26
D71: ='Assumptions&Scenario'!P27 | L71: ='Assumptions&Scenario'!T27 | M71: ='Assumptions&Scenario'!U27
D72: ='Assumptions&Scenario'!P28 | L72: ='Assumptions&Scenario'!T28 | M72: ='Assumptions&Scenario'!U28
D73: ='Assumptions&Scenario'!P29 | L73: ='Assumptions&Scenario'!T29 | M73: ='Assumptions&Scenario'!U29
D74: ='Assumptions&Scenario'!P30 | L74: ='Assumptions&Scenario'!T30 | M74: ='Assumptions&Scenario'!U30
D75: Total Fixed Cost | L75: ='Assumptions&Scenario'!L100 | M75: ='Assumptions&Scenario'!M100 | N75: ='Assumptions&Scenario'!N100 | O75: ='Assumptions&Scenario'!O100 | P75: ='Assumptions&Scenario'!P100 | Q75: ='Assumptions&Scenario'!Q100 | R75: ='Assumptions&Scenario'!R100 | S75: ='Assumptions&Scenario'!S100 | ... U75: ='Assumptions&Scenario'!U100
U78: =$U$2
B79: ='Assumptions&Scenario'!$K$10
B80: Annual Aggregate Cost Schedule
L81: Projected
C82: FIN Years | J82: ="FY"&TEXT(RIGHT(K82,2)-(COLUMN(K82)-COLUMN()),"00") | K82: ="FY"&TEXT(DATE(YEAR('Data Sheet'!$K$16)+(MONTH('Data Sheet'!$K$16)>3),1,1),"YY") | L82: ="FY"&TEXT(RIGHT(K82,2)+COLUMN()-COLUMN(K82),"00") | M82: ="FY"&TEXT(RIGHT(L82,2)+COLUMN()-COLUMN(L82),"00") | N82: ="FY"&TEXT(RIGHT(M82,2)+COLUMN()-COLUMN(M82),"00") | O82: ="FY"&TEXT(RIGHT(N82,2)+COLUMN()-COLUMN(N82),"00") | P82: ="FY"&TEXT(RIGHT(O82,2)+COLUMN()-COLUMN(O82),"00") | Q82: ="FY"&TEXT(RIGHT(P82,2)+COLUMN()-COLUMN(P82),"00") | R82: ="FY"&TEXT(RIGHT(Q82,2)+COLUMN()-COLUMN(Q82),"00") | S82: ="FY"&TEXT(RIGHT(R82,2)+COLUMN()-COLUMN(R82),"00") | ... U82: ="FY"&TEXT(RIGHT(T82,2)+COLUMN()-COLUMN(T82),"00")
C87: ="Total Volume "& 'Assumptions&Scenario'!$K$42 | H87: =$H$10 | K87: =K17 | L87: =L17 | M87: =M17 | N87: =N17 | O87: =O17 | P87: =P17 | Q87: =Q17 | R87: =R17 | ... U87: =U17
C88: Aggregate Cost | H88: =$H$21
C89: Variable Cost
D90: =D62 | J90: =HistoricalData!T181 | K90: =HistoricalData!U181 | L90: =L$87*L120/$H$87 | M90: =M$87*M120/$H$87
D91: =D63 | J91: =HistoricalData!T182 | K91: =HistoricalData!U182 | L91: =L$87*L121/$H$87 | M91: =M$87*M121/$H$87
D92: =D64 | J92: =HistoricalData!T183 | K92: =HistoricalData!U183 | L92: =L$87*L122/$H$87 | M92: =M$87*M122/$H$87
D93: =D65 | J93: =HistoricalData!T184 | K93: =HistoricalData!U184 | L93: =L$87*L123/$H$87 | M93: =M$87*M123/$H$87
D94: =D66 | J94: =HistoricalData!T185 | K94: =HistoricalData!U185 | L94: =L$87*L124/$H$87 | M94: =M$87*M124/$H$87
D95: =D67 | J95: =HistoricalData!T186 | K95: =HistoricalData!U186 | L95: =SUM(L90:L94) | M95: =SUM(M90:M94) | N95: =N$87*N125/$H$87 | O95: =O$87*O125/$H$87 | P95: =P$87*P125/$H$87 | Q95: =Q$87*Q125/$H$87 | R95: =R$87*R125/$H$87 | S95: =S$87*S125/$H$87 | T95: =T$87*T125/$H$87 | U95: =U$87*U125/$H$87
C97: Fixed Cost
D98: =D70 | J98: =HistoricalData!T189 | K98: =HistoricalData!U189 | L98: ='Assumptions&Scenario'!S26 | M98: =L98*(1+M70)
D99: =D71 | J99: =HistoricalData!T190 | K99: =HistoricalData!U190 | L99: ='Assumptions&Scenario'!S27 | M99: =L99*(1+M71)
D100: =D72 | J100: =HistoricalData!T191 | K100: =HistoricalData!U191 | L100: ='Assumptions&Scenario'!S28 | M100: =L100*(1+M72)
D101: =D73 | J101: =HistoricalData!T192 | K101: =HistoricalData!U192 | L101: ='Assumptions&Scenario'!S29 | M101: =L101*(1+M73)
D102: =D74 | J102: =HistoricalData!T193 | K102: =HistoricalData!U193 | L102: ='Assumptions&Scenario'!S30 | M102: =L102*(1+M74)
D103: =D75 | J103: =HistoricalData!T194 | K103: =HistoricalData!U194 | L103: =SUM(L98:L102) | M103: =SUM(M98:M102) | N103: =M103*(1+N75) | O103: =N103*(1+O75) | P103: =O103*(1+P75) | Q103: =P103*(1+Q75) | R103: =Q103*(1+R75) | S103: =R103*(1+S75) | T103: =S103*(1+T75) | U103: =T103*(1+U75)
C105: Total Cost | J105: =HistoricalData!T195 | K105: =HistoricalData!U195 | L105: =L103+L95 | M105: =M103+M95 | N105: =N103+N95 | O105: =O103+O95 | P105: =P103+P95 | Q105: =Q103+Q95 | R105: =R103+R95 | S105: =S103+S95 | ... U105: =U103+U95
D106: Cost Growth | K106: =IFERROR(K105/J105-1, 0) | L106: =IFERROR(L105/K105-1, 0) | M106: =IFERROR(M105/L105-1, 0) | N106: =IFERROR(N105/M105-1, 0) | O106: =IFERROR(O105/N105-1, 0) | P106: =IFERROR(P105/O105-1, 0) | Q106: =IFERROR(Q105/P105-1, 0) | R106: =IFERROR(R105/Q105-1, 0) | ... U106: =IFERROR(U105/T105-1, 0)
U109: =$U$2
B110: ='Assumptions&Scenario'!$K$10
B111: Annual Cost Per Unit Schedule
L112: Projected
C113: FIN Years | J113: ="FY"&TEXT(RIGHT(K113,2)-(COLUMN(K113)-COLUMN()),"00") | K113: ="FY"&TEXT(DATE(YEAR('Data Sheet'!$K$16)+(MONTH('Data Sheet'!$K$16)>3),1,1),"YY") | L113: ="FY"&TEXT(RIGHT(K113,2)+COLUMN()-COLUMN(K113),"00") | M113: ="FY"&TEXT(RIGHT(L113,2)+COLUMN()-COLUMN(L113),"00") | N113: ="FY"&TEXT(RIGHT(M113,2)+COLUMN()-COLUMN(M113),"00") | O113: ="FY"&TEXT(RIGHT(N113,2)+COLUMN()-COLUMN(N113),"00") | P113: ="FY"&TEXT(RIGHT(O113,2)+COLUMN()-COLUMN(O113),"00") | Q113: ="FY"&TEXT(RIGHT(P113,2)+COLUMN()-COLUMN(P113),"00") | R113: ="FY"&TEXT(RIGHT(Q113,2)+COLUMN()-COLUMN(Q113),"00") | S113: ="FY"&TEXT(RIGHT(R113,2)+COLUMN()-COLUMN(R113),"00") | ... U113: ="FY"&TEXT(RIGHT(T113,2)+COLUMN()-COLUMN(T113),"00")
C117: =$C$87 | H117: =$H$10 | J117: =J17 | K117: =K17 | L117: =L17 | M117: =M17 | N117: =N17 | O117: =O17 | P117: =P17 | Q117: =Q17 | ... U117: =U17
C118: Cost Per Unit | H118: ='Assumptions&Scenario'!K44
C119: Variable Cost
D120: =D90 | J120: =HistoricalData!T199 | K120: =HistoricalData!U199 | L120: ='Assumptions&Scenario'!K26 | M120: =L120*(1+M62)
D121: =D91 | J121: =HistoricalData!T200 | K121: =HistoricalData!U200 | L121: ='Assumptions&Scenario'!K27 | M121: =L121*(1+M63)
D122: =D92 | J122: =HistoricalData!T201 | K122: =HistoricalData!U201 | L122: ='Assumptions&Scenario'!K28 | M122: =L122*(1+M64)
D123: =D93 | J123: =HistoricalData!T202 | K123: =HistoricalData!U202 | L123: ='Assumptions&Scenario'!K29 | M123: =L123*(1+M65)
D124: =D94 | J124: =HistoricalData!T203 | K124: =HistoricalData!U203 | L124: ='Assumptions&Scenario'!K30 | M124: =L124*(1+M66)
D125: =D95 | J125: =HistoricalData!T204 | K125: =HistoricalData!U204 | L125: =SUM(L120:L124) | M125: =SUM(M120:M124) | N125: =M125*(1+N67) | O125: =N125*(1+O67) | P125: =O125*(1+P67) | Q125: =P125*(1+Q67) | R125: =Q125*(1+R67) | S125: =R125*(1+S67) | T125: =S125*(1+T67) | U125: =T125*(1+U67)
C127: Fixed Cost
D128: =D98 | J128: =HistoricalData!T207 | K128: =HistoricalData!U207 | L128: =IFERROR(L98*$H$117/L$117, 0) | M128: =IFERROR(M98*$H$117/M$117, 0)
D129: =D99 | J129: =HistoricalData!T208 | K129: =HistoricalData!U208 | L129: =IFERROR(L99*$H$117/L$117, 0) | M129: =IFERROR(M99*$H$117/M$117, 0)
D130: =D100 | J130: =HistoricalData!T209 | K130: =HistoricalData!U209 | L130: =IFERROR(L100*$H$117/L$117, 0) | M130: =IFERROR(M100*$H$117/M$117, 0)
D131: =D101 | J131: =HistoricalData!T210 | K131: =HistoricalData!U210 | L131: =IFERROR(L101*$H$117/L$117, 0) | M131: =IFERROR(M101*$H$117/M$117, 0)
...

Sheet ModelBFSI
U2: =UPPER("Currently Running " & CHOOSE('Assumptions&Scenario'!H88, 'Assumptions&Scenario'!D102,'Assumptions&Scenario'!D103,'Assumptions&Scenario'!D104) & " Scenario")
B3: ='Assumptions&Scenario'!$K$10
B4: Annual Income Expense History | Y4: Annual Income Expense Forecast
C6: FIN Years | J6: ="FY"&TEXT(RIGHT(K6,2)-(COLUMN(K6)-COLUMN()),"00") | K6: ="FY"&TEXT(RIGHT(L6,2)-(COLUMN(L6)-COLUMN()),"00") | L6: ="FY"&TEXT(RIGHT(M6,2)-(COLUMN(M6)-COLUMN()),"00") | M6: ="FY"&TEXT(RIGHT(N6,2)-(COLUMN(N6)-COLUMN()),"00") | N6: ="FY"&TEXT(RIGHT(O6,2)-(COLUMN(O6)-COLUMN()),"00") | O6: ="FY"&TEXT(RIGHT(P6,2)-(COLUMN(P6)-COLUMN()),"00") | P6: ="FY"&TEXT(RIGHT(Q6,2)-(COLUMN(Q6)-COLUMN()),"00") | Q6: ="FY"&TEXT(RIGHT(R6,2)-(COLUMN(R6)-COLUMN()),"00") | ... T6: ="FY"&TEXT(RIGHT(U6,2)-(COLUMN(U6)-COLUMN()),"00") | U6: ="FY"&TEXT(DATE(YEAR('Data Sheet'!$K$16)+(MONTH('Data Sheet'!$K$16)>3),1,1),"YY") | Y6: =Model!$L$6 | Z6: ="FY"&TEXT(RIGHT(Y6,2)+COLUMN()-COLUMN(Y6),"00") | AA6: ="FY"&TEXT(RIGHT(Z6,2)+COLUMN()-COLUMN(Z6),"00") | AB6: ="FY"&TEXT(RIGHT(AA6,2)+COLUMN()-COLUMN(AA6),"00") | AC6: ="FY"&TEXT(RIGHT(AB6,2)+COLUMN()-COLUMN(AB6),"00") | AD6: ="FY"&TEXT(RIGHT(AC6,2)+COLUMN()-COLUMN(AC6),"00") | AE6: ="FY"&TEXT(RIGHT(AD6,2)+COLUMN()-COLUMN(AD6),"00") | AF6: ="FY"&TEXT(RIGHT(AE6,2)+COLUMN()-COLUMN(AE6),"00") | AG6: ="FY"&TEXT(RIGHT(AF6,2)+COLUMN()-COLUMN(AF6),"00") | AH6: ="FY"&TEXT(RIGHT(AG6,2)+COLUMN()-COLUMN(AG6),"00")
C10: Interest Income | H10: =HistoricalData!H10 | Y10: {=IFERROR(_xlfn.FORECAST.LINEAR(RIGHT(Y$6,2), $J10:$U10, VALUE(RIGHT($J$6:$U$6,2))), 0)} | Z10: {=IFERROR(_xlfn.FORECAST.LINEAR(RIGHT(Z$6,2), $J10:$U10, VALUE(RIGHT($J$6:$U$6,2))), 0)} | AA10: {=IFERROR(_xlfn.FORECAST.LINEAR(RIGHT(AA$6,2), $J10:$U10, VALUE(RIGHT($J$6:$U$6,2))), 0)} | AB10: {=IFERROR(_xlfn.FORECAST.LINEAR(RIGHT(AB$6,2), $J10:$U10, VALUE(RIGHT($J$6:$U$6,2))), 0)} | AC10: {=IFERROR(_xlfn.FORECAST.LINEAR(RIGHT(AC$6,2), $J10:$U10, VALUE(RIGHT($J$6:$U$6,2))), 0)} | AD10: {=IFERROR(_xlfn.FORECAST.LINEAR(RIGHT(AD$6,2), $J10:$U10, VALUE(RIGHT($J$6:$U$6,2))), 0)} | AE10: {=IFERROR(_xlfn.FORECAST.LINEAR(RIGHT(AE$6,2), $J10:$U10, VALUE(RIGHT($J$6:$U$6,2))), 0)} | AF10: {=IFERROR(_xlfn.FORECAST.LINEAR(RIGHT(AF$6,2), $J10:$U10, VALUE(RIGHT($J$6:$U$6,2))), 0)} | ... AH10: {=IFERROR(_xlfn.FORECAST.LINEAR(RIGHT(AH$6,2), $J10:$U10, VALUE(RIGHT($J$6:$U$6,2))), 0)}
C11: Interest Expenses | Y11: {=IFERROR(_xlfn.FORECAST.LINEAR(RIGHT(Y$6,2), $J11:$U11, VALUE(RIGHT($J$6:$U$6,2))), 0)} | Z11: {=IFERROR(_xlfn.FORECAST.LINEAR(RIGHT(Z$6,2), $J11:$U11, VALUE(RIGHT($J$6:$U$6,2))), 0)} | AA11: {=IFERROR(_xlfn.FORECAST.LINEAR(RIGHT(AA$6,2), $J11:$U11, VALUE(RIGHT($J$6:$U$6,2))), 0)} | AB11: {=IFERROR(_xlfn.FORECAST.LINEAR(RIGHT(AB$6,2), $J11:$U11, VALUE(RIGHT($J$6:$U$6,2))), 0)} | AC11: {=IFERROR(_xlfn.FORECAST.LINEAR(RIGHT(AC$6,2), $J11:$U11, VALUE(RIGHT($J$6:$U$6,2))), 0)} | AD11: {=IFERROR(_xlfn.FORECAST.LINEAR(RIGHT(AD$6,2), $J11:$U11, VALUE(RIGHT($J$6:$U$6,2))), 0)} | AE11: {=IFERROR(_xlfn.FORECAST.LINEAR(RIGHT(AE$6,2), $J11:$U11, VALUE(RIGHT($J$6:$U$6,2))), 0)} | AF11: {=IFERROR(_xlfn.FORECAST.LINEAR(RIGHT(AF$6,2), $J11:$U11, VALUE(RIGHT($J$6:$U$6,2))), 0)} | ... AH11: {=IFERROR(_xlfn.FORECAST.LINEAR(RIGHT(AH$6,2), $J11:$U11, VALUE(RIGHT($J$6:$U$6,2))), 0)}
C12: Net Interest Income | Y12: {=IFERROR(_xlfn.FORECAST.LINEAR(RIGHT(Y$6,2), $J12:$U12, VALUE(RIGHT($J$6:$U$6,2))), 0)} | Z12: {=IFERROR(_xlfn.FORECAST.LINEAR(RIGHT(Z$6,2), $J12:$U12, VALUE(RIGHT($J$6:$U$6,2))), 0)} | AA12: {=IFERROR(_xlfn.FORECAST.LINEAR(RIGHT(AA$6,2), $J12:$U12, VALUE(RIGHT($J$6:$U$6,2))), 0)} | AB12: {=IFERROR(_xlfn.FORECAST.LINEAR(RIGHT(AB$6,2), $J12:$U12, VALUE(RIGHT($J$6:$U$6,2))), 0)} | AC12: {=IFERROR(_xlfn.FORECAST.LINEAR(RIGHT(AC$6,2), $J12:$U12, VALUE(RIGHT($J$6:$U$6,2))), 0)} | AD12: {=IFERROR(_xlfn.FORECAST.LINEAR(RIGHT(AD$6,2), $J12:$U12, VALUE(RIGHT($J$6:$U$6,2))), 0)} | AE12: {=IFERROR(_xlfn.FORECAST.LINEAR(RIGHT(AE$6,2), $J12:$U12, VALUE(RIGHT($J$6:$U$6,2))), 0)} | AF12: {=IFERROR(_xlfn.FORECAST.LINEAR(RIGHT(AF$6,2), $J12:$U12, VALUE(RIGHT($J$6:$U$6,2))), 0)} | ... AH12: {=IFERROR(_xlfn.FORECAST.LINEAR(RIGHT(AH$6,2), $J12:$U12, VALUE(RIGHT($J$6:$U$6,2))), 0)}
C15: Net Interest Margin | Y15: {=IFERROR(_xlfn.FORECAST.LINEAR(RIGHT(Y$6,2), $J15:$U15, VALUE(RIGHT($J$6:$U$6,2))), 0)} | Z15: {=IFERROR(_xlfn.FORECAST.LINEAR(RIGHT(Z$6,2), $J15:$U15, VALUE(RIGHT($J$6:$U$6,2))), 0)} | AA15: {=IFERROR(_xlfn.FORECAST.LINEAR(RIGHT(AA$6,2), $J15:$U15, VALUE(RIGHT($J$6:$U$6,2))), 0)} | AB15: {=IFERROR(_xlfn.FORECAST.LINEAR(RIGHT(AB$6,2), $J15:$U15, VALUE(RIGHT($J$6:$U$6,2))), 0)} | AC15: {=IFERROR(_xlfn.FORECAST.LINEAR(RIGHT(AC$6,2), $J15:$U15, VALUE(RIGHT($J$6:$U$6,2))), 0)} | AD15: {=IFERROR(_xlfn.FORECAST.LINEAR(RIGHT(AD$6,2), $J15:$U15, VALUE(RIGHT($J$6:$U$6,2))), 0)} | AE15: {=IFERROR(_xlfn.FORECAST.LINEAR(RIGHT(AE$6,2), $J15:$U15, VALUE(RIGHT($J$6:$U$6,2))), 0)} | AF15: {=IFERROR(_xlfn.FORECAST.LINEAR(RIGHT(AF$6,2), $J15:$U15, VALUE(RIGHT($J$6:$U$6,2))), 0)} | ... AH15: {=IFERROR(_xlfn.FORECAST.LINEAR(RIGHT(AH$6,2), $J15:$U15, VALUE(RIGHT($J$6:$U$6,2))), 0)}
C17: Other Income | Y17: {=IFERROR(_xlfn.FORECAST.LINEAR(RIGHT(Y$6,2), $J17:$U17, VALUE(RIGHT($J$6:$U$6,2))), 0)} | Z17: {=IFERROR(_xlfn.FORECAST.LINEAR(RIGHT(Z$6,2), $J17:$U17, VALUE(RIGHT($J$6:$U$6,2))), 0)} | AA17: {=IFERROR(_xlfn.FORECAST.LINEAR(RIGHT(AA$6,2), $J17:$U17, VALUE(RIGHT($J$6:$U$6,2))), 0)} | AB17: {=IFERROR(_xlfn.FORECAST.LINEAR(RIGHT(AB$6,2), $J17:$U17, VALUE(RIGHT($J$6:$U$6,2))), 0)} | AC17: {=IFERROR(_xlfn.FORECAST.LINEAR(RIGHT(AC$6,2), $J17:$U17, VALUE(RIGHT($J$6:$U$6,2))), 0)} | AD17: {=IFERROR(_xlfn.FORECAST.LINEAR(RIGHT(AD$6,2), $J17:$U17, VALUE(RIGHT($J$6:$U$6,2))), 0)} | AE17: {=IFERROR(_xlfn.FORECAST.LINEAR(RIGHT(AE$6,2), $J17:$U17, VALUE(RIGHT($J$6:$U$6,2))), 0)} | AF17: {=IFERROR(_xlfn.FORECAST.LINEAR(RIGHT(AF$6,2), $J17:$U17, VALUE(RIGHT($J$6:$U$6,2))), 0)} | ... AH17: {=IFERROR(_xlfn.FORECAST.LINEAR(RIGHT(AH$6,2), $J17:$U17, VALUE(RIGHT($J$6:$U$6,2))), 0)}
C18: Total Income | Y18: {=IFERROR(_xlfn.FORECAST.LINEAR(RIGHT(Y$6,2), $J18:$U18, VALUE(RIGHT($J$6:$U$6,2))), 0)} | Z18: {=IFERROR(_xlfn.FORECAST.LINEAR(RIGHT(Z$6,2), $J18:$U18, VALUE(RIGHT($J$6:$U$6,2))), 0)} | AA18: {=IFERROR(_xlfn.FORECAST.LINEAR(RIGHT(AA$6,2), $J18:$U18, VALUE(RIGHT($J$6:$U$6,2))), 0)} | AB18: {=IFERROR(_xlfn.FORECAST.LINEAR(RIGHT(AB$6,2), $J18:$U18, VALUE(RIGHT($J$6:$U$6,2))), 0)} | AC18: {=IFERROR(_xlfn.FORECAST.LINEAR(RIGHT(AC$6,2), $J18:$U18, VALUE(RIGHT($J$6:$U$6,2))), 0)} | AD18: {=IFERROR(_xlfn.FORECAST.LINEAR(RIGHT(AD$6,2), $J18:$U18, VALUE(RIGHT($J$6:$U$6,2))), 0)} | AE18: {=IFERROR(_xlfn.FORECAST.LINEAR(RIGHT(AE$6,2), $J18:$U18, VALUE(RIGHT($J$6:$U$6,2))), 0)} | AF18: {=IFERROR(_xlfn.FORECAST.LINEAR(RIGHT(AF$6,2), $J18:$U18, VALUE(RIGHT($J$6:$U$6,2))), 0)} | ... AH18: {=IFERROR(_xlfn.FORECAST.LINEAR(RIGHT(AH$6,2), $J18:$U18, VALUE(RIGHT($J$6:$U$6,2))), 0)}
C20: Pre Provision Profit | Y20: {=IFERROR(_xlfn.FORECAST.LINEAR(RIGHT(Y$6,2), $J20:$U20, VALUE(RIGHT($J$6:$U$6,2))), 0)} | Z20: {=IFERROR(_xlfn.FORECAST.LINEAR(RIGHT(Z$6,2), $J20:$U20, VALUE(RIGHT($J$6:$U$6,2))), 0)} | AA20: {=IFERROR(_xlfn.FORECAST.LINEAR(RIGHT(AA$6,2), $J20:$U20, VALUE(RIGHT($J$6:$U$6,2))), 0)} | AB20: {=IFERROR(_xlfn.FORECAST.LINEAR(RIGHT(AB$6,2), $J20:$U20, VALUE(RIGHT($J$6:$U$6,2))), 0)} | AC20: {=IFERROR(_xlfn.FORECAST.LINEAR(RIGHT(AC$6,2), $J20:$U20, VALUE(RIGHT($J$6:$U$6,2))), 0)} | AD20: {=IFERROR(_xlfn.FORECAST.LINEAR(RIGHT(AD$6,2), $J20:$U20, VALUE(RIGHT($J$6:$U$6,2))), 0)} | AE20: {=IFERROR(_xlfn.FORECAST.LINEAR(RIGHT(AE$6,2), $J20:$U20, VALUE(RIGHT($J$6:$U$6,2))), 0)} | AF20: {=IFERROR(_xlfn.FORECAST.LINEAR(RIGHT(AF$6,2), $J20:$U20, VALUE(RIGHT($J$6:$U$6,2))), 0)} | ... AH20: {=IFERROR(_xlfn.FORECAST.LINEAR(RIGHT(AH$6,2), $J20:$U20, VALUE(RIGHT($J$6:$U$6,2))), 0)}
C22: Provision | Y22: {=IFERROR(_xlfn.FORECAST.LINEAR(RIGHT(Y$6,2), $J22:$U22, VALUE(RIGHT($J$6:$U$6,2))), 0)} | Z22: {=IFERROR(_xlfn.FORECAST.LINEAR(RIGHT(Z$6,2), $J22:$U22, VALUE(RIGHT($J$6:$U$6,2))), 0)} | AA22: {=IFERROR(_xlfn.FORECAST.LINEAR(RIGHT(AA$6,2), $J22:$U22, VALUE(RIGHT($J$6:$U$6,2))), 0)} | AB22: {=IFERROR(_xlfn.FORECAST.LINEAR(RIGHT(AB$6,2), $J22:$U22, VALUE(RIGHT($J$6:$U$6,2))), 0)} | AC22: {=IFERROR(_xlfn.FORECAST.LINEAR(RIGHT(AC$6,2), $J22:$U22, VALUE(RIGHT($J$6:$U$6,2))), 0)} | AD22: {=IFERROR(_xlfn.FORECAST.LINEAR(RIGHT(AD$6,2), $J22:$U22, VALUE(RIGHT($J$6:$U$6,2))), 0)} | AE22: {=IFERROR(_xlfn.FORECAST.LINEAR(RIGHT(AE$6,2), $J22:$U22, VALUE(RIGHT($J$6:$U$6,2))), 0)} | AF22: {=IFERROR(_xlfn.FORECAST.LINEAR(RIGHT(AF$6,2), $J22:$U22, VALUE(RIGHT($J$6:$U$6,2))), 0)} | ... AH22: {=IFERROR(_xlfn.FORECAST.LINEAR(RIGHT(AH$6,2), $J22:$U22, VALUE(RIGHT($J$6:$U$6,2))), 0)}
C24: Profit before Tax
C26: Tax
C27: Standalone Profit | Y27: {=IFERROR(_xlfn.FORECAST.LINEAR(RIGHT(Y$6,2), $J27:$U27, VALUE(RIGHT($J$6:$U$6,2))), 0)} | Z27: {=IFERROR(_xlfn.FORECAST.LINEAR(RIGHT(Z$6,2), $J27:$U27, VALUE(RIGHT($J$6:$U$6,2))), 0)} | AA27: {=IFERROR(_xlfn.FORECAST.LINEAR(RIGHT(AA$6,2), $J27:$U27, VALUE(RIGHT($J$6:$U$6,2))), 0)} | AB27: {=IFERROR(_xlfn.FORECAST.LINEAR(RIGHT(AB$6,2), $J27:$U27, VALUE(RIGHT($J$6:$U$6,2))), 0)} | AC27: {=IFERROR(_xlfn.FORECAST.LINEAR(RIGHT(AC$6,2), $J27:$U27, VALUE(RIGHT($J$6:$U$6,2))), 0)} | AD27: {=IFERROR(_xlfn.FORECAST.LINEAR(RIGHT(AD$6,2), $J27:$U27, VALUE(RIGHT($J$6:$U$6,2))), 0)} | AE27: {=IFERROR(_xlfn.FORECAST.LINEAR(RIGHT(AE$6,2), $J27:$U27, VALUE(RIGHT($J$6:$U$6,2))), 0)} | AF27: {=IFERROR(_xlfn.FORECAST.LINEAR(RIGHT(AF$6,2), $J27:$U27, VALUE(RIGHT($J$6:$U$6,2))), 0)} | ... AH27: {=IFERROR(_xlfn.FORECAST.LINEAR(RIGHT(AH$6,2), $J27:$U27, VALUE(RIGHT($J$6:$U$6,2))), 0)}
C29: Subsidiary Profit
D30: Subsidiary 1 | Y30: {=IFERROR(_xlfn.FORECAST.LINEAR(RIGHT(Y$6,2), $J30:$U30, VALUE(RIGHT($J$6:$U$6,2))), 0)} | Z30: {=IFERROR(_xlfn.FORECAST.LINEAR(RIGHT(Z$6,2), $J30:$U30, VALUE(RIGHT($J$6:$U$6,2))), 0)} | AA30: {=IFERROR(_xlfn.FORECAST.LINEAR(RIGHT(AA$6,2), $J30:$U30, VALUE(RIGHT($J$6:$U$6,2))), 0)} | AB30: {=IFERROR(_xlfn.FORECAST.LINEAR(RIGHT(AB$6,2), $J30:$U30, VALUE(RIGHT($J$6:$U$6,2))), 0)} | AC30: {=IFERROR(_xlfn.FORECAST.LINEAR(RIGHT(AC$6,2), $J30:$U30, VALUE(RIGHT($J$6:$U$6,2))), 0)} | AD30: {=IFERROR(_xlfn.FORECAST.LINEAR(RIGHT(AD$6,2), $J30:$U30, VALUE(RIGHT($J$6:$U$6,2))), 0)} | AE30: {=IFERROR(_xlfn.FORECAST.LINEAR(RIGHT(AE$6,2), $J30:$U30, VALUE(RIGHT($J$6:$U$6,2))), 0)} | AF30: {=IFERROR(_xlfn.FORECAST.LINEAR(RIGHT(AF$6,2), $J30:$U30, VALUE(RIGHT($J$6:$U$6,2))), 0)} | ... AH30: {=IFERROR(_xlfn.FORECAST.LINEAR(RIGHT(AH$6,2), $J30:$U30, VALUE(RIGHT($J$6:$U$6,2))), 0)}
D31: Subsidiary 2 | Y31: {=IFERROR(_xlfn.FORECAST.LINEAR(RIGHT(Y$6,2), $J31:$U31, VALUE(RIGHT($J$6:$U$6,2))), 0)} | Z31: {=IFERROR(_xlfn.FORECAST.LINEAR(RIGHT(Z$6,2), $J31:$U31, VALUE(RIGHT($J$6:$U$6,2))), 0)} | AA31: {=IFERROR(_xlfn.FORECAST.LINEAR(RIGHT(AA$6,2), $J31:$U31, VALUE(RIGHT($J$6:$U$6,2))), 0)} | AB31: {=IFERROR(_xlfn.FORECAST.LINEAR(RIGHT(AB$6,2), $J31:$U31, VALUE(RIGHT($J$6:$U$6,2))), 0)} | AC31: {=IFERROR(_xlfn.FORECAST.LINEAR(RIGHT(AC$6,2), $J31:$U31, VALUE(RIGHT($J$6:$U$6,2))), 0)} | AD31: {=IFERROR(_xlfn.FORECAST.LINEAR(RIGHT(AD$6,2), $J31:$U31, VALUE(RIGHT($J$6:$U$6,2))), 0)} | AE31: {=IFERROR(_xlfn.FORECAST.LINEAR(RIGHT(AE$6,2), $J31:$U31, VALUE(RIGHT($J$6:$U$6,2))), 0)} | AF31: {=IFERROR(_xlfn.FORECAST.LINEAR(RIGHT(AF$6,2), $J31:$U31, VALUE(RIGHT($J$6:$U$6,2))), 0)} | ... AH31: {=IFERROR(_xlfn.FORECAST.LINEAR(RIGHT(AH$6,2), $J31:$U31, VALUE(RIGHT($J$6:$U$6,2))), 0)}
D32: Subsidiary 3 | Y32: {=IFERROR(_xlfn.FORECAST.LINEAR(RIGHT(Y$6,2), $J32:$U32, VALUE(RIGHT($J$6:$U$6,2))), 0)} | Z32: {=IFERROR(_xlfn.FORECAST.LINEAR(RIGHT(Z$6,2), $J32:$U32, VALUE(RIGHT($J$6:$U$6,2))), 0)} | AA32: {=IFERROR(_xlfn.FORECAST.LINEAR(RIGHT(AA$6,2), $J32:$U32, VALUE(RIGHT($J$6:$U$6,2))), 0)} | AB32: {=IFERROR(_xlfn.FORECAST.LINEAR(RIGHT(AB$6,2), $J32:$U32, VALUE(RIGHT($J$6:$U$6,2))), 0)} | AC32: {=IFERROR(_xlfn.FORECAST.LINEAR(RIGHT(AC$6,2), $J32:$U32, VALUE(RIGHT($J$6:$U$6,2))), 0)} | AD32: {=IFERROR(_xlfn.FORECAST.LINEAR(RIGHT(AD$6,2), $J32:$U32, VALUE(RIGHT($J$6:$U$6,2))), 0)} | AE32: {=IFERROR(_xlfn.FORECAST.LINEAR(RIGHT(AE$6,2), $J32:$U32, VALUE(RIGHT($J$6:$U$6,2))), 0)} | AF32: {=IFERROR(_xlfn.FORECAST.LINEAR(RIGHT(AF$6,2), $J32:$U32, VALUE(RIGHT($J$6:$U$6,2))), 0)} | ... AH32: {=IFERROR(_xlfn.FORECAST.LINEAR(RIGHT(AH$6,2), $J32:$U32, VALUE(RIGHT($J$6:$U$6,2))), 0)}
D33: Subsidiary 4 | Y33: {=IFERROR(_xlfn.FORECAST.LINEAR(RIGHT(Y$6,2), $J33:$U33, VALUE(RIGHT($J$6:$U$6,2))), 0)} | Z33: {=IFERROR(_xlfn.FORECAST.LINEAR(RIGHT(Z$6,2), $J33:$U33, VALUE(RIGHT($J$6:$U$6,2))), 0)} | AA33: {=IFERROR(_xlfn.FORECAST.LINEAR(RIGHT(AA$6,2), $J33:$U33, VALUE(RIGHT($J$6:$U$6,2))), 0)} | AB33: {=IFERROR(_xlfn.FORECAST.LINEAR(RIGHT(AB$6,2), $J33:$U33, VALUE(RIGHT($J$6:$U$6,2))), 0)} | AC33: {=IFERROR(_xlfn.FORECAST.LINEAR(RIGHT(AC$6,2), $J33:$U33, VALUE(RIGHT($J$6:$U$6,2))), 0)} | AD33: {=IFERROR(_xlfn.FORECAST.LINEAR(RIGHT(AD$6,2), $J33:$U33, VALUE(RIGHT($J$6:$U$6,2))), 0)} | AE33: {=IFERROR(_xlfn.FORECAST.LINEAR(RIGHT(AE$6,2), $J33:$U33, VALUE(RIGHT($J$6:$U$6,2))), 0)} | AF33: {=IFERROR(_xlfn.FORECAST.LINEAR(RIGHT(AF$6,2), $J33:$U33, VALUE(RIGHT($J$6:$U$6,2))), 0)} | ... AH33: {=IFERROR(_xlfn.FORECAST.LINEAR(RIGHT(AH$6,2), $J33:$U33, VALUE(RIGHT($J$6:$U$6,2))), 0)}
D34: Subsidiary 5 | Y34: {=IFERROR(_xlfn.FORECAST.LINEAR(RIGHT(Y$6,2), $J34:$U34, VALUE(RIGHT($J$6:$U$6,2))), 0)} | Z34: {=IFERROR(_xlfn.FORECAST.LINEAR(RIGHT(Z$6,2), $J34:$U34, VALUE(RIGHT($J$6:$U$6,2))), 0)} | AA34: {=IFERROR(_xlfn.FORECAST.LINEAR(RIGHT(AA$6,2), $J34:$U34, VALUE(RIGHT($J$6:$U$6,2))), 0)} | AB34: {=IFERROR(_xlfn.FORECAST.LINEAR(RIGHT(AB$6,2), $J34:$U34, VALUE(RIGHT($J$6:$U$6,2))), 0)} | AC34: {=IFERROR(_xlfn.FORECAST.LINEAR(RIGHT(AC$6,2), $J34:$U34, VALUE(RIGHT($J$6:$U$6,2))), 0)} | AD34: {=IFERROR(_xlfn.FORECAST.LINEAR(RIGHT(AD$6,2), $J34:$U34, VALUE(RIGHT($J$6:$U$6,2))), 0)} | AE34: {=IFERROR(_xlfn.FORECAST.LINEAR(RIGHT(AE$6,2), $J34:$U34, VALUE(RIGHT($J$6:$U$6,2))), 0)} | AF34: {=IFERROR(_xlfn.FORECAST.LINEAR(RIGHT(AF$6,2), $J34:$U34, VALUE(RIGHT($J$6:$U$6,2))), 0)} | ... AH34: {=IFERROR(_xlfn.FORECAST.LINEAR(RIGHT(AH$6,2), $J34:$U34, VALUE(RIGHT($J$6:$U$6,2))), 0)}
D35: Subsidiary 6 | Y35: {=IFERROR(_xlfn.FORECAST.LINEAR(RIGHT(Y$6,2), $J35:$U35, VALUE(RIGHT($J$6:$U$6,2))), 0)} | Z35: {=IFERROR(_xlfn.FORECAST.LINEAR(RIGHT(Z$6,2), $J35:$U35, VALUE(RIGHT($J$6:$U$6,2))), 0)} | AA35: {=IFERROR(_xlfn.FORECAST.LINEAR(RIGHT(AA$6,2), $J35:$U35, VALUE(RIGHT($J$6:$U$6,2))), 0)} | AB35: {=IFERROR(_xlfn.FORECAST.LINEAR(RIGHT(AB$6,2), $J35:$U35, VALUE(RIGHT($J$6:$U$6,2))), 0)} | AC35: {=IFERROR(_xlfn.FORECAST.LINEAR(RIGHT(AC$6,2), $J35:$U35, VALUE(RIGHT($J$6:$U$6,2))), 0)} | AD35: {=IFERROR(_xlfn.FORECAST.LINEAR(RIGHT(AD$6,2), $J35:$U35, VALUE(RIGHT($J$6:$U$6,2))), 0)} | AE35: {=IFERROR(_xlfn.FORECAST.LINEAR(RIGHT(AE$6,2), $J35:$U35, VALUE(RIGHT($J$6:$U$6,2))), 0)} | AF35: {=IFERROR(_xlfn.FORECAST.LINEAR(RIGHT(AF$6,2), $J35:$U35, VALUE(RIGHT($J$6:$U$6,2))), 0)} | ... AH35: {=IFERROR(_xlfn.FORECAST.LINEAR(RIGHT(AH$6,2), $J35:$U35, VALUE(RIGHT($J$6:$U$6,2))), 0)}
C37: Consolidated Profit | L37: ='Data Sheet'!B30 | M37: ='Data Sheet'!C30 | N37: ='Data Sheet'!D30 | O37: ='Data Sheet'!E30 | P37: ='Data Sheet'!F30 | Q37: ='Data Sheet'!G30 | R37: ='Data Sheet'!H30 | S37: ='Data Sheet'!I30 | ... U37: ='Data Sheet'!K30 | Y37: {=IFERROR(_xlfn.FORECAST.LINEAR(RIGHT(Y$6,2), $J37:$U37, VALUE(RIGHT($J$6:$U$6,2))), 0)} | Z37: {=IFERROR(_xlfn.FORECAST.LINEAR(RIGHT(Z$6,2), $J37:$U37, VALUE(RIGHT($J$6:$U$6,2))), 0)} | AA37: {=IFERROR(_xlfn.FORECAST.LINEAR(RIGHT(AA$6,2), $J37:$U37, VALUE(RIGHT($J$6:$U$6,2))), 0)} | AB37: {=IFERROR(_xlfn.FORECAST.LINEAR(RIGHT(AB$6,2), $J37:$U37, VALUE(RIGHT($J$6:$U$6,2))), 0)} | AC37: {=IFERROR(_xlfn.FORECAST.LINEAR(RIGHT(AC$6,2), $J37:$U37, VALUE(RIGHT($J$6:$U$6,2))), 0)} | AD37: {=IFERROR(_xlfn.FORECAST.LINEAR(RIGHT(AD$6,2), $J37:$U37, VALUE(RIGHT($J$6:$U$6,2))), 0)} | AE37: {=IFERROR(_xlfn.FORECAST.LINEAR(RIGHT(AE$6,2), $J37:$U37, VALUE(RIGHT($J$6:$U$6,2))), 0)} | AF37: {=IFERROR(_xlfn.FORECAST.LINEAR(RIGHT(AF$6,2), $J37:$U37, VALUE(RIGHT($J$6:$U$6,2))), 0)} | ... AH37: {=IFERROR(_xlfn.FORECAST.LINEAR(RIGHT(AH$6,2), $J37:$U37, VALUE(RIGHT($J$6:$U$6,2))), 0)}
C39: Wt. Avg. Shares | H39: =HistoricalData!H349 | J39: =HistoricalData!J349 | K39: =HistoricalData!K349 | L39: =HistoricalData!L349 | M39: =HistoricalData!M349 | N39: =HistoricalData!N349 | O39: =HistoricalData!O349 | P39: =HistoricalData!P349 | Q39: =HistoricalData!Q349 | ... U39: =HistoricalData!U349 | Y39: =$U39 | Z39: =$U39 | AA39: =$U39 | AB39: =$U39 | AC39: =$U39 | AD39: =$U39 | AE39: =$U39 | AF39: =$U39 | ... AH39: =$U39
C40: EPS (Diluted) | H40: =HistoricalData!H350 | J40: =HistoricalData!J350 | K40: =HistoricalData!K350 | L40: =HistoricalData!L350 | M40: =HistoricalData!M350 | N40: =HistoricalData!N350 | O40: =HistoricalData!O350 | P40: =HistoricalData!P350 | Q40: =HistoricalData!Q350 | ... U40: =HistoricalData!U350 | Y40: =IFERROR(Y37/Y39, 0) | Z40: =IFERROR(Z37/Z39, 0) | AA40: =IFERROR(AA37/AA39, 0) | AB40: =IFERROR(AB37/AB39, 0) | AC40: =IFERROR(AC37/AC39, 0) | AD40: =IFERROR(AD37/AD39, 0) | AE40: =IFERROR(AE37/AE39, 0) | AF40: =IFERROR(AF37/AF39, 0) | ... AH40: =IFERROR(AH37/AH39, 0)
C41: Share Price | H41: =H40 | J41: =HistoricalData!J351 | K41: =HistoricalData!K351 | L41: =HistoricalData!L351 | M41: =HistoricalData!M351 | N41: =HistoricalData!N351 | O41: =HistoricalData!O351 | P41: =HistoricalData!P351 | Q41: =HistoricalData!Q351 | ... U41: =HistoricalData!U351 | Y41: =$U$43*Y40 | Z41: =$U$43*Z40 | AA41: =$U$43*AA40 | AB41: =$U$43*AB40 | AC41: =$U$43*AC40 | AD41: =$U$43*AD40 | AE41: =$U$43*AE40 | AF41: =$U$43*AF40 | ... AH41: =$U$43*AH40
C42: Market Cap | H42: =$H$10 | J42: =IFERROR(J41*J39, 0) | K42: =IFERROR(K41*K39, 0) | L42: =IFERROR(L41*L39, 0) | M42: =IFERROR(M41*M39, 0) | N42: =IFERROR(N41*N39, 0) | O42: =IFERROR(O41*O39, 0) | P42: =IFERROR(P41*P39, 0) | Q42: =IFERROR(Q41*Q39, 0) | ... U42: =IFERROR(U41*U39, 0) | Y42: =IFERROR(Y41*Y39, 0) | Z42: =IFERROR(Z41*Z39, 0) | AA42: =IFERROR(AA41*AA39, 0) | AB42: =IFERROR(AB41*AB39, 0) | AC42: =IFERROR(AC41*AC39, 0) | AD42: =IFERROR(AD41*AD39, 0) | AE42: =IFERROR(AE41*AE39, 0) | AF42: =IFERROR(AF41*AF39, 0) | ... AH42: =IFERROR(AH41*AH39, 0)
C43: TTM PE | J43: =IFERROR(J41/J40, 0) | K43: =IFERROR(K41/K40, 0) | L43: =IFERROR(L41/L40, 0) | M43: =IFERROR(M41/M40, 0) | N43: =IFERROR(N41/N40, 0) | O43: =IFERROR(O41/O40, 0) | P43: =IFERROR(P41/P40, 0) | Q43: =IFERROR(Q41/Q40, 0) | ... U43: =IFERROR(U41/U40, 0) | Y43: =IFERROR(Y41/Y40, 0) | Z43: =IFERROR(Z41/Z40, 0) | AA43: =IFERROR(AA41/AA40, 0) | AB43: =IFERROR(AB41/AB40, 0) | AC43: =IFERROR(AC41/AC40, 0) | AD43: =IFERROR(AD41/AD40, 0) | AE43: =IFERROR(AE41/AE40, 0) | AF43: =IFERROR(AF41/AF40, 0) | ... AH43: =IFERROR(AH41/AH40, 0)
C44: Book Value | H44: =$H$10 | J44: =HistoricalData!J522 | K44: =HistoricalData!K522 | L44: =HistoricalData!L522 | M44: =HistoricalData!M522 | N44: =HistoricalData!N522 | O44: =HistoricalData!O522 | P44: =HistoricalData!P522 | Q44: =HistoricalData!Q522 | ... U44: =HistoricalData!U522
C45: TTM PB | J45: =IFERROR(J42/J44, 0) | K45: =IFERROR(K42/K44, 0) | L45: =IFERROR(L42/L44, 0) | M45: =IFERROR(M42/M44, 0) | N45: =IFERROR(N42/N44, 0) | O45: =IFERROR(O42/O44, 0) | P45: =IFERROR(P42/P44, 0) | Q45: =IFERROR(Q42/Q44, 0) | ... U45: =IFERROR(U42/U44, 0)
C46: Result Date
U49: =$U$2
B50: ='Assumptions&Scenario'!$K$10
B51: Annual Banking History | Y51: Annual Banking Forecast
C53: FIN Years | J53: ="FY"&TEXT(RIGHT(K53,2)-(COLUMN(K53)-COLUMN()),"00") | K53: ="FY"&TEXT(RIGHT(L53,2)-(COLUMN(L53)-COLUMN()),"00") | L53: ="FY"&TEXT(RIGHT(M53,2)-(COLUMN(M53)-COLUMN()),"00") | M53: ="FY"&TEXT(RIGHT(N53,2)-(COLUMN(N53)-COLUMN()),"00") | N53: ="FY"&TEXT(RIGHT(O53,2)-(COLUMN(O53)-COLUMN()),"00") | O53: ="FY"&TEXT(RIGHT(P53,2)-(COLUMN(P53)-COLUMN()),"00") | P53: ="FY"&TEXT(RIGHT(Q53,2)-(COLUMN(Q53)-COLUMN()),"00") | Q53: ="FY"&TEXT(RIGHT(R53,2)-(COLUMN(R53)-COLUMN()),"00") | ... T53: ="FY"&TEXT(RIGHT(U53,2)-(COLUMN(U53)-COLUMN()),"00") | U53: ="FY"&TEXT(DATE(YEAR('Data Sheet'!$K$16)+(MONTH('Data Sheet'!$K$16)>3),1,1),"YY") | Y53: =Model!$L$6 | Z53: ="FY"&TEXT(RIGHT(Y53,2)+COLUMN()-COLUMN(Y53),"00") | AA53: ="FY"&TEXT(RIGHT(Z53,2)+COLUMN()-COLUMN(Z53),"00") | AB53: ="FY"&TEXT(RIGHT(AA53,2)+COLUMN()-COLUMN(AA53),"00") | AC53: ="FY"&TEXT(RIGHT(AB53,2)+COLUMN()-COLUMN(AB53),"00") | AD53: ="FY"&TEXT(RIGHT(AC53,2)+COLUMN()-COLUMN(AC53),"00") | AE53: ="FY"&TEXT(RIGHT(AD53,2)+COLUMN()-COLUMN(AD53),"00") | AF53: ="FY"&TEXT(RIGHT(AE53,2)+COLUMN()-COLUMN(AE53),"00") | AG53: ="FY"&TEXT(RIGHT(AF53,2)+COLUMN()-COLUMN(AF53),"00") | AH53: ="FY"&TEXT(RIGHT(AG53,2)+COLUMN()-COLUMN(AG53),"00")
C57: Deposits | H57: =$H$10 | Y57: {=IFERROR(_xlfn.FORECAST.LINEAR(RIGHT(Y$6,2), $J57:$U57, VALUE(RIGHT($J$6:$U$6,2))), 0)} | Z57: {=IFERROR(_xlfn.FORECAST.LINEAR(RIGHT(Z$6,2), $J57:$U57, VALUE(RIGHT($J$6:$U$6,2))), 0)} | AA57: {=IFERROR(_xlfn.FORECAST.LINEAR(RIGHT(AA$6,2), $J57:$U57, VALUE(RIGHT($J$6:$U$6,2))), 0)} | AB57: {=IFERROR(_xlfn.FORECAST.LINEAR(RIGHT(AB$6,2), $J57:$U57, VALUE(RIGHT($J$6:$U$6,2))), 0)} | AC57: {=IFERROR(_xlfn.FORECAST.LINEAR(RIGHT(AC$6,2), $J57:$U57, VALUE(RIGHT($J$6:$U$6,2))), 0)} | AD57: {=IFERROR(_xlfn.FORECAST.LINEAR(RIGHT(AD$6,2), $J57:$U57, VALUE(RIGHT($J$6:$U$6,2))), 0)} | AE57: {=IFERROR(_xlfn.FORECAST.LINEAR(RIGHT(AE$6,2), $J57:$U57, VALUE(RIGHT($J$6:$U$6,2))), 0)} | AF57: {=IFERROR(_xlfn.FORECAST.LINEAR(RIGHT(AF$6,2), $J57:$U57, VALUE(RIGHT($J$6:$U$6,2))), 0)} | ... AH57: {=IFERROR(_xlfn.FORECAST.LINEAR(RIGHT(AH$6,2), $J57:$U57, VALUE(RIGHT($J$6:$U$6,2))), 0)}
D58: Deposits Growth | K58: =IFERROR(K57/J57-1, 0) | L58: =IFERROR(L57/K57-1, 0) | M58: =IFERROR(M57/L57-1, 0) | N58: =IFERROR(N57/M57-1, 0) | O58: =IFERROR(O57/N57-1, 0) | P58: =IFERROR(P57/O57-1, 0) | Q58: =IFERROR(Q57/P57-1, 0) | R58: =IFERROR(R57/Q57-1, 0) | ... U58: =IFERROR(U57/T57-1, 0) | Y58: =IFERROR(Y57/U57-1, 0) | Z58: =IFERROR(Z57/Y57-1, 0) | AA58: =IFERROR(AA57/Z57-1, 0) | AB58: =IFERROR(AB57/AA57-1, 0) | AC58: =IFERROR(AC57/AB57-1, 0) | AD58: =IFERROR(AD57/AC57-1, 0) | AE58: =IFERROR(AE57/AD57-1, 0) | AF58: =IFERROR(AF57/AE57-1, 0) | AG58: =IFERROR(AG57/AF57-1, 0) | AH58: =IFERROR(AH57/AG57-1, 0)
C59: Loans / AUM | Y59: {=IFERROR(_xlfn.FORECAST.LINEAR(RIGHT(Y$6,2), $J59:$U59, VALUE(RIGHT($J$6:$U$6,2))), 0)} | Z59: {=IFERROR(_xlfn.FORECAST.LINEAR(RIGHT(Z$6,2), $J59:$U59, VALUE(RIGHT($J$6:$U$6,2))), 0)} | AA59: {=IFERROR(_xlfn.FORECAST.LINEAR(RIGHT(AA$6,2), $J59:$U59, VALUE(RIGHT($J$6:$U$6,2))), 0)} | AB59: {=IFERROR(_xlfn.FORECAST.LINEAR(RIGHT(AB$6,2), $J59:$U59, VALUE(RIGHT($J$6:$U$6,2))), 0)} | AC59: {=IFERROR(_xlfn.FORECAST.LINEAR(RIGHT(AC$6,2), $J59:$U59, VALUE(RIGHT($J$6:$U$6,2))), 0)} | AD59: {=IFERROR(_xlfn.FORECAST.LINEAR(RIGHT(AD$6,2), $J59:$U59, VALUE(RIGHT($J$6:$U$6,2))), 0)} | AE59: {=IFERROR(_xlfn.FORECAST.LINEAR(RIGHT(AE$6,2), $J59:$U59, VALUE(RIGHT($J$6:$U$6,2))), 0)} | AF59: {=IFERROR(_xlfn.FORECAST.LINEAR(RIGHT(AF$6,2), $J59:$U59, VALUE(RIGHT($J$6:$U$6,2))), 0)} | ... AH59: {=IFERROR(_xlfn.FORECAST.LINEAR(RIGHT(AH$6,2), $J59:$U59, VALUE(RIGHT($J$6:$U$6,2))), 0)}
D60: Loan/AUM Growth | K60: =IFERROR(K59/J59-1, 0) | L60: =IFERROR(L59/K59-1, 0) | M60: =IFERROR(M59/L59-1, 0) | N60: =IFERROR(N59/M59-1, 0) | O60: =IFERROR(O59/N59-1, 0) | P60: =IFERROR(P59/O59-1, 0) | Q60: =IFERROR(Q59/P59-1, 0) | R60: =IFERROR(R59/Q59-1, 0) | ... U60: =IFERROR(U59/T59-1, 0) | Y60: =IFERROR(Y59/U59-1, 0) | Z60: =IFERROR(Z59/Y59-1, 0) | AA60: =IFERROR(AA59/Z59-1, 0) | AB60: =IFERROR(AB59/AA59-1, 0) | AC60: =IFERROR(AC59/AB59-1, 0) | AD60: =IFERROR(AD59/AC59-1, 0) | AE60: =IFERROR(AE59/AD59-1, 0) | AF60: =IFERROR(AF59/AE59-1, 0) | AG60: =IFERROR(AG59/AF59-1, 0) | AH60: =IFERROR(AH59/AG59-1, 0)
D61: NII/Loans or AUM | J61: =IFERROR(J12/J59, 0) | K61: =IFERROR(K12/K59, 0) | L61: =IFERROR(L12/L59, 0) | M61: =IFERROR(M12/M59, 0) | N61: =IFERROR(N12/N59, 0) | O61: =IFERROR(O12/O59, 0) | P61: =IFERROR(P12/P59, 0) | Q61: =IFERROR(Q12/Q59, 0) | ... U61: =IFERROR(U12/U59, 0)
C62: Net Disbursment | Y62: {=IFERROR(_xlfn.FORECAST.LINEAR(RIGHT(Y$6,2), $J62:$U62, VALUE(RIGHT($J$6:$U$6,2))), 0)} | Z62: {=IFERROR(_xlfn.FORECAST.LINEAR(RIGHT(Z$6,2), $J62:$U62, VALUE(RIGHT($J$6:$U$6,2))), 0)} | AA62: {=IFERROR(_xlfn.FORECAST.LINEAR(RIGHT(AA$6,2), $J62:$U62, VALUE(RIGHT($J$6:$U$6,2))), 0)} | AB62: {=IFERROR(_xlfn.FORECAST.LINEAR(RIGHT(AB$6,2), $J62:$U62, VALUE(RIGHT($J$6:$U$6,2))), 0)} | AC62: {=IFERROR(_xlfn.FORECAST.LINEAR(RIGHT(AC$6,2), $J62:$U62, VALUE(RIGHT($J$6:$U$6,2))), 0)} | AD62: {=IFERROR(_xlfn.FORECAST.LINEAR(RIGHT(AD$6,2), $J62:$U62, VALUE(RIGHT($J$6:$U$6,2))), 0)} | AE62: {=IFERROR(_xlfn.FORECAST.LINEAR(RIGHT(AE$6,2), $J62:$U62, VALUE(RIGHT($J$6:$U$6,2))), 0)} | AF62: {=IFERROR(_xlfn.FORECAST.LINEAR(RIGHT(AF$6,2), $J62:$U62, VALUE(RIGHT($J$6:$U$6,2))), 0)} | ... AH62: {=IFERROR(_xlfn.FORECAST.LINEAR(RIGHT(AH$6,2), $J62:$U62, VALUE(RIGHT($J$6:$U$6,2))), 0)}
C64: Slippages | Y64: {=IFERROR(_xlfn.FORECAST.LINEAR(RIGHT(Y$6,2), $J64:$U64, VALUE(RIGHT($J$6:$U$6,2))), 0)} | Z64: {=IFERROR(_xlfn.FORECAST.LINEAR(RIGHT(Z$6,2), $J64:$U64, VALUE(RIGHT($J$6:$U$6,2))), 0)} | AA64: {=IFERROR(_xlfn.FORECAST.LINEAR(RIGHT(AA$6,2), $J64:$U64, VALUE(RIGHT($J$6:$U$6,2))), 0)} | AB64: {=IFERROR(_xlfn.FORECAST.LINEAR(RIGHT(AB$6,2), $J64:$U64, VALUE(RIGHT($J$6:$U$6,2))), 0)} | AC64: {=IFERROR(_xlfn.FORECAST.LINEAR(RIGHT(AC$6,2), $J64:$U64, VALUE(RIGHT($J$6:$U$6,2))), 0)} | AD64: {=IFERROR(_xlfn.FORECAST.LINEAR(RIGHT(AD$6,2), $J64:$U64, VALUE(RIGHT($J$6:$U$6,2))), 0)} | AE64: {=IFERROR(_xlfn.FORECAST.LINEAR(RIGHT(AE$6,2), $J64:$U64, VALUE(RIGHT($J$6:$U$6,2))), 0)} | AF64: {=IFERROR(_xlfn.FORECAST.LINEAR(RIGHT(AF$6,2), $J64:$U64, VALUE(RIGHT($J$6:$U$6,2))), 0)} | ... AH64: {=IFERROR(_xlfn.FORECAST.LINEAR(RIGHT(AH$6,2), $J64:$U64, VALUE(RIGHT($J$6:$U$6,2))), 0)}
C65: Slippages%
C66: GNPA | Y66: {=IFERROR(_xlfn.FORECAST.LINEAR(RIGHT(Y$6,2), $J66:$U66, VALUE(RIGHT($J$6:$U$6,2))), 0)} | Z66: {=IFERROR(_xlfn.FORECAST.LINEAR(RIGHT(Z$6,2), $J66:$U66, VALUE(RIGHT($J$6:$U$6,2))), 0)} | AA66: {=IFERROR(_xlfn.FORECAST.LINEAR(RIGHT(AA$6,2), $J66:$U66, VALUE(RIGHT($J$6:$U$6,2))), 0)} | AB66: {=IFERROR(_xlfn.FORECAST.LINEAR(RIGHT(AB$6,2), $J66:$U66, VALUE(RIGHT($J$6:$U$6,2))), 0)} | AC66: {=IFERROR(_xlfn.FORECAST.LINEAR(RIGHT(AC$6,2), $J66:$U66, VALUE(RIGHT($J$6:$U$6,2))), 0)} | AD66: {=IFERROR(_xlfn.FORECAST.LINEAR(RIGHT(AD$6,2), $J66:$U66, VALUE(RIGHT($J$6:$U$6,2))), 0)} | AE66: {=IFERROR(_xlfn.FORECAST.LINEAR(RIGHT(AE$6,2), $J66:$U66, VALUE(RIGHT($J$6:$U$6,2))), 0)} | AF66: {=IFERROR(_xlfn.FORECAST.LINEAR(RIGHT(AF$6,2), $J66:$U66, VALUE(RIGHT($J$6:$U$6,2))), 0)} | ... AH66: {=IFERROR(_xlfn.FORECAST.LINEAR(RIGHT(AH$6,2), $J66:$U66, VALUE(RIGHT($J$6:$U$6,2))), 0)}
C67: NNPA | Y67: {=IFERROR(_xlfn.FORECAST.LINEAR(RIGHT(Y$6,2), $J67:$U67, VALUE(RIGHT($J$6:$U$6,2))), 0)} | Z67: {=IFERROR(_xlfn.FORECAST.LINEAR(RIGHT(Z$6,2), $J67:$U67, VALUE(RIGHT($J$6:$U$6,2))), 0)} | AA67: {=IFERROR(_xlfn.FORECAST.LINEAR(RIGHT(AA$6,2), $J67:$U67, VALUE(RIGHT($J$6:$U$6,2))), 0)} | AB67: {=IFERROR(_xlfn.FORECAST.LINEAR(RIGHT(AB$6,2), $J67:$U67, VALUE(RIGHT($J$6:$U$6,2))), 0)} | AC67: {=IFERROR(_xlfn.FORECAST.LINEAR(RIGHT(AC$6,2), $J67:$U67, VALUE(RIGHT($J$6:$U$6,2))), 0)} | AD67: {=IFERROR(_xlfn.FORECAST.LINEAR(RIGHT(AD$6,2), $J67:$U67, VALUE(RIGHT($J$6:$U$6,2))), 0)} | AE67: {=IFERROR(_xlfn.FORECAST.LINEAR(RIGHT(AE$6,2), $J67:$U67, VALUE(RIGHT($J$6:$U$6,2))), 0)} | AF67: {=IFERROR(_xlfn.FORECAST.LINEAR(RIGHT(AF$6,2), $J67:$U67, VALUE(RIGHT($J$6:$U$6,2))), 0)} | ... AH67: {=IFERROR(_xlfn.FORECAST.LINEAR(RIGHT(AH$6,2), $J67:$U67, VALUE(RIGHT($J$6:$U$6,2))), 0)}
C68: GNPA%
C69: NNPA%
C71: PCR (calc)%
C72: Cost to Core Income%
C73: CASA (Reported)%
C74: CAR (Tier-1)
C76: RoA%
C77: RoE%
C79: Branches | Y79: {=IFERROR(_xlfn.FORECAST.LINEAR(RIGHT(Y$6,2), $J79:$U79, VALUE(RIGHT($J$6:$U$6,2))), 0)} | Z79: {=IFERROR(_xlfn.FORECAST.LINEAR(RIGHT(Z$6,2), $J79:$U79, VALUE(RIGHT($J$6:$U$6,2))), 0)} | AA79: {=IFERROR(_xlfn.FORECAST.LINEAR(RIGHT(AA$6,2), $J79:$U79, VALUE(RIGHT($J$6:$U$6,2))), 0)} | AB79: {=IFERROR(_xlfn.FORECAST.LINEAR(RIGHT(AB$6,2), $J79:$U79, VALUE(RIGHT($J$6:$U$6,2))), 0)} | AC79: {=IFERROR(_xlfn.FORECAST.LINEAR(RIGHT(AC$6,2), $J79:$U79, VALUE(RIGHT($J$6:$U$6,2))), 0)} | AD79: {=IFERROR(_xlfn.FORECAST.LINEAR(RIGHT(AD$6,2), $J79:$U79, VALUE(RIGHT($J$6:$U$6,2))), 0)} | AE79: {=IFERROR(_xlfn.FORECAST.LINEAR(RIGHT(AE$6,2), $J79:$U79, VALUE(RIGHT($J$6:$U$6,2))), 0)} | AF79: {=IFERROR(_xlfn.FORECAST.LINEAR(RIGHT(AF$6,2), $J79:$U79, VALUE(RIGHT($J$6:$U$6,2))), 0)} | ... AH79: {=IFERROR(_xlfn.FORECAST.LINEAR(RIGHT(AH$6,2), $J79:$U79, VALUE(RIGHT($J$6:$U$6,2))), 0)}
C80: ATM | Y80: {=IFERROR(_xlfn.FORECAST.LINEAR(RIGHT(Y$6,2), $J80:$U80, VALUE(RIGHT($J$6:$U$6,2))), 0)} | Z80: {=IFERROR(_xlfn.FORECAST.LINEAR(RIGHT(Z$6,2), $J80:$U80, VALUE(RIGHT($J$6:$U$6,2))), 0)} | AA80: {=IFERROR(_xlfn.FORECAST.LINEAR(RIGHT(AA$6,2), $J80:$U80, VALUE(RIGHT($J$6:$U$6,2))), 0)} | AB80: {=IFERROR(_xlfn.FORECAST.LINEAR(RIGHT(AB$6,2), $J80:$U80, VALUE(RIGHT($J$6:$U$6,2))), 0)} | AC80: {=IFERROR(_xlfn.FORECAST.LINEAR(RIGHT(AC$6,2), $J80:$U80, VALUE(RIGHT($J$6:$U$6,2))), 0)} | AD80: {=IFERROR(_xlfn.FORECAST.LINEAR(RIGHT(AD$6,2), $J80:$U80, VALUE(RIGHT($J$6:$U$6,2))), 0)} | AE80: {=IFERROR(_xlfn.FORECAST.LINEAR(RIGHT(AE$6,2), $J80:$U80, VALUE(RIGHT($J$6:$U$6,2))), 0)} | AF80: {=IFERROR(_xlfn.FORECAST.LINEAR(RIGHT(AF$6,2), $J80:$U80, VALUE(RIGHT($J$6:$U$6,2))), 0)} | ... AH80: {=IFERROR(_xlfn.FORECAST.LINEAR(RIGHT(AH$6,2), $J80:$U80, VALUE(RIGHT($J$6:$U$6,2))), 0)}
C81: Employee | Y81: {=IFERROR(_xlfn.FORECAST.LINEAR(RIGHT(Y$6,2), $J81:$U81, VALUE(RIGHT($J$6:$U$6,2))), 0)} | Z81: {=IFERROR(_xlfn.FORECAST.LINEAR(RIGHT(Z$6,2), $J81:$U81, VALUE(RIGHT($J$6:$U$6,2))), 0)} | AA81: {=IFERROR(_xlfn.FORECAST.LINEAR(RIGHT(AA$6,2), $J81:$U81, VALUE(RIGHT($J$6:$U$6,2))), 0)} | AB81: {=IFERROR(_xlfn.FORECAST.LINEAR(RIGHT(AB$6,2), $J81:$U81, VALUE(RIGHT($J$6:$U$6,2))), 0)} | AC81: {=IFERROR(_xlfn.FORECAST.LINEAR(RIGHT(AC$6,2), $J81:$U81, VALUE(RIGHT($J$6:$U$6,2))), 0)} | AD81: {=IFERROR(_xlfn.FORECAST.LINEAR(RIGHT(AD$6,2), $J81:$U81, VALUE(RIGHT($J$6:$U$6,2))), 0)} | AE81: {=IFERROR(_xlfn.FORECAST.LINEAR(RIGHT(AE$6,2), $J81:$U81, VALUE(RIGHT($J$6:$U$6,2))), 0)} | AF81: {=IFERROR(_xlfn.FORECAST.LINEAR(RIGHT(AF$6,2), $J81:$U81, VALUE(RIGHT($J$6:$U$6,2))), 0)} | ... AH81: {=IFERROR(_xlfn.FORECAST.LINEAR(RIGHT(AH$6,2), $J81:$U81, VALUE(RIGHT($J$6:$U$6,2))), 0)}
U84: =$U$2
B85: ='Assumptions&Scenario'!$K$10
B86: Annual Loan Distribution History | Y86: Annual Loan Distribution Forecast
C88: FIN Years | J88: ="FY"&TEXT(RIGHT(K88,2)-(COLUMN(K88)-COLUMN()),"00") | K88: ="FY"&TEXT(RIGHT(L88,2)-(COLUMN(L88)-COLUMN()),"00") | L88: ="FY"&TEXT(RIGHT(M88,2)-(COLUMN(M88)-COLUMN()),"00") | M88: ="FY"&TEXT(RIGHT(N88,2)-(COLUMN(N88)-COLUMN()),"00") | N88: ="FY"&TEXT(RIGHT(O88,2)-(COLUMN(O88)-COLUMN()),"00") | O88: ="FY"&TEXT(RIGHT(P88,2)-(COLUMN(P88)-COLUMN()),"00") | P88: ="FY"&TEXT(RIGHT(Q88,2)-(COLUMN(Q88)-COLUMN()),"00") | Q88: ="FY"&TEXT(RIGHT(R88,2)-(COLUMN(R88)-COLUMN()),"00") | ... T88: ="FY"&TEXT(RIGHT(U88,2)-(COLUMN(U88)-COLUMN()),"00") | U88: ="FY"&TEXT(DATE(YEAR('Data Sheet'!$K$16)+(MONTH('Data Sheet'!$K$16)>3),1,1),"YY") | Y88: =Model!$L$6 | Z88: ="FY"&TEXT(RIGHT(Y88,2)+COLUMN()-COLUMN(Y88),"00") | AA88: ="FY"&TEXT(RIGHT(Z88,2)+COLUMN()-COLUMN(Z88),"00") | AB88: ="FY"&TEXT(RIGHT(AA88,2)+COLUMN()-COLUMN(AA88),"00") | AC88: ="FY"&TEXT(RIGHT(AB88,2)+COLUMN()-COLUMN(AB88),"00") | AD88: ="FY"&TEXT(RIGHT(AC88,2)+COLUMN()-COLUMN(AC88),"00") | AE88: ="FY"&TEXT(RIGHT(AD88,2)+COLUMN()-COLUMN(AD88),"00") | AF88: ="FY"&TEXT(RIGHT(AE88,2)+COLUMN()-COLUMN(AE88),"00") | AG88: ="FY"&TEXT(RIGHT(AF88,2)+COLUMN()-COLUMN(AF88),"00") | AH88: ="FY"&TEXT(RIGHT(AG88,2)+COLUMN()-COLUMN(AG88),"00")
C93: Total Retail | H93: =$H$10 | Y93: {=IFERROR(_xlfn.FORECAST.LINEAR(RIGHT(Y$6,2), $J93:$U93, VALUE(RIGHT($J$6:$U$6,2))), 0)} | Z93: {=IFERROR(_xlfn.FORECAST.LINEAR(RIGHT(Z$6,2), $J93:$U93, VALUE(RIGHT($J$6:$U$6,2))), 0)} | AA93: {=IFERROR(_xlfn.FORECAST.LINEAR(RIGHT(AA$6,2), $J93:$U93, VALUE(RIGHT($J$6:$U$6,2))), 0)} | AB93: {=IFERROR(_xlfn.FORECAST.LINEAR(RIGHT(AB$6,2), $J93:$U93, VALUE(RIGHT($J$6:$U$6,2))), 0)} | AC93: {=IFERROR(_xlfn.FORECAST.LINEAR(RIGHT(AC$6,2), $J93:$U93, VALUE(RIGHT($J$6:$U$6,2))), 0)} | AD93: {=IFERROR(_xlfn.FORECAST.LINEAR(RIGHT(AD$6,2), $J93:$U93, VALUE(RIGHT($J$6:$U$6,2))), 0)} | AE93: {=IFERROR(_xlfn.FORECAST.LINEAR(RIGHT(AE$6,2), $J93:$U93, VALUE(RIGHT($J$6:$U$6,2))), 0)} | AF93: {=IFERROR(_xlfn.FORECAST.LINEAR(RIGHT(AF$6,2), $J93:$U93, VALUE(RIGHT($J$6:$U$6,2))), 0)} | ... AH93: {=IFERROR(_xlfn.FORECAST.LINEAR(RIGHT(AH$6,2), $J93:$U93, VALUE(RIGHT($J$6:$U$6,2))), 0)}
D94: Home Loan / Mortgage | Y94: {=IFERROR(_xlfn.FORECAST.LINEAR(RIGHT(Y$6,2), $J94:$U94, VALUE(RIGHT($J$6:$U$6,2))), 0)} | Z94: {=IFERROR(_xlfn.FORECAST.LINEAR(RIGHT(Z$6,2), $J94:$U94, VALUE(RIGHT($J$6:$U$6,2))), 0)} | AA94: {=IFERROR(_xlfn.FORECAST.LINEAR(RIGHT(AA$6,2), $J94:$U94, VALUE(RIGHT($J$6:$U$6,2))), 0)} | AB94: {=IFERROR(_xlfn.FORECAST.LINEAR(RIGHT(AB$6,2), $J94:$U94, VALUE(RIGHT($J$6:$U$6,2))), 0)} | AC94: {=IFERROR(_xlfn.FORECAST.LINEAR(RIGHT(AC$6,2), $J94:$U94, VALUE(RIGHT($J$6:$U$6,2))), 0)} | AD94: {=IFERROR(_xlfn.FORECAST.LINEAR(RIGHT(AD$6,2), $J94:$U94, VALUE(RIGHT($J$6:$U$6,2))), 0)} | AE94: {=IFERROR(_xlfn.FORECAST.LINEAR(RIGHT(AE$6,2), $J94:$U94, VALUE(RIGHT($J$6:$U$6,2))), 0)} | AF94: {=IFERROR(_xlfn.FORECAST.LINEAR(RIGHT(AF$6,2), $J94:$U94, VALUE(RIGHT($J$6:$U$6,2))), 0)} | ... AH94: {=IFERROR(_xlfn.FORECAST.LINEAR(RIGHT(AH$6,2), $J94:$U94, VALUE(RIGHT($J$6:$U$6,2))), 0)}
D95: Loan against Property | Y95: {=IFERROR(_xlfn.FORECAST.LINEAR(RIGHT(Y$6,2), $J95:$U95, VALUE(RIGHT($J$6:$U$6,2))), 0)} | Z95: {=IFERROR(_xlfn.FORECAST.LINEAR(RIGHT(Z$6,2), $J95:$U95, VALUE(RIGHT($J$6:$U$6,2))), 0)} | AA95: {=IFERROR(_xlfn.FORECAST.LINEAR(RIGHT(AA$6,2), $J95:$U95, VALUE(RIGHT($J$6:$U$6,2))), 0)} | AB95: {=IFERROR(_xlfn.FORECAST.LINEAR(RIGHT(AB$6,2), $J95:$U95, VALUE(RIGHT($J$6:$U$6,2))), 0)} | AC95: {=IFERROR(_xlfn.FORECAST.LINEAR(RIGHT(AC$6,2), $J95:$U95, VALUE(RIGHT($J$6:$U$6,2))), 0)} | AD95: {=IFERROR(_xlfn.FORECAST.LINEAR(RIGHT(AD$6,2), $J95:$U95, VALUE(RIGHT($J$6:$U$6,2))), 0)} | AE95: {=IFERROR(_xlfn.FORECAST.LINEAR(RIGHT(AE$6,2), $J95:$U95, VALUE(RIGHT($J$6:$U$6,2))), 0)} | AF95: {=IFERROR(_xlfn.FORECAST.LINEAR(RIGHT(AF$6,2), $J95:$U95, VALUE(RIGHT($J$6:$U$6,2))), 0)} | ... AH95: {=IFERROR(_xlfn.FORECAST.LINEAR(RIGHT(AH$6,2), $J95:$U95, VALUE(RIGHT($J$6:$U$6,2))), 0)}
D96: Auto / Vehicle Loan | Y96: {=IFERROR(_xlfn.FORECAST.LINEAR(RIGHT(Y$6,2), $J96:$U96, VALUE(RIGHT($J$6:$U$6,2))), 0)} | Z96: {=IFERROR(_xlfn.FORECAST.LINEAR(RIGHT(Z$6,2), $J96:$U96, VALUE(RIGHT($J$6:$U$6,2))), 0)} | AA96: {=IFERROR(_xlfn.FORECAST.LINEAR(RIGHT(AA$6,2), $J96:$U96, VALUE(RIGHT($J$6:$U$6,2))), 0)} | AB96: {=IFERROR(_xlfn.FORECAST.LINEAR(RIGHT(AB$6,2), $J96:$U96, VALUE(RIGHT($J$6:$U$6,2))), 0)} | AC96: {=IFERROR(_xlfn.FORECAST.LINEAR(RIGHT(AC$6,2), $J96:$U96, VALUE(RIGHT($J$6:$U$6,2))), 0)} | AD96: {=IFERROR(_xlfn.FORECAST.LINEAR(RIGHT(AD$6,2), $J96:$U96, VALUE(RIGHT($J$6:$U$6,2))), 0)} | AE96: {=IFERROR(_xlfn.FORECAST.LINEAR(RIGHT(AE$6,2), $J96:$U96, VALUE(RIGHT($J$6:$U$6,2))), 0)} | AF96: {=IFERROR(_xlfn.FORECAST.LINEAR(RIGHT(AF$6,2), $J96:$U96, VALUE(RIGHT($J$6:$U$6,2))), 0)} | ... AH96: {=IFERROR(_xlfn.FORECAST.LINEAR(RIGHT(AH$6,2), $J96:$U96, VALUE(RIGHT($J$6:$U$6,2))), 0)}
D97: Gold Loans | Y97: {=IFERROR(_xlfn.FORECAST.LINEAR(RIGHT(Y$6,2), $J97:$U97, VALUE(RIGHT($J$6:$U$6,2))), 0)} | Z97: {=IFERROR(_xlfn.FORECAST.LINEAR(RIGHT(Z$6,2), $J97:$U97, VALUE(RIGHT($J$6:$U$6,2))), 0)} | AA97: {=IFERROR(_xlfn.FORECAST.LINEAR(RIGHT(AA$6,2), $J97:$U97, VALUE(RIGHT($J$6:$U$6,2))), 0)} | AB97: {=IFERROR(_xlfn.FORECAST.LINEAR(RIGHT(AB$6,2), $J97:$U97, VALUE(RIGHT($J$6:$U$6,2))), 0)} | AC97: {=IFERROR(_xlfn.FORECAST.LINEAR(RIGHT(AC$6,2), $J97:$U97, VALUE(RIGHT($J$6:$U$6,2))), 0)} | AD97: {=IFERROR(_xlfn.FORECAST.LINEAR(RIGHT(AD$6,2), $J97:$U97, VALUE(RIGHT($J$6:$U$6,2))), 0)} | AE97: {=IFERROR(_xlfn.FORECAST.LINEAR(RIGHT(AE$6,2), $J97:$U97, VALUE(RIGHT($J$6:$U$6,2))), 0)} | AF97: {=IFERROR(_xlfn.FORECAST.LINEAR(RIGHT(AF$6,2), $J97:$U97, VALUE(RIGHT($J$6:$U$6,2))), 0)} | ... AH97: {=IFERROR(_xlfn.FORECAST.LINEAR(RIGHT(AH$6,2), $J97:$U97, VALUE(RIGHT($J$6:$U$6,2))), 0)}
D98: Other Secured Retail | Y98: {=IFERROR(_xlfn.FORECAST.LINEAR(RIGHT(Y$6,2), $J98:$U98, VALUE(RIGHT($J$6:$U$6,2))), 0)} | Z98: {=IFERROR(_xlfn.FORECAST.LINEAR(RIGHT(Z$6,2), $J98:$U98, VALUE(RIGHT($J$6:$U$6,2))), 0)} | AA98: {=IFERROR(_xlfn.FORECAST.LINEAR(RIGHT(AA$6,2), $J98:$U98, VALUE(RIGHT($J$6:$U$6,2))), 0)} | AB98: {=IFERROR(_xlfn.FORECAST.LINEAR(RIGHT(AB$6,2), $J98:$U98, VALUE(RIGHT($J$6:$U$6,2))), 0)} | AC98: {=IFERROR(_xlfn.FORECAST.LINEAR(RIGHT(AC$6,2), $J98:$U98, VALUE(RIGHT($J$6:$U$6,2))), 0)} | AD98: {=IFERROR(_xlfn.FORECAST.LINEAR(RIGHT(AD$6,2), $J98:$U98, VALUE(RIGHT($J$6:$U$6,2))), 0)} | AE98: {=IFERROR(_xlfn.FORECAST.LINEAR(RIGHT(AE$6,2), $J98:$U98, VALUE(RIGHT($J$6:$U$6,2))), 0)} | AF98: {=IFERROR(_xlfn.FORECAST.LINEAR(RIGHT(AF$6,2), $J98:$U98, VALUE(RIGHT($J$6:$U$6,2))), 0)} | ... AH98: {=IFERROR(_xlfn.FORECAST.LINEAR(RIGHT(AH$6,2), $J98:$U98, VALUE(RIGHT($J$6:$U$6,2))), 0)}
D99: Personal Loans | Y99: {=IFERROR(_xlfn.FORECAST.LINEAR(RIGHT(Y$6,2), $J99:$U99, VALUE(RIGHT($J$6:$U$6,2))), 0)} | Z99: {=IFERROR(_xlfn.FORECAST.LINEAR(RIGHT(Z$6,2), $J99:$U99, VALUE(RIGHT($J$6:$U$6,2))), 0)} | AA99: {=IFERROR(_xlfn.FORECAST.LINEAR(RIGHT(AA$6,2), $J99:$U99, VALUE(RIGHT($J$6:$U$6,2))), 0)} | AB99: {=IFERROR(_xlfn.FORECAST.LINEAR(RIGHT(AB$6,2), $J99:$U99, VALUE(RIGHT($J$6:$U$6,2))), 0)} | AC99: {=IFERROR(_xlfn.FORECAST.LINEAR(RIGHT(AC$6,2), $J99:$U99, VALUE(RIGHT($J$6:$U$6,2))), 0)} | AD99: {=IFERROR(_xlfn.FORECAST.LINEAR(RIGHT(AD$6,2), $J99:$U99, VALUE(RIGHT($J$6:$U$6,2))), 0)} | AE99: {=IFERROR(_xlfn.FORECAST.LINEAR(RIGHT(AE$6,2), $J99:$U99, VALUE(RIGHT($J$6:$U$6,2))), 0)} | AF99: {=IFERROR(_xlfn.FORECAST.LINEAR(RIGHT(AF$6,2), $J99:$U99, VALUE(RIGHT($J$6:$U$6,2))), 0)} | ... AH99: {=IFERROR(_xlfn.FORECAST.LINEAR(RIGHT(AH$6,2), $J99:$U99, VALUE(RIGHT($J$6:$U$6,2))), 0)}
D100: Credit Card / Payment Products | Y100: {=IFERROR(_xlfn.FORECAST.LINEAR(RIGHT(Y$6,2), $J100:$U100, VALUE(RIGHT($J$6:$U$6,2))), 0)} | Z100: {=IFERROR(_xlfn.FORECAST.LINEAR(RIGHT(Z$6,2), $J100:$U100, VALUE(RIGHT($J$6:$U$6,2))), 0)} | AA100: {=IFERROR(_xlfn.FORECAST.LINEAR(RIGHT(AA$6,2), $J100:$U100, VALUE(RIGHT($J$6:$U$6,2))), 0)} | AB100: {=IFERROR(_xlfn.FORECAST.LINEAR(RIGHT(AB$6,2), $J100:$U100, VALUE(RIGHT($J$6:$U$6,2))), 0)} | AC100: {=IFERROR(_xlfn.FORECAST.LINEAR(RIGHT(AC$6,2), $J100:$U100, VALUE(RIGHT($J$6:$U$6,2))), 0)} | AD100: {=IFERROR(_xlfn.FORECAST.LINEAR(RIGHT(AD$6,2), $J100:$U100, VALUE(RIGHT($J$6:$U$6,2))), 0)} | AE100: {=IFERROR(_xlfn.FORECAST.LINEAR(RIGHT(AE$6,2), $J100:$U100, VALUE(RIGHT($J$6:$U$6,2))), 0)} | AF100: {=IFERROR(_xlfn.FORECAST.LINEAR(RIGHT(AF$6,2), $J100:$U100, VALUE(RIGHT($J$6:$U$6,2))), 0)} | ... AH100: {=IFERROR(_xlfn.FORECAST.LINEAR(RIGHT(AH$6,2), $J100:$U100, VALUE(RIGHT($J$6:$U$6,2))), 0)}
D101: Other Unsecured Retail | Y101: {=IFERROR(_xlfn.FORECAST.LINEAR(RIGHT(Y$6,2), $J101:$U101, VALUE(RIGHT($J$6:$U$6,2))), 0)} | Z101: {=IFERROR(_xlfn.FORECAST.LINEAR(RIGHT(Z$6,2), $J101:$U101, VALUE(RIGHT($J$6:$U$6,2))), 0)} | AA101: {=IFERROR(_xlfn.FORECAST.LINEAR(RIGHT(AA$6,2), $J101:$U101, VALUE(RIGHT($J$6:$U$6,2))), 0)} | AB101: {=IFERROR(_xlfn.FORECAST.LINEAR(RIGHT(AB$6,2), $J101:$U101, VALUE(RIGHT($J$6:$U$6,2))), 0)} | AC101: {=IFERROR(_xlfn.FORECAST.LINEAR(RIGHT(AC$6,2), $J101:$U101, VALUE(RIGHT($J$6:$U$6,2))), 0)} | AD101: {=IFERROR(_xlfn.FORECAST.LINEAR(RIGHT(AD$6,2), $J101:$U101, VALUE(RIGHT($J$6:$U$6,2))), 0)} | AE101: {=IFERROR(_xlfn.FORECAST.LINEAR(RIGHT(AE$6,2), $J101:$U101, VALUE(RIGHT($J$6:$U$6,2))), 0)} | AF101: {=IFERROR(_xlfn.FORECAST.LINEAR(RIGHT(AF$6,2), $J101:$U101, VALUE(RIGHT($J$6:$U$6,2))), 0)} | ... AH101: {=IFERROR(_xlfn.FORECAST.LINEAR(RIGHT(AH$6,2), $J101:$U101, VALUE(RIGHT($J$6:$U$6,2))), 0)}
C102: Agri Loan | Y102: {=IFERROR(_xlfn.FORECAST.LINEAR(RIGHT(Y$6,2), $J102:$U102, VALUE(RIGHT($J$6:$U$6,2))), 0)} | Z102: {=IFERROR(_xlfn.FORECAST.LINEAR(RIGHT(Z$6,2), $J102:$U102, VALUE(RIGHT($J$6:$U$6,2))), 0)} | AA102: {=IFERROR(_xlfn.FORECAST.LINEAR(RIGHT(AA$6,2), $J102:$U102, VALUE(RIGHT($J$6:$U$6,2))), 0)} | AB102: {=IFERROR(_xlfn.FORECAST.LINEAR(RIGHT(AB$6,2), $J102:$U102, VALUE(RIGHT($J$6:$U$6,2))), 0)} | AC102: {=IFERROR(_xlfn.FORECAST.LINEAR(RIGHT(AC$6,2), $J102:$U102, VALUE(RIGHT($J$6:$U$6,2))), 0)} | AD102: {=IFERROR(_xlfn.FORECAST.LINEAR(RIGHT(AD$6,2), $J102:$U102, VALUE(RIGHT($J$6:$U$6,2))), 0)} | AE102: {=IFERROR(_xlfn.FORECAST.LINEAR(RIGHT(AE$6,2), $J102:$U102, VALUE(RIGHT($J$6:$U$6,2))), 0)} | AF102: {=IFERROR(_xlfn.FORECAST.LINEAR(RIGHT(AF$6,2), $J102:$U102, VALUE(RIGHT($J$6:$U$6,2))), 0)} | ... AH102: {=IFERROR(_xlfn.FORECAST.LINEAR(RIGHT(AH$6,2), $J102:$U102, VALUE(RIGHT($J$6:$U$6,2))), 0)}
C103: Corporate Total | Y103: {=IFERROR(_xlfn.FORECAST.LINEAR(RIGHT(Y$6,2), $J103:$U103, VALUE(RIGHT($J$6:$U$6,2))), 0)} | Z103: {=IFERROR(_xlfn.FORECAST.LINEAR(RIGHT(Z$6,2), $J103:$U103, VALUE(RIGHT($J$6:$U$6,2))), 0)} | AA103: {=IFERROR(_xlfn.FORECAST.LINEAR(RIGHT(AA$6,2), $J103:$U103, VALUE(RIGHT($J$6:$U$6,2))), 0)} | AB103: {=IFERROR(_xlfn.FORECAST.LINEAR(RIGHT(AB$6,2), $J103:$U103, VALUE(RIGHT($J$6:$U$6,2))), 0)} | AC103: {=IFERROR(_xlfn.FORECAST.LINEAR(RIGHT(AC$6,2), $J103:$U103, VALUE(RIGHT($J$6:$U$6,2))), 0)} | AD103: {=IFERROR(_xlfn.FORECAST.LINEAR(RIGHT(AD$6,2), $J103:$U103, VALUE(RIGHT($J$6:$U$6,2))), 0)} | AE103: {=IFERROR(_xlfn.FORECAST.LINEAR(RIGHT(AE$6,2), $J103:$U103, VALUE(RIGHT($J$6:$U$6,2))), 0)} | AF103: {=IFERROR(_xlfn.FORECAST.LINEAR(RIGHT(AF$6,2), $J103:$U103, VALUE(RIGHT($J$6:$U$6,2))), 0)} | ... AH103: {=IFERROR(_xlfn.FORECAST.LINEAR(RIGHT(AH$6,2), $J103:$U103, VALUE(RIGHT($J$6:$U$6,2))), 0)}
D104: Commercial Transportation | Y104: {=IFERROR(_xlfn.FORECAST.LINEAR(RIGHT(Y$6,2), $J104:$U104, VALUE(RIGHT($J$6:$U$6,2))), 0)} | Z104: {=IFERROR(_xlfn.FORECAST.LINEAR(RIGHT(Z$6,2), $J104:$U104, VALUE(RIGHT($J$6:$U$6,2))), 0)} | AA104: {=IFERROR(_xlfn.FORECAST.LINEAR(RIGHT(AA$6,2), $J104:$U104, VALUE(RIGHT($J$6:$U$6,2))), 0)} | AB104: {=IFERROR(_xlfn.FORECAST.LINEAR(RIGHT(AB$6,2), $J104:$U104, VALUE(RIGHT($J$6:$U$6,2))), 0)} | AC104: {=IFERROR(_xlfn.FORECAST.LINEAR(RIGHT(AC$6,2), $J104:$U104, VALUE(RIGHT($J$6:$U$6,2))), 0)} | AD104: {=IFERROR(_xlfn.FORECAST.LINEAR(RIGHT(AD$6,2), $J104:$U104, VALUE(RIGHT($J$6:$U$6,2))), 0)} | AE104: {=IFERROR(_xlfn.FORECAST.LINEAR(RIGHT(AE$6,2), $J104:$U104, VALUE(RIGHT($J$6:$U$6,2))), 0)} | AF104: {=IFERROR(_xlfn.FORECAST.LINEAR(RIGHT(AF$6,2), $J104:$U104, VALUE(RIGHT($J$6:$U$6,2))), 0)} | ... AH104: {=IFERROR(_xlfn.FORECAST.LINEAR(RIGHT(AH$6,2), $J104:$U104, VALUE(RIGHT($J$6:$U$6,2))), 0)}
D105: Microfinance | Y105: {=IFERROR(_xlfn.FORECAST.LINEAR(RIGHT(Y$6,2), $J105:$U105, VALUE(RIGHT($J$6:$U$6,2))), 0)} | Z105: {=IFERROR(_xlfn.FORECAST.LINEAR(RIGHT(Z$6,2), $J105:$U105, VALUE(RIGHT($J$6:$U$6,2))), 0)} | AA105: {=IFERROR(_xlfn.FORECAST.LINEAR(RIGHT(AA$6,2), $J105:$U105, VALUE(RIGHT($J$6:$U$6,2))), 0)} | AB105: {=IFERROR(_xlfn.FORECAST.LINEAR(RIGHT(AB$6,2), $J105:$U105, VALUE(RIGHT($J$6:$U$6,2))), 0)} | AC105: {=IFERROR(_xlfn.FORECAST.LINEAR(RIGHT(AC$6,2), $J105:$U105, VALUE(RIGHT($J$6:$U$6,2))), 0)} | AD105: {=IFERROR(_xlfn.FORECAST.LINEAR(RIGHT(AD$6,2), $J105:$U105, VALUE(RIGHT($J$6:$U$6,2))), 0)} | AE105: {=IFERROR(_xlfn.FORECAST.LINEAR(RIGHT(AE$6,2), $J105:$U105, VALUE(RIGHT($J$6:$U$6,2))), 0)} | AF105: {=IFERROR(_xlfn.FORECAST.LINEAR(RIGHT(AF$6,2), $J105:$U105, VALUE(RIGHT($J$6:$U$6,2))), 0)} | ... AH105: {=IFERROR(_xlfn.FORECAST.LINEAR(RIGHT(AH$6,2), $J105:$U105, VALUE(RIGHT($J$6:$U$6,2))), 0)}
D106: Business Banking / SME Business | Y106: {=IFERROR(_xlfn.FORECAST.LINEAR(RIGHT(Y$6,2), $J106:$U106, VALUE(RIGHT($J$6:$U$6,2))), 0)} | Z106: {=IFERROR(_xlfn.FORECAST.LINEAR(RIGHT(Z$6,2), $J106:$U106, VALUE(RIGHT($J$6:$U$6,2))), 0)} | AA106: {=IFERROR(_xlfn.FORECAST.LINEAR(RIGHT(AA$6,2), $J106:$U106, VALUE(RIGHT($J$6:$U$6,2))), 0)} | AB106: {=IFERROR(_xlfn.FORECAST.LINEAR(RIGHT(AB$6,2), $J106:$U106, VALUE(RIGHT($J$6:$U$6,2))), 0)} | AC106: {=IFERROR(_xlfn.FORECAST.LINEAR(RIGHT(AC$6,2), $J106:$U106, VALUE(RIGHT($J$6:$U$6,2))), 0)} | AD106: {=IFERROR(_xlfn.FORECAST.LINEAR(RIGHT(AD$6,2), $J106:$U106, VALUE(RIGHT($J$6:$U$6,2))), 0)} | AE106: {=IFERROR(_xlfn.FORECAST.LINEAR(RIGHT(AE$6,2), $J106:$U106, VALUE(RIGHT($J$6:$U$6,2))), 0)} | AF106: {=IFERROR(_xlfn.FORECAST.LINEAR(RIGHT(AF$6,2), $J106:$U106, VALUE(RIGHT($J$6:$U$6,2))), 0)} | ... AH106: {=IFERROR(_xlfn.FORECAST.LINEAR(RIGHT(AH$6,2), $J106:$U106, VALUE(RIGHT($J$6:$U$6,2))), 0)}
D107: Emerging Corporates | Y107: {=IFERROR(_xlfn.FORECAST.LINEAR(RIGHT(Y$6,2), $J107:$U107, VALUE(RIGHT($J$6:$U$6,2))), 0)} | Z107: {=IFERROR(_xlfn.FORECAST.LINEAR(RIGHT(Z$6,2), $J107:$U107, VALUE(RIGHT($J$6:$U$6,2))), 0)} | AA107: {=IFERROR(_xlfn.FORECAST.LINEAR(RIGHT(AA$6,2), $J107:$U107, VALUE(RIGHT($J$6:$U$6,2))), 0)} | AB107: {=IFERROR(_xlfn.FORECAST.LINEAR(RIGHT(AB$6,2), $J107:$U107, VALUE(RIGHT($J$6:$U$6,2))), 0)} | AC107: {=IFERROR(_xlfn.FORECAST.LINEAR(RIGHT(AC$6,2), $J107:$U107, VALUE(RIGHT($J$6:$U$6,2))), 0)} | AD107: {=IFERROR(_xlfn.FORECAST.LINEAR(RIGHT(AD$6,2), $J107:$U107, VALUE(RIGHT($J$6:$U$6,2))), 0)} | AE107: {=IFERROR(_xlfn.FORECAST.LINEAR(RIGHT(AE$6,2), $J107:$U107, VALUE(RIGHT($J$6:$U$6,2))), 0)} | AF107: {=IFERROR(_xlfn.FORECAST.LINEAR(RIGHT(AF$6,2), $J107:$U107, VALUE(RIGHT($J$6:$U$6,2))), 0)} | ... AH107: {=IFERROR(_xlfn.FORECAST.LINEAR(RIGHT(AH$6,2), $J107:$U107, VALUE(RIGHT($J$6:$U$6,2))), 0)}
D108: Corporate and other wholesale | Y108: {=IFERROR(_xlfn.FORECAST.LINEAR(RIGHT(Y$6,2), $J108:$U108, VALUE(RIGHT($J$6:$U$6,2))), 0)} | Z108: {=IFERROR(_xlfn.FORECAST.LINEAR(RIGHT(Z$6,2), $J108:$U108, VALUE(RIGHT($J$6:$U$6,2))), 0)} | AA108: {=IFERROR(_xlfn.FORECAST.LINEAR(RIGHT(AA$6,2), $J108:$U108, VALUE(RIGHT($J$6:$U$6,2))), 0)} | AB108: {=IFERROR(_xlfn.FORECAST.LINEAR(RIGHT(AB$6,2), $J108:$U108, VALUE(RIGHT($J$6:$U$6,2))), 0)} | AC108: {=IFERROR(_xlfn.FORECAST.LINEAR(RIGHT(AC$6,2), $J108:$U108, VALUE(RIGHT($J$6:$U$6,2))), 0)} | AD108: {=IFERROR(_xlfn.FORECAST.LINEAR(RIGHT(AD$6,2), $J108:$U108, VALUE(RIGHT($J$6:$U$6,2))), 0)} | AE108: {=IFERROR(_xlfn.FORECAST.LINEAR(RIGHT(AE$6,2), $J108:$U108, VALUE(RIGHT($J$6:$U$6,2))), 0)} | AF108: {=IFERROR(_xlfn.FORECAST.LINEAR(RIGHT(AF$6,2), $J108:$U108, VALUE(RIGHT($J$6:$U$6,2))), 0)} | ... AH108: {=IFERROR(_xlfn.FORECAST.LINEAR(RIGHT(AH$6,2), $J108:$U108, VALUE(RIGHT($J$6:$U$6,2))), 0)}
D109: Other Non-Retail | Y109: {=IFERROR(_xlfn.FORECAST.LINEAR(RIGHT(Y$6,2), $J109:$U109, VALUE(RIGHT($J$6:$U$6,2))), 0)} | Z109: {=IFERROR(_xlfn.FORECAST.LINEAR(RIGHT(Z$6,2), $J109:$U109, VALUE(RIGHT($J$6:$U$6,2))), 0)} | AA109: {=IFERROR(_xlfn.FORECAST.LINEAR(RIGHT(AA$6,2), $J109:$U109, VALUE(RIGHT($J$6:$U$6,2))), 0)} | AB109: {=IFERROR(_xlfn.FORECAST.LINEAR(RIGHT(AB$6,2), $J109:$U109, VALUE(RIGHT($J$6:$U$6,2))), 0)} | AC109: {=IFERROR(_xlfn.FORECAST.LINEAR(RIGHT(AC$6,2), $J109:$U109, VALUE(RIGHT($J$6:$U$6,2))), 0)} | AD109: {=IFERROR(_xlfn.FORECAST.LINEAR(RIGHT(AD$6,2), $J109:$U109, VALUE(RIGHT($J$6:$U$6,2))), 0)} | AE109: {=IFERROR(_xlfn.FORECAST.LINEAR(RIGHT(AE$6,2), $J109:$U109, VALUE(RIGHT($J$6:$U$6,2))), 0)} | AF109: {=IFERROR(_xlfn.FORECAST.LINEAR(RIGHT(AF$6,2), $J109:$U109, VALUE(RIGHT($J$6:$U$6,2))), 0)} | ... AH109: {=IFERROR(_xlfn.FORECAST.LINEAR(RIGHT(AH$6,2), $J109:$U109, VALUE(RIGHT($J$6:$U$6,2))), 0)}
C110: Total Loans / AUM | Y110: {=IFERROR(_xlfn.FORECAST.LINEAR(RIGHT(Y$6,2), $J110:$U110, VALUE(RIGHT($J$6:$U$6,2))), 0)} | Z110: {=IFERROR(_xlfn.FORECAST.LINEAR(RIGHT(Z$6,2), $J110:$U110, VALUE(RIGHT($J$6:$U$6,2))), 0)} | AA110: {=IFERROR(_xlfn.FORECAST.LINEAR(RIGHT(AA$6,2), $J110:$U110, VALUE(RIGHT($J$6:$U$6,2))), 0)} | AB110: {=IFERROR(_xlfn.FORECAST.LINEAR(RIGHT(AB$6,2), $J110:$U110, VALUE(RIGHT($J$6:$U$6,2))), 0)} | AC110: {=IFERROR(_xlfn.FORECAST.LINEAR(RIGHT(AC$6,2), $J110:$U110, VALUE(RIGHT($J$6:$U$6,2))), 0)} | AD110: {=IFERROR(_xlfn.FORECAST.LINEAR(RIGHT(AD$6,2), $J110:$U110, VALUE(RIGHT($J$6:$U$6,2))), 0)} | AE110: {=IFERROR(_xlfn.FORECAST.LINEAR(RIGHT(AE$6,2), $J110:$U110, VALUE(RIGHT($J$6:$U$6,2))), 0)} | AF110: {=IFERROR(_xlfn.FORECAST.LINEAR(RIGHT(AF$6,2), $J110:$U110, VALUE(RIGHT($J$6:$U$6,2))), 0)} | ... AH110: {=IFERROR(_xlfn.FORECAST.LINEAR(RIGHT(AH$6,2), $J110:$U110, VALUE(RIGHT($J$6:$U$6,2))), 0)}
C112: Contribution
C113: Total Retail | J113: =IFERROR(J93/J$110, 0) | K113: =IFERROR(K93/K$110, 0) | L113: =IFERROR(L93/L$110, 0) | M113: =IFERROR(M93/M$110, 0) | N113: =IFERROR(N93/N$110, 0) | O113: =IFERROR(O93/O$110, 0) | P113: =IFERROR(P93/P$110, 0) | Q113: =IFERROR(Q93/Q$110, 0) | ... U113: =IFERROR(U93/U$110, 0)
D114: Home Loan / Mortgage / LAP | J114: =IFERROR((J94+J95)/J$110, 0) | K114: =IFERROR((K94+K95)/K$110, 0) | L114: =IFERROR((L94+L95)/L$110, 0) | M114: =IFERROR((M94+M95)/M$110, 0) | N114: =IFERROR((N94+N95)/N$110, 0) | O114: =IFERROR((O94+O95)/O$110, 0) | P114: =IFERROR((P94+P95)/P$110, 0) | Q114: =IFERROR((Q94+Q95)/Q$110, 0) | ... U114: =IFERROR((U94+U95)/U$110, 0)
D115: Auto / Vehicle Loan | J115: =IFERROR(J96/J$110, 0) | K115: =IFERROR(K96/K$110, 0) | L115: =IFERROR(L96/L$110, 0) | M115: =IFERROR(M96/M$110, 0) | N115: =IFERROR(N96/N$110, 0) | O115: =IFERROR(O96/O$110, 0) | P115: =IFERROR(P96/P$110, 0) | Q115: =IFERROR(Q96/Q$110, 0) | ... U115: =IFERROR(U96/U$110, 0)
D116: Gold Loans | J116: =IFERROR(J97/J$110, 0) | K116: =IFERROR(K97/K$110, 0) | L116: =IFERROR(L97/L$110, 0) | M116: =IFERROR(M97/M$110, 0) | N116: =IFERROR(N97/N$110, 0) | O116: =IFERROR(O97/O$110, 0) | P116: =IFERROR(P97/P$110, 0) | Q116: =IFERROR(Q97/Q$110, 0) | ... U116: =IFERROR(U97/U$110, 0)
D117: Personal Loans | J117: =IFERROR(J99/J$110, 0) | K117: =IFERROR(K99/K$110, 0) | L117: =IFERROR(L99/L$110, 0) | M117: =IFERROR(M99/M$110, 0) | N117: =IFERROR(N99/N$110, 0) | O117: =IFERROR(O99/O$110, 0) | P117: =IFERROR(P99/P$110, 0) | Q117: =IFERROR(Q99/Q$110, 0) | ... U117: =IFERROR(U99/U$110, 0)
D118: Credit Card / Payment Products | J118: =IFERROR(J100/J$110, 0) | K118: =IFERROR(K100/K$110, 0) | L118: =IFERROR(L100/L$110, 0) | M118: =IFERROR(M100/M$110, 0) | N118: =IFERROR(N100/N$110, 0) | O118: =IFERROR(O100/O$110, 0) | P118: =IFERROR(P100/P$110, 0) | Q118: =IFERROR(Q100/Q$110, 0) | ... U118: =IFERROR(U100/U$110, 0)
C119: Agri Loan | J119: =IFERROR(J102/J$110, 0) | K119: =IFERROR(K102/K$110, 0) | L119: =IFERROR(L102/L$110, 0) | M119: =IFERROR(M102/M$110, 0) | N119: =IFERROR(N102/N$110, 0) | O119: =IFERROR(O102/O$110, 0) | P119: =IFERROR(P102/P$110, 0) | Q119: =IFERROR(Q102/Q$110, 0) | ... U119: =IFERROR(U102/U$110, 0)
C120: Corporate Total | J120: =IFERROR(J103/J$110, 0) | K120: =IFERROR(K103/K$110, 0) | L120: =IFERROR(L103/L$110, 0) | M120: =IFERROR(M103/M$110, 0) | N120: =IFERROR(N103/N$110, 0) | O120: =IFERROR(O103/O$110, 0) | P120: =IFERROR(P103/P$110, 0) | Q120: =IFERROR(Q103/Q$110, 0) | ... U120: =IFERROR(U103/U$110, 0)
C122: Growth
C123: Total Retail | K123: =IFERROR(K93/J93-1, 0) | L123: =IFERROR(L93/K93-1, 0) | M123: =IFERROR(M93/L93-1, 0) | N123: =IFERROR(N93/M93-1, 0) | O123: =IFERROR(O93/N93-1, 0) | P123: =IFERROR(P93/O93-1, 0) | Q123: =IFERROR(Q93/P93-1, 0) | R123: =IFERROR(R93/Q93-1, 0) | ... U123: =IFERROR(U93/T93-1, 0)
D124: Home Loan / Mortgage / LAP | K124: =IFERROR(K94/J94-1, 0) | L124: =IFERROR(L94/K94-1, 0) | M124: =IFERROR(M94/L94-1, 0) | N124: =IFERROR(N94/M94-1, 0) | O124: =IFERROR(O94/N94-1, 0) | P124: =IFERROR(P94/O94-1, 0) | Q124: =IFERROR(Q94/P94-1, 0) | R124: =IFERROR(R94/Q94-1, 0) | ... U124: =IFERROR(U94/T94-1, 0)
C125: Agri Loan | K125: =IFERROR(K102/J102-1, 0) | L125: =IFERROR(L102/K102-1, 0) | M125: =IFERROR(M102/L102-1, 0) | N125: =IFERROR(N102/M102-1, 0) | O125: =IFERROR(O102/N102-1, 0) | P125: =IFERROR(P102/O102-1, 0) | Q125: =IFERROR(Q102/P102-1, 0) | R125: =IFERROR(R102/Q102-1, 0) | ... U125: =IFERROR(U102/T102-1, 0)
C126: Corporate Total | K126: =IFERROR(K103/J103-1, 0) | L126: =IFERROR(L103/K103-1, 0) | M126: =IFERROR(M103/L103-1, 0) | N126: =IFERROR(N103/M103-1, 0) | O126: =IFERROR(O103/N103-1, 0) | P126: =IFERROR(P103/O103-1, 0) | Q126: =IFERROR(Q103/P103-1, 0) | R126: =IFERROR(R103/Q103-1, 0) | ... U126: =IFERROR(U103/T103-1, 0)
U129: =$U$2
B130: ='Assumptions&Scenario'!$K$10
B131: Quarterly Income Expense History | Y131: Quarterly Income Expense Forecast
J132: 1 | K132: 2 | L132: 3 | M132: 4 | N132: 5 | O132: 6 | P132: 7 | Q132: 8 | R132: 9 | S132: 10 | T132: 11 | U132: 12 | Y132: 13 | Z132: 14 | AA132: 15 | AB132: 16 | AC132: 17 | AD132: 18 | AE132: 19 | AF132: 20 | AG132: 21 | AH132: 22
C133: Quarters | J133: ="FY"&TEXT(MID(K133,3,2)-IF(RIGHT(K133,1)="1",1,0),"00")&"Q"&CHOOSE(RIGHT(K133,1)+0,4,1,2,3) | K133: ="FY"&TEXT(MID(L133,3,2)-IF(RIGHT(L133,1)="1",1,0),"00")&"Q"&CHOOSE(RIGHT(L133,1)+0,4,1,2,3) | L133: ="FY"&TEXT(MID(M133,3,2)-IF(RIGHT(M133,1)="1",1,0),"00")&"Q"&CHOOSE(RIGHT(M133,1)+0,4,1,2,3) | M133: ="FY"&TEXT(MID(N133,3,2)-IF(RIGHT(N133,1)="1",1,0),"00")&"Q"&CHOOSE(RIGHT(N133,1)+0,4,1,2,3) | N133: ="FY"&TEXT(MID(O133,3,2)-IF(RIGHT(O133,1)="1",1,0),"00")&"Q"&CHOOSE(RIGHT(O133,1)+0,4,1,2,3) | O133: ="FY"&TEXT(MID(P133,3,2)-IF(RIGHT(P133,1)="1",1,0),"00")&"Q"&CHOOSE(RIGHT(P133,1)+0,4,1,2,3) | P133: ="FY"&TEXT(MID(Q133,3,2)-IF(RIGHT(Q133,1)="1",1,0),"00")&"Q"&CHOOSE(RIGHT(Q133,1)+0,4,1,2,3) | Q133: ="FY"&TEXT(MID(R133,3,2)-IF(RIGHT(R133,1)="1",1,0),"00")&"Q"&CHOOSE(RIGHT(R133,1)+0,4,1,2,3) | ... T133: ="FY"&TEXT(MID(U133,3,2)-IF(RIGHT(U133,1)="1",1,0),"00")&"Q"&CHOOSE(RIGHT(U133,1)+0,4,1,2,3) | U133: ="FY"&TEXT(YEAR('Data Sheet'!$K$41)+(MONTH('Data Sheet'!$K$41)>3)-2000,"00")&"Q"&INT((MOD(MONTH('Data Sheet'!$K$41)-4,12))/3)+1 | Y133: =Model!$N$31 | Z133: ="FY"&TEXT(MID(Y133,3,2)+IF(RIGHT(Y133,1)="4",1,0),"00")&"Q"&MOD(RIGHT(Y133,1),4)+1 | AA133: ="FY"&TEXT(MID(Z133,3,2)+IF(RIGHT(Z133,1)="4",1,0),"00")&"Q"&MOD(RIGHT(Z133,1),4)+1 | AB133: ="FY"&TEXT(MID(AA133,3,2)+IF(RIGHT(AA133,1)="4",1,0),"00")&"Q"&MOD(RIGHT(AA133,1),4)+1 | AC133: ="FY"&TEXT(MID(AB133,3,2)+IF(RIGHT(AB133,1)="4",1,0),"00")&"Q"&MOD(RIGHT(AB133,1),4)+1 | AD133: ="FY"&TEXT(MID(AC133,3,2)+IF(RIGHT(AC133,1)="4",1,0),"00")&"Q"&MOD(RIGHT(AC133,1),4)+1 | AE133: ="FY"&TEXT(MID(AD133,3,2)+IF(RIGHT(AD133,1)="4",1,0),"00")&"Q"&MOD(RIGHT(AD133,1),4)+1 | AF133: ="FY"&TEXT(MID(AE133,3,2)+IF(RIGHT(AE133,1)="4",1,0),"00")&"Q"&MOD(RIGHT(AE133,1),4)+1 | AG133: ="FY"&TEXT(MID(AF133,3,2)+IF(RIGHT(AF133,1)="4",1,0),"00")&"Q"&MOD(RIGHT(AF133,1),4)+1 | AH133: ="FY"&TEXT(MID(AG133,3,2)+IF(RIGHT(AG133,1)="4",1,0),"00")&"Q"&MOD(RIGHT(AG133,1),4)+1
C137: Interest Income | H137: =$H$10 | Y137: =IFERROR(_xlfn.FORECAST.LINEAR(Y$132, $J137:$U137, $J$132:$U$132), 0) | Z137: =IFERROR(_xlfn.FORECAST.LINEAR(Z$132, $J137:$U137, $J$132:$U$132), 0) | AA137: =IFERROR(_xlfn.FORECAST.LINEAR(AA$132, $J137:$U137, $J$132:$U$132), 0) | AB137: =IFERROR(_xlfn.FORECAST.LINEAR(AB$132, $J137:$U137, $J$132:$U$132), 0) | AC137: =IFERROR(_xlfn.FORECAST.LINEAR(AC$132, $J137:$U137, $J$132:$U$132), 0) | AD137: =IFERROR(_xlfn.FORECAST.LINEAR(AD$132, $J137:$U137, $J$132:$U$132), 0) | AE137: =IFERROR(_xlfn.FORECAST.LINEAR(AE$132, $J137:$U137, $J$132:$U$132), 0) | AF137: =IFERROR(_xlfn.FORECAST.LINEAR(AF$132, $J137:$U137, $J$132:$U$132), 0) | ... AH137: =IFERROR(_xlfn.FORECAST.LINEAR(AH$132, $J137:$U137, $J$132:$U$132), 0)
C138: Interest Expenses | Y138: =IFERROR(_xlfn.FORECAST.LINEAR(Y$132, $J138:$U138, $J$132:$U$132), 0) | Z138: =IFERROR(_xlfn.FORECAST.LINEAR(Z$132, $J138:$U138, $J$132:$U$132), 0) | AA138: =IFERROR(_xlfn.FORECAST.LINEAR(AA$132, $J138:$U138, $J$132:$U$132), 0) | AB138: =IFERROR(_xlfn.FORECAST.LINEAR(AB$132, $J138:$U138, $J$132:$U$132), 0) | AC138: =IFERROR(_xlfn.FORECAST.LINEAR(AC$132, $J138:$U138, $J$132:$U$132), 0) | AD138: =IFERROR(_xlfn.FORECAST.LINEAR(AD$132, $J138:$U138, $J$132:$U$132), 0) | AE138: =IFERROR(_xlfn.FORECAST.LINEAR(AE$132, $J138:$U138, $J$132:$U$132), 0) | AF138: =IFERROR(_xlfn.FORECAST.LINEAR(AF$132, $J138:$U138, $J$132:$U$132), 0) | ... AH138: =IFERROR(_xlfn.FORECAST.LINEAR(AH$132, $J138:$U138, $J$132:$U$132), 0)
C139: Net Interest Income | Y139: =IFERROR(_xlfn.FORECAST.LINEAR(Y$132, $J139:$U139, $J$132:$U$132), 0) | Z139: =IFERROR(_xlfn.FORECAST.LINEAR(Z$132, $J139:$U139, $J$132:$U$132), 0) | AA139: =IFERROR(_xlfn.FORECAST.LINEAR(AA$132, $J139:$U139, $J$132:$U$132), 0) | AB139: =IFERROR(_xlfn.FORECAST.LINEAR(AB$132, $J139:$U139, $J$132:$U$132), 0) | AC139: =IFERROR(_xlfn.FORECAST.LINEAR(AC$132, $J139:$U139, $J$132:$U$132), 0) | AD139: =IFERROR(_xlfn.FORECAST.LINEAR(AD$132, $J139:$U139, $J$132:$U$132), 0) | AE139: =IFERROR(_xlfn.FORECAST.LINEAR(AE$132, $J139:$U139, $J$132:$U$132), 0) | AF139: =IFERROR(_xlfn.FORECAST.LINEAR(AF$132, $J139:$U139, $J$132:$U$132), 0) | ... AH139: =IFERROR(_xlfn.FORECAST.LINEAR(AH$132, $J139:$U139, $J$132:$U$132), 0)
...

Sheet Analysts&Consensus
B3: ='Assumptions&Scenario'!$K$10
B4: Concensus Expecations
X5: Target Price | AA5: Revenue Growth | AD5: EPS Growth
G6: Date | H6: FIN Yr | I6: TP(Avg) | J6: TP(Min) | K6: TP(Max) | L6: Rev.(Avg) | M6: Rev.(Min) | N6: Rev.(Max) | O6: EPS(Avg) | P6: EPS(Min) | Q6: EPS(Max) | R6: #Count | X6: Avg. Up | Y6: Min Up | Z6: Max Up | AA6: Avg. Up | AB6: Min Up | AC6: Max Up | AD6: Avg. Up | AE6: Min Up | AF6: Max Up
X10: =IFERROR(I10/'Assumptions&Scenario'!U41-1, 0) | Y10: =IFERROR(J10/'Assumptions&Scenario'!U41-1, 0) | Z10: =IFERROR(K10/'Assumptions&Scenario'!U41-1, 0) | AA10: =IFERROR(L10/Model!K176-1, 0) | AB10: =IFERROR(M10/Model!K176-1, 0) | AC10: =IFERROR(N10/Model!K176-1, 0) | AD10: =IFERROR(O10/Model!K203-1, 0) | AE10: =IFERROR(P10/Model!K203-1, 0) | AF10: =IFERROR(Q10/Model!K203-1, 0)
AA11: =IFERROR(L11/L10-1, 0) | AB11: =IFERROR(M11/M10-1, 0) | AC11: =IFERROR(N11/N10-1, 0) | AD11: =IFERROR(O11/O10-1, 0) | AE11: =IFERROR(P11/P10-1, 0) | AF11: =IFERROR(Q11/Q10-1, 0)
B54: ='Assumptions&Scenario'!$K$10
B55: Analysts Expecations
C57: Type | D57: Quarter | E57: Date | F57: Mcap(Cr) | G57: Price | H57: Firm | I57: Reco | J57: TP | K57: Fwd PE | L57: FIN Yr | M57: EPS | N57: Rev. | O57: EBIT% | P57: Profit | Q57: A1 | R57: A2 | S57: A3 | T57: Lead Analyst

Sheet Customization
A1: How to use it?
A3: You can customize this workbook as you want.
B4: You can add custom formating, add conditional formating, add your own formulas… do ANYTHING.
B5: Please don't edit the "Data Sheet" only.
A7: After customization, you can upload this back on Screener.
B8: Upload on: | C8: https://www.screener.in/excel/
A10: Download your customized workbooks now onwards.
B11: Now whenever you will "Export to excel" from Screener, it will export your customized file.
A14: TESTING:
B15: This is a testing feature currently.
B16: You can report any formula errors on the worksheet at: support@screener.in

Sheet Data Sheet
A1: COMPANY NAME | B1: TATA CONSULTANCY SERVICES LTD | E1: =IF(B2<>B3, "A NEW VERSION OF THE WORKSHEET IS AVAILABLE", "")
A2: LATEST VERSION | B2: 2.1 | E2: PLEASE DO NOT MAKE ANY CHANGES TO THIS SHEET
A3: CURRENT VERSION | B3: 2.1
A5: META
A6: Number of shares | B6: =IF(B9>0, B9/B8, 0)
A7: Face Value | B7: 1
A8: Current Price | B8: 2384.25
A9: Market Capitalization | B9: 862642.48
A15: PROFIT & LOSS
A16: Report Date | B16: 42460 | C16: 42825 | D16: 43190 | E16: 43555 | F16: 43921 | G16: 44286 | H16: 44651 | I16: 45016 | J16: 45382 | K16: 45747
A17: Sales | B17: 108646 | C17: 117966 | D17: 123104 | E17: 146463 | F17: 156949 | G17: 164177 | H17: 191754 | I17: 225458 | J17: 240893 | K17: 255324
A18: Raw Material Cost | C18: 94 | D18: 86 | E18: 40 | F18: 18 | G18: 14 | H18: 29 | I18: 37 | J18: 42 | K18: 49
A19: Change in Inventory | C19: 1
A20: Power and Fuel
A21: Other Mfr. Exp | B21: 2571 | C21: 2715 | D21: 2614 | E21: 2230 | F21: 1887 | G21: 1448 | H21: 1134 | I21: 1844 | J21: 3660 | K21: 11599
A22: Employee Cost | B22: 55348 | C22: 61621 | D22: 66396 | E22: 78246 | F22: 85952 | G22: 91814 | H22: 107554 | I22: 127522 | J22: 140131 | K22: 145788
A23: Selling and admin | B23: 15589 | C23: 16392 | D23: 16808 | E23: 20387 | F23: 20527 | G23: 18322 | H23: 23187 | I23: 28913 | J23: 24151 | K23: 20729
A24: Other Expenses | B24: 4461 | C24: 4834 | D24: 4684 | E24: 6054 | F24: 6456 | G24: 6033 | H24: 6793 | I24: 7883 | J24: 8613 | K24: 9752
A25: Other Income | B25: 3084 | C25: 4221 | D25: 3642 | E25: 4311 | F25: 4592 | G25: 1916 | H25: 4018 | I25: 3449 | J25: 3464 | K25: 3962
A26: Depreciation | B26: 1888 | C26: 1987 | D26: 2014 | E26: 2056 | F26: 3529 | G26: 4065 | H26: 4604 | I26: 5022 | J26: 4985 | K26: 5242
A27: Interest | B27: 33 | C27: 32 | D27: 52 | E27: 198 | F27: 924 | G27: 637 | H27: 784 | I27: 779 | J27: 778 | K27: 796
A28: Profit before tax | B28: 31840 | C28: 34513 | D28: 34092 | E28: 41563 | F28: 42248 | G28: 43760 | H28: 51687 | I28: 56907 | J28: 61997 | K28: 65331
A29: Tax | B29: 7502 | C29: 8156 | D29: 8212 | E29: 10001 | F29: 9801 | G29: 11198 | H29: 13238 | I29: 14604 | J29: 15898 | K29: 16534
A30: Net profit | B30: 24270 | C30: 26289 | D30: 25826 | E30: 31472 | F30: 32340 | G30: 32430 | H30: 38327 | I30: 42147 | J30: 45908 | K30: 48553
A31: Dividend Amount | B31: 8569.5 | C31: 9259 | D31: 9550 | E31: 11250 | F31: 27375 | G31: 14060 | H31: 15738 | I31: 42090 | J31: 26426 | K31: 45612
A40: Quarters
A41: Report Date | B41: 45199 | C41: 45291 | D41: 45382 | E41: 45473 | F41: 45565 | G41: 45657 | H41: 45747 | I41: 45838 | J41: 45930 | K41: 46022
A42: Sales | B42: 59692 | C42: 60583 | D42: 61237 | E42: 62613 | F42: 64259 | G42: 63973 | H42: 64479 | I42: 63437 | J42: 65799 | K42: 67087
A43: Expenses | B43: 43946 | C43: 44195 | D43: 44073 | E43: 45951 | F43: 47528 | G43: 46939 | H43: 47499 | I43: 46562 | J43: 47821 | K43: 48818
A44: Other Income | B44: 1006 | C44: -96 | D44: 1157 | E44: 962 | F44: 729 | G44: 1243 | H44: 1028 | I44: 1660 | J44: -268 | K44: -2273
A45: Depreciation | B45: 1263 | C45: 1233 | D45: 1246 | E45: 1220 | F45: 1266 | G45: 1377 | H45: 1379 | I45: 1361 | J45: 1413 | K45: 1380
A46: Interest | B46: 159 | C46: 230 | D46: 226 | E46: 173 | F46: 162 | G46: 234 | H46: 227 | I46: 195 | J46: 229 | K46: 538
A47: Profit before tax | B47: 15330 | C47: 14829 | D47: 16849 | E47: 16231 | F47: 16032 | G47: 16666 | H47: 16402 | I47: 16979 | J47: 16068 | K47: 14078
A48: Tax | B48: 3950 | C48: 3732 | D48: 4347 | E48: 4126 | F48: 4077 | G48: 4222 | H48: 4109 | I48: 4160 | J48: 3937 | K48: 3358
A49: Net profit | B49: 11342 | C49: 11058 | D49: 12434 | E49: 12040 | F49: 11909 | G49: 12380 | H49: 12224 | I49: 12760 | J49: 12075 | K49: 10657
A50: Operating Profit | B50: 15746 | C50: 16388 | D50: 17164 | E50: 16662 | F50: 16731 | G50: 17034 | H50: 16980 | I50: 16875 | J50: 17978 | K50: 18269
A55: BALANCE SHEET
A56: Report Date | B56: 42460 | C56: 42825 | D56: 43190 | E56: 43555 | F56: 43921 | G56: 44286 | H56: 44651 | I56: 45016 | J56: 45382 | K56: 45747
A57: Equity Share Capital | B57: 197 | C57: 197 | D57: 191 | E57: 375 | F57: 375 | G57: 370 | H57: 366 | I57: 366 | J57: 362 | K57: 362
A58: Reserves | B58: 70875 | C58: 86017 | D58: 84937 | E58: 89071 | F58: 83751 | G58: 86063 | H58: 88773 | I58: 90058 | J58: 90127 | K58: 94394
A59: Borrowings | B59: 245 | C59: 289 | D59: 247 | E59: 62 | F59: 8174 | G59: 7795 | H59: 7818 | I59: 7688 | J59: 8021 | K59: 9392
A60: Other Liabilities | B60: 16974 | C60: 15830 | D60: 19751 | E60: 24393 | F60: 27827 | G60: 35764 | H60: 43967 | I60: 44747 | J60: 46962 | K60: 54501
A61: Total | B61: 88291 | C61: 102333 | D61: 105126 | E61: 113901 | F61: 120127 | G61: 129992 | H61: 140924 | I61: 142859 | J61: 145472 | K61: 158649
A62: Net Block | B62: 11774 | C62: 11701 | D62: 11973 | E62: 12290 | F62: 20928 | G62: 21021 | H62: 21298 | I62: 20515 | J62: 19604 | K62: 23053
A63: Capital Work in Progress | B63: 1670 | C63: 1541 | D63: 1278 | E63: 963 | F63: 906 | G63: 926 | H63: 1205 | I63: 1234 | J63: 1564 | K63: 1546
A64: Investments | B64: 22822 | C64: 41980 | D64: 36008 | E64: 29330 | F64: 26356 | G64: 29373 | H64: 30485 | I64: 37163 | J64: 31762 | K64: 30964
A65: Other Assets | B65: 52025 | C65: 47111 | D65: 55867 | E65: 71318 | F65: 71937 | G65: 78672 | H65: 87936 | I65: 83947 | J65: 92542 | K65: 103086
A66: Total | B66: 88291 | C66: 102333 | D66: 105126 | E66: 113901 | F66: 120127 | G66: 129992 | H66: 140924 | I66: 142859 | J66: 145472 | K66: 158649
A67: Receivables | B67: 24073 | C67: 22617 | D67: 24943 | E67: 27346 | F67: 30532 | G67: 30079 | H67: 41810 | I67: 49954 | J67: 53577 | K67: 59046
... A70: No. of Equity Shares | B70: 1970427941 | C70: 1970427941 | D70: 1914287591 | E70: 3752384706 | F70: 3752384706 | G70: 3699051373 | H70: 3659051373 | I70: 3659051373 | J70: 3618087518 | K70: 3618087518
A71: New Bonus Shares
A72: Face value | B72: 1 | C72: 1 | D72: 1 | E72: 1 | F72: 1 | G72: 1 | H72: 1 | I72: 1 | J72: 1 | K72: 1
A80: CASH FLOW:
A81: Report Date | B81: 42460 | C81: 42825 | D81: 43190 | E81: 43555 | F81: 43921 | G81: 44286 | H81: 44651 | I81: 45016 | J81: 45382 | K81: 45747
A82: Cash from Operating Activity | B82: 19109 | C82: 25223 | D82: 25067 | E82: 28593 | F82: 32369 | G82: 38802 | H82: 39949 | I82: 41965 | J82: 44338 | K82: 48908
A83: Cash from Investing Activity | B83: -5010 | C83: -16895 | D83: 3104 | E83: 1645 | F83: 8968 | G83: -7956 | H83: -738 | I83: 548 | J83: 6091 | K83: -2144
A84: Cash from Financing Activity | B84: -9666 | C84: -11026 | D84: -26885 | E84: -27897 | F84: -39915 | G84: -32634 | H84: -33581 | I84: -47878 | J84: -48536 | K84: -47438
A85: Net Cash Flow | B85: 4433 | C85: -2698 | D85: 1286 | E85: 2341 | F85: 1422 | G85: -1788 | H85: 5630 | I85: -5365 | J85: 1893 | K85: -674
A90: PRICE: | B90: 1260.15 | C90: 1215.9 | D90: 1424.58 | E90: 2001.65 | F90: 1826.1 | G90: 3177.85 | H90: 3739.95 | I90: 3205.9 | J90: 3876.3 | K90: 3606.15
A92: DERIVED:
A93: Adjusted Equity Shares in Cr | B93: 394.09 | C93: 394.09 | D93: 382.86 | E93: 375.24 | F93: 375.24 | G93: 369.91 | H93: 365.91 | I93: 365.91 | J93: 361.81 | K93: 361.81
